Workbook

Sheet Legend
A1: Bulwark — Map Data Workbook
A2: Companion to Bulwark-Map-GDD.md. Every number here is a design lever; the GDD explains why.
A5: HOW TO USE THIS WORKBOOK
A6: Blue text | B6: Hardcoded input — this is a knob you turn.
A7: Black text | B7: Formula — derived. Do not overwrite.
A8: Green text | B8: Pulls from another sheet.
A9: Yellow fill | B9: Key assumption. Flagged because it was invented, not specified.
A11: EDIT THESE SHEETS
A12: Global_Params | B12: Master tunables. Everything downstream recalculates from here.
A13: Growth_Curve | B13: The 8-wave ring expansion shape. The single most important curve in the design.
A14: Maps | B14: The 9-map sequence: dimensions, primary resource, difficulty.
A15: Factions | B15: The 9 factions: premium resource, harvester yield.
A16: Resources | B16: Value, node yield, respawn rules per resource type.
A17: Harvester_Upgrades | B17: Between-match progression.
A18: Star_Rubric | B18: The 5 wave-star conditions and their thresholds.
A20: DERIVED — DO NOT HAND-EDIT
A21: Wave_Table | B21: 72 rows (9 maps x 8 waves). The build target. Every field is a formula.
A22: Score_Model | B22: Worked example of the map score and the 3.0-star gate.
A24: OPEN ASSUMPTIONS (yellow cells)
A25: Map + faction names | B25: Placeholders. Real names live in Bulwark GDD v2.0 — swap them in.
A26: Map dimensions 2-8 | B26: Only the small (24x16) and large (64x32) maps were specified. Maps 2-8 are interpolated.
A27: All balance numbers | B27: First-pass. They exist so the curve is playable, not because they are right.

Sheet Global_Params
A1: Global Parameters
A2: Master knobs. Wave_Table and Score_Model read from here.
A4: Param | B4: Value | C4: Unit | D4: Notes
A5: STRUCTURE
A6: Maps_In_Campaign | B6: 9 | C6: count | D6: Fixed sequence, all must be cleared.
A7: Waves_Per_Map | B7: 8 | C7: count | D7: One dialog interaction after each wave.
A8: Star_Gate | B8: 3 | C8: stars | D8: Average wave stars needed to unlock the next map.
A9: Max_Stars_Per_Wave | B9: 5 | C9: stars | D9: See Star_Rubric — 5 independent points.
A10: GRID
A11: Map1_Width | B11: 24 | C11: tiles | D11: Smallest map, as specified.
A12: Map1_Height | B12: 16 | C12: tiles | D12: Smallest map, as specified.
A13: Map9_Width | B13: 64 | C13: tiles | D13: Largest map, as specified.
A14: Map9_Height | B14: 32 | C14: tiles | D14: Largest map, as specified.
A15: SPAWNS
A16: Spawn_Setback | B16: 2 | C16: tiles | D16: Spawn sits this far OUTSIDE the current playable edge.
A17: Base_Spawn_Budget | B17: 100 | C17: pts | D17: Wave 1, map 1 enemy budget. Scales by wave ramp x map difficulty.
A18: Wave_Ramp | B18: 0.18 | C18: per wave | D18: Budget growth per wave within a map.
A19: Air_Share_W1 | B19: 0.1 | C19: fraction | D19: Air share of budget at wave 1.
A20: Air_Share_W8 | B20: 0.3 | C20: fraction | D20: Air share of budget at wave 8. Air pressure ramps.
A21: Water_Share | B21: 0.15 | C21: fraction | D21: Flat. Water lanes only exist on water-bearing maps.
A22: ECONOMY
A23: Gold_Per_Resource | B23: 1 | C23: gold/unit | D23: Conversion at map end.
A24: Time_Bonus_Cap | B24: 400 | C24: gold | D24: Max completion-time bonus on a perfect-tempo run.
A25: Par_Time_Per_100_Tiles | B25: 42 | C25: sec | D25: Par time scales with total playable area.
A26: Premium_Ring_Seed | B26: 3 | C26: nodes | D26: Fresh premium nodes seeded in EACH newly-opened ring.
A27: Primary_Respawn_Sec | B27: 75 | C27: sec | D27: Primary respawns in-match. Premium NEVER does.
A28: Uncollectable_Floor | B28: 0.25 | C28: fraction | D28: Min share of map resource that must remain uncollectable.
A29: QUEST / LOYALTY
A30: Quest_First_Wave | B30: 5 | C30: wave | D30: Quest resource appears only in the LAST 4 WAVES, as the map fans out.
A31: Quest_Edge_Band | B31: 0.8 | C31: fraction | D31: Quest nodes spawn beyond this fraction of the playable radius. Far edge only.
A32: Quest_Jitter_Tiles | B32: 4 | C32: tiles | D32: Random scatter on placement. The player cannot pre-plan the route.
A33: Loyalty_Per_Node | B33: 10 | C33: pts | D33: Loyalty awarded per quest node fully harvested.
A34: Rival_Penalty | B34: 0.5 | C34: fraction | D34: Loyalty gained with a faction is LOST with its rival at this rate.
A35: Tech_T1_Threshold | B35: 100 | C35: loyalty | D35: Unlocks the faction's UNIT.
A36: Tech_T2_Threshold | B36: 260 | C36: loyalty | D36: Unlocks the faction's STRUCTURE.
A37: Tech_T3_Threshold | B37: 520 | C37: loyalty | D37: Unlocks the faction's BASE UPGRADE.
A38: QUEST CONTRACT
A39: Decline_Cost | B39: 30 | C39: loyalty | D39: Lost with the giver when you REFUSE their quest. There is no neutral option.
A40: Decline_Rival_Gain | B40: 0.5 | C40: fraction | D40: Refusing a faction PLEASES its rival, at this share of Decline_Cost.
A41: Fulfil_Threshold | B41: 0.6 | C41: fraction | D41: Harvest at least this share of quest nodes or the contract is FAILED.
A42: Broken_Promise_Penalty | B42: 45 | C42: loyalty | D42: Extra loss for accepting and failing. MUST exceed Decline_Cost.
A46: Yellow = invented first-pass value. Tune in playtest.
A47: Broken_Promise_Penalty MUST be > Decline_Cost, or overpromising is cheaper than refusing and the contract has no weight.

Sheet Growth_Curve
A1: Ring Growth Curve
A2: Linear fraction of the full map that is playable at each wave. Slow-fast-slow: small openings early, the big reveal at waves 4-6, a modest final ring.
A4: Wave | B4: Linear_Fraction | C4: Area_Fraction | D4: Ring_Area_Added | E4: Shape Note
A5: 1 | B5: 0.4 | C5: =B5^2 -> 0.16 | D5: =C5 -> 0.16 | E5: Start pocket. Player can see the walls.
A6: 2 | B6: 0.46 | C6: =B6^2 -> 0.2116 | D6: =C6-C5 -> 0.0516 | E6: Teaser. One new crop, one new spawn angle.
A7: 3 | B7: 0.54 | C7: =B7^2 -> 0.2916 | D7: =C7-C6 -> 0.08 | E7: Primary field opens. Harvester routing starts to matter.
A8: 4 | B8: 0.66 | C8: =B8^2 -> 0.4356 | D8: =C8-C7 -> 0.144 | E8: THE REVEAL. Area nearly doubles. Premium is suddenly far away.
A9: 5 | B9: 0.79 | C9: =B9^2 -> 0.6241 | D9: =C9-C8 -> 0.1885 | E9: Overextension wave. Spawn distance is now real travel time.
A10: 6 | B10: 0.89 | C10: =B10^2 -> 0.7921 | D10: =C10-C9 -> 0.168 | E10: Consolidation. Growth slows, pressure does not.
A11: 7 | B11: 0.96 | C11: =B11^2 -> 0.9216 | D11: =C11-C10 -> 0.1295 | E11: Last sliver. Almost nothing new to grab.
A12: 8 | B12: 1 | C12: =B12^2 -> 1 | D12: =C12-C11 -> 0.0784 | E12: Full map. Final stand, then the map score.
A14: Area_Fraction = Linear_Fraction^2 (both axes scale together, so the map keeps its aspect ratio).
A15: Ring_Area_Added is the design signal: it should peak at wave 4-5. If it is flat, the mid-game is flat.

Sheet Maps
A1: Map Sequence (9 maps, fixed order)
A2: The MAP sets the primary resource. The FACTION sets the premium — see Factions.
A4: Map_ID | B4: Map_Name | C4: Full_W | D4: Full_H | E4: Full_Area | F4: Primary_Resource | G4: Has_Water | H4: Difficulty | I4: Par_Time_Sec | J4: Quest_Giver_Faction | K4: Notes
A5: 1 | B5: Map_01 | C5: =ROUND((Global_Params!$B$11+(Global_Params!$B$13-Global_Params!$B$11)*(A5-1)/(Global_Params!$B$6-1))/2,0)*2 -> 24 | D5: =ROUND((Global_Params!$B$12+(Global_Params!$B$14-Global_Params!$B$12)*(A5-1)/(Global_Params!$B$6-1))/2,0)*2 -> 16 | E5: =C5*D5 -> 384 | F5: Flowers | G5: No | H5: 1 | I5: =ROUND(E5/100*Global_Params!$B$25*8,0) -> 1290 | J5: 3 | K5: Tutorial pressure. Ground only. Teaches the ring.
A6: 2 | B6: Map_02 | C6: =ROUND((Global_Params!$B$11+(Global_Params!$B$13-Global_Params!$B$11)*(A6-1)/(Global_Params!$B$6-1))/2,0)*2 -> 30 | D6: =ROUND((Global_Params!$B$12+(Global_Params!$B$14-Global_Params!$B$12)*(A6-1)/(Global_Params!$B$6-1))/2,0)*2 -> 18 | E6: =C6*D6 -> 540 | F6: Flowers | G6: No | H6: 1.1 | I6: =ROUND(E6/100*Global_Params!$B$25*8,0) -> 1814 | J6: 7 | K6: Air introduced. Same footprint, new axis.
A7: 3 | B7: Map_03 | C7: =ROUND((Global_Params!$B$11+(Global_Params!$B$13-Global_Params!$B$11)*(A7-1)/(Global_Params!$B$6-1))/2,0)*2 -> 34 | D7: =ROUND((Global_Params!$B$12+(Global_Params!$B$14-Global_Params!$B$12)*(A7-1)/(Global_Params!$B$6-1))/2,0)*2 -> 20 | E7: =C7*D7 -> 680 | F7: Minerals | G7: Yes | H7: 1.2 | I7: =ROUND(E7/100*Global_Params!$B$25*8,0) -> 2285 | J7: 1 | K7: Water lanes. Harvester escort becomes a thing.
A8: 4 | B8: Map_04 | C8: =ROUND((Global_Params!$B$11+(Global_Params!$B$13-Global_Params!$B$11)*(A8-1)/(Global_Params!$B$6-1))/2,0)*2 -> 40 | D8: =ROUND((Global_Params!$B$12+(Global_Params!$B$14-Global_Params!$B$12)*(A8-1)/(Global_Params!$B$6-1))/2,0)*2 -> 22 | E8: =C8*D8 -> 880 | F8: Minerals | G8: No | H8: 1.3 | I8: =ROUND(E8/100*Global_Params!$B$25*8,0) -> 2957 | J8: 5 | K8: First mid-size map. The reveal wave lands hard here.
A9: 5 | B9: Map_05 | C9: =ROUND((Global_Params!$B$11+(Global_Params!$B$13-Global_Params!$B$11)*(A9-1)/(Global_Params!$B$6-1))/2,0)*2 -> 44 | D9: =ROUND((Global_Params!$B$12+(Global_Params!$B$14-Global_Params!$B$12)*(A9-1)/(Global_Params!$B$6-1))/2,0)*2 -> 24 | E9: =C9*D9 -> 1056 | F9: Crystals | G9: Yes | H9: 1.4 | I9: =ROUND(E9/100*Global_Params!$B$25*8,0) -> 3548 | J9: 9 | K9: Crystals: high value, slow harvest. Tempo trap.
A10: 6 | B10: Map_06 | C10: =ROUND((Global_Params!$B$11+(Global_Params!$B$13-Global_Params!$B$11)*(A10-1)/(Global_Params!$B$6-1))/2,0)*2 -> 50 | D10: =ROUND((Global_Params!$B$12+(Global_Params!$B$14-Global_Params!$B$12)*(A10-1)/(Global_Params!$B$6-1))/2,0)*2 -> 26 | E10: =C10*D10 -> 1300 | F10: Flowers | G10: Yes | H10: 1.5 | I10: =ROUND(E10/100*Global_Params!$B$25*8,0) -> 4368 | J10: 2 | K10: Three-way spawn pressure.
A11: 7 | B11: Map_07 | C11: =ROUND((Global_Params!$B$11+(Global_Params!$B$13-Global_Params!$B$11)*(A11-1)/(Global_Params!$B$6-1))/2,0)*2 -> 54 | D11: =ROUND((Global_Params!$B$12+(Global_Params!$B$14-Global_Params!$B$12)*(A11-1)/(Global_Params!$B$6-1))/2,0)*2 -> 28 | E11: =C11*D11 -> 1512 | F11: Minerals | G11: No | H11: 1.6 | I11: =ROUND(E11/100*Global_Params!$B$25*8,0) -> 5080 | J11: 8 | K11: Widest ground field. Routing puzzle.
A12: 8 | B12: Map_08 | C12: =ROUND((Global_Params!$B$11+(Global_Params!$B$13-Global_Params!$B$11)*(A12-1)/(Global_Params!$B$6-1))/2,0)*2 -> 60 | D12: =ROUND((Global_Params!$B$12+(Global_Params!$B$14-Global_Params!$B$12)*(A12-1)/(Global_Params!$B$6-1))/2,0)*2 -> 30 | E12: =C12*D12 -> 1800 | F12: Crystals | G12: Yes | H12: 1.7 | I12: =ROUND(E12/100*Global_Params!$B$25*8,0) -> 6048 | J12: 4 | K12: Premium is deliberately stranded far out.
A13: 9 | B13: Map_09 | C13: =ROUND((Global_Params!$B$11+(Global_Params!$B$13-Global_Params!$B$11)*(A13-1)/(Global_Params!$B$6-1))/2,0)*2 -> 64 | D13: =ROUND((Global_Params!$B$12+(Global_Params!$B$14-Global_Params!$B$12)*(A13-1)/(Global_Params!$B$6-1))/2,0)*2 -> 32 | E13: =C13*D13 -> 2048 | F13: Crystals | G13: Yes | H13: 1.8 | I13: =ROUND(E13/100*Global_Params!$B$25*8,0) -> 6881 | J13: 6 | K13: Full 64x32. Everything at once.
A15: Quest_Giver_Faction: whose loyalty the map's quest resource earns. Each map serves a different faction's quest.
A16: Par_Time_Sec is the WHOLE map (8 waves). Difficulty scales spawn budget. Full_W/Full_H interpolated — only maps 1 and 9 specified.

Sheet Factions
A1: Factions (9) — Premium Resource & Harvester Profile
A2: Faction names are placeholders; pull the real nine from Bulwark GDD v2.0.
A4: Faction_ID | B4: Faction_Name | C4: Premium_Resource | D4: Premium_Secondary | E4: Rival_Faction | F4: Yield_Mult | G4: Harvester_Base_Capacity | H4: Harvester_Base_Speed | I4: Harvester_Base_HP | J4: Profile
A5: 1 | B5: Faction_01 | C5: Crystals | D5: Minerals | E5: 2 | F5: 1 | G5: 40 | H5: 3 | I5: 120 | J5: Baseline. The tuning reference.
A6: 2 | B6: Faction_02 | C6: Flowers | D6: Crystals | E6: 1 | F6: 1.15 | G6: 32 | H6: 3.6 | I6: 90 | J6: Fast, fragile. Grabs premium and runs.
A7: 3 | B7: Faction_03 | C7: Minerals | D7: Flowers | E7: 4 | F7: 0.9 | G7: 55 | H7: 2.2 | I7: 170 | J7: Slow tank. Sits in the field and eats hits.
A8: 4 | B8: Faction_04 | C8: Crystals | D8: Flowers | E8: 3 | F8: 1.05 | G8: 38 | H8: 3.2 | I8: 110 | J8: Generalist with a premium bias.
A9: 5 | B9: Faction_05 | C9: Flowers | D9: Minerals | E9: 6 | F9: 1.2 | G9: 28 | H9: 3.8 | I9: 80 | J9: Highest yield, lowest survivability. Greed faction.
A10: 6 | B10: Faction_06 | C10: Minerals | D10: Crystals | E10: 5 | F10: 0.95 | G10: 50 | H10: 2.5 | I10: 155 | J10: Escort-dependent.
A11: 7 | B11: Faction_07 | C11: Crystals | D11: Minerals | E11: 8 | F11: 1.1 | G11: 36 | H11: 3.1 | I11: 115 | J11: Two harvesters, half capacity each (see GDD).
A12: 8 | B12: Faction_08 | C12: Flowers | D12: Crystals | E12: 7 | F12: 1 | G12: 42 | H12: 2.9 | I12: 125 | J12: Balanced.
A13: 9 | B13: Faction_09 | C13: Minerals | D13: Flowers | E13: none | F13: 0.85 | G13: 60 | H13: 2 | I13: 190 | J13: UNALIGNED. No rival — the diplomat. Can court everyone.
A15: CLASH FIX: if a faction's premium == the map's primary, the premium SWAPS to Premium_Secondary.
A16: Premium_Secondary must never equal Premium_Resource. That single constraint guarantees the swap never re-collides,
A17: which guarantees all THREE resource types are always in play with three distinct roles. See Resource_Roles.
A18: RIVALS are reciprocal pairs: (1,2) (3,4) (5,6) (7,8). Faction 09 is unaligned and has no rival.
A19: An odd faction count means someone has to be the diplomat. Use it — 09 is the only faction that can max every tech tree.

Sheet Resources
A1: Resource Types
A2: Two tiers per map: the map's primary, and the faction's premium.
A4: Resource | B4: Tier | C4: Value_Per_Unit | D4: Units_Per_Node | E4: Harvest_Sec_Per_Node | F4: Respawns_In_Match | G4: Respawn_Sec | H4: Notes
A5: Flowers | B5: Primary | C5: 4 | D5: 25 | E5: 6 | F5: Yes | G5: =Global_Params!$B$26 -> 3 | H5: Cheap, fast, everywhere. The safe income.
A6: Minerals | B6: Primary | C6: 6 | D6: 20 | E6: 9 | F6: Yes | G6: =Global_Params!$B$26 -> 3 | H6: Slower to pull, better per node.
A7: Crystals | B7: Primary | C7: 9 | D7: 14 | E7: 14 | F7: Yes | G7: =Global_Params!$B$26*1.4 -> 4.2 | H7: Tempo trap: high value, brutal harvest time.
A8: Flowers | B8: Premium | C8: 14 | D8: 18 | E8: 9 | F8: No | G8: n/a | H8: Premium NEVER respawns. Seeded fresh per ring only.
A9: Minerals | B9: Premium | C9: 20 | D9: 15 | E9: 13 | F9: No | G9: n/a | H9: Premium NEVER respawns. Seeded fresh per ring only.
A10: Crystals | B10: Premium | C10: 30 | D10: 10 | E10: 20 | F10: No | G10: n/a | H10: The greed prize. Deep in the new ring, every time.
A12: Premium/Primary value ratio is ~3.3x. That ratio IS the greed dial — raise it and players overextend.

Sheet Harvester_Upgrades
A1: Harvester Upgrades (between matches)
A2: Bought with gold from the map score.
A4: Level | B4: Gold_Cost | C4: Cumulative_Gold | D4: Capacity_Mult | E4: Speed_Mult | F4: HP_Mult | G4: Unlock | H4: Notes
A5: 1 | B5: 0 | C5: =B5 -> 0 | D5: 1 | E5: 1 | F5: 1 | G5: — | H5: Starting harvester.
A6: 2 | B6: 600 | C6: =C5+B6 -> 600 | D6: 1.2 | E6: 1.05 | F6: 1.15 | G6: — | H6: Pure throughput.
A7: 3 | B7: 1500 | C7: =C6+B7 -> 2100 | D7: 1.4 | E7: 1.15 | F7: 1.3 | G7: Auto-return at 90% | H7: Reduces micro.
A8: 4 | B8: 3200 | C8: =C7+B8 -> 5300 | D8: 1.65 | E8: 1.25 | F8: 1.55 | G8: 2nd harvester | H8: The economy inflection. Two routes at once.
A9: 5 | B9: 6000 | C9: =C8+B9 -> 11300 | D9: 2 | E9: 1.4 | F9: 1.9 | G9: Premium fast-harvest | H9: Endgame greed enabler.
A11: Cumulative cost to max = 11,300 gold. Sanity check it against 9 maps of net score in Score_Model.

Sheet Star_Rubric
A1: Wave Star Rubric — 5 independent points
A2: Wave stars average across the 8 waves. Average >= 3.0 unlocks the next map.
A4: Star | B4: Condition | C4: Threshold | D4: Pressures | E4: Design Intent
A5: 1 | B5: Core takes no damage this wave | C5: 0 leaks | D5: Defense | E5: The floor. Bad defense costs a star immediately.
A6: 2 | B6: Zero harvesters lost this wave | C6: 0 losses | D6: Don't overextend | E6: Directly opposes star 4. That tension is the game.
A7: 3 | B7: Primary quota met | C7: 60% of primary in-ring | D7: Baseline harvesting | E7: Achievable while playing safe. Guarantees a 3-star floor.
A8: 4 | B8: Premium claimed in the new ring | C8: All ring premium nodes | D8: Greed | E8: Fresh premium seeded every ring, so this star is ALWAYS live.
A9: 5 | B9: Wave cleared under par time | C9: <= wave par | D9: Tempo | E9: Opposes farming the primary respawn. Forces the player to leave value behind.
A11: GATE MATH
A12: 3 stars = held the line and harvested competently. 4-5 = took the ring risk and got out clean.
A13: Gate is AVERAGE >= 3.0 across 8 waves, so a player can eat one bad wave without restarting the map.
A14: Worst survivable run: seven 3-star waves + one 0-star wave = 2.63. FAILS. One disaster is not survivable.
A15: Seven 3-star waves + one 5-star wave = 3.25. PASSES. So a single greedy wave rescues a mediocre run.
A16: That asymmetry is intentional: it pushes players to take the greed star at least once per map.

Sheet Wave_Table
A1: Wave Table — 72 rows (9 maps x 8 waves)
A2: THE BUILD TARGET. Every cell is derived. Change Global_Params / Growth_Curve / Maps and this recalculates.
A4: Map_ID | B4: Wave | C4: Playable_W | D4: Playable_H | E4: Playable_Area | F4: Ring_Area_Added | G4: Spawn_Dist_X | H4: Spawn_Dist_Y | I4: Side_Focus | J4: Spawn_Budget | K4: Ground_Pts | L4: Air_Pts | M4: Water_Pts | N4: Primary_Nodes | O4: Premium_Nodes | P4: Primary_Quota_Nodes | Q4: Wave_Par_Sec | R4: Map_Primary | S4: Linear_Fraction | T4: Quest_Nodes | U4: Quest_Side | V4: Quest_Band_Min_X | W4: Quest_Band_Min_Y | X4: Quest_Jitter | Y4: Loyalty_Available
A5: 1 | B5: 1 | C5: =MIN(Maps!$C$5-2,ROUND(Maps!$C$5*Growth_Curve!$B$5/2,0)*2) -> 10 | D5: =MIN(Maps!$D$5,ROUND(Maps!$D$5*Growth_Curve!$B$5/2,0)*2) -> 6 | E5: =C5*D5 -> 60 | F5: =E5 -> 60 | G5: =ROUND(C5/2,0)+Global_Params!$B$16 -> 7 | H5: =ROUND(D5/2,0)+Global_Params!$B$16 -> 5 | I5: L | J5: =ROUND(Global_Params!$B$17*(1+Global_Params!$B$18*(B5-1))*Maps!$H$5,0) -> 100 | K5: =J5-L5-M5 -> 90 | L5: =ROUND(J5*(Global_Params!$B$19+(Global_Params!$B$20-Global_Params!$B$19)*(B5-1)/(Global_Params!$B$7-1)),0) -> 10 | M5: =ROUND(J5*IF(Maps!$G$5="Yes",Global_Params!$B$21,0),0) -> 0 | N5: =MAX(2,ROUND(E5/45,0)) -> 2 | O5: =1 -> 1 | P5: =ROUND(N5*0.6,0) -> 1 | Q5: =ROUND(E5/100*Global_Params!$B$25,0) -> 25 | R5: =Maps!$F$5 -> Flowers | S5: =Growth_Curve!$B$5 -> 0.4 | T5: =IF(B5<Global_Params!$B$30,0,MAX(1,ROUND(E5/260,0))) -> 0 | U5: =IF(T5=0,"-","R") -> - | V5: =IF(T5=0,0,ROUND(C5/2*Global_Params!$B$31,0)) -> 0 | W5: =IF(T5=0,0,ROUND(D5/2*Global_Params!$B$31,0)) -> 0 | X5: =IF(T5=0,0,Global_Params!$B$32) -> 0 | Y5: =T5*Global_Params!$B$33 -> 0
A6: 1 | B6: 2 | C6: =MIN(Maps!$C$5-2,MAX(C5+2,ROUND(Maps!$C$5*Growth_Curve!$B$6/2,0)*2)) -> 12 | D6: =MIN(Maps!$D$5,MAX(D5,ROUND(Maps!$D$5*Growth_Curve!$B$6/2,0)*2)) -> 8 | E6: =C6*D6 -> 96 | F6: =E6-E5 -> 36 | G6: =ROUND(C6/2,0)+Global_Params!$B$16 -> 8 | H6: =ROUND(D6/2,0)+Global_Params!$B$16 -> 6 | I6: R | J6: =ROUND(Global_Params!$B$17*(1+Global_Params!$B$18*(B6-1))*Maps!$H$5,0) -> 118 | K6: =J6-L6-M6 -> 103 | L6: =ROUND(J6*(Global_Params!$B$19+(Global_Params!$B$20-Global_Params!$B$19)*(B6-1)/(Global_Params!$B$7-1)),0) -> 15 | M6: =ROUND(J6*IF(Maps!$G$5="Yes",Global_Params!$B$21,0),0) -> 0 | N6: =MAX(2,ROUND(E6/45,0)) -> 2 | O6: =MAX(1,MIN(Global_Params!$B$26,ROUND(F6/50,0))) -> 1 | P6: =ROUND(N6*0.6,0) -> 1 | Q6: =ROUND(E6/100*Global_Params!$B$25,0) -> 40 | R6: =Maps!$F$5 -> Flowers | S6: =Growth_Curve!$B$6 -> 0.46 | T6: =IF(B6<Global_Params!$B$30,0,MAX(1,ROUND(E6/260,0))) -> 0 | U6: =IF(T6=0,"-","L") -> - | V6: =IF(T6=0,0,ROUND(C6/2*Global_Params!$B$31,0)) -> 0 | W6: =IF(T6=0,0,ROUND(D6/2*Global_Params!$B$31,0)) -> 0 | X6: =IF(T6=0,0,Global_Params!$B$32) -> 0 | Y6: =T6*Global_Params!$B$33 -> 0
A7: 1 | B7: 3 | C7: =MIN(Maps!$C$5-2,MAX(C6+2,ROUND(Maps!$C$5*Growth_Curve!$B$7/2,0)*2)) -> 14 | D7: =MIN(Maps!$D$5,MAX(D6,ROUND(Maps!$D$5*Growth_Curve!$B$7/2,0)*2)) -> 8 | E7: =C7*D7 -> 112 | F7: =E7-E6 -> 16 | G7: =ROUND(C7/2,0)+Global_Params!$B$16 -> 9 | H7: =ROUND(D7/2,0)+Global_Params!$B$16 -> 6 | I7: L | J7: =ROUND(Global_Params!$B$17*(1+Global_Params!$B$18*(B7-1))*Maps!$H$5,0) -> 136 | K7: =J7-L7-M7 -> 115 | L7: =ROUND(J7*(Global_Params!$B$19+(Global_Params!$B$20-Global_Params!$B$19)*(B7-1)/(Global_Params!$B$7-1)),0) -> 21 | M7: =ROUND(J7*IF(Maps!$G$5="Yes",Global_Params!$B$21,0),0) -> 0 | N7: =MAX(2,ROUND(E7/45,0)) -> 2 | O7: =MAX(1,MIN(Global_Params!$B$26,ROUND(F7/50,0))) -> 1 | P7: =ROUND(N7*0.6,0) -> 1 | Q7: =ROUND(E7/100*Global_Params!$B$25,0) -> 47 | R7: =Maps!$F$5 -> Flowers | S7: =Growth_Curve!$B$7 -> 0.54 | T7: =IF(B7<Global_Params!$B$30,0,MAX(1,ROUND(E7/260,0))) -> 0 | U7: =IF(T7=0,"-","R") -> - | V7: =IF(T7=0,0,ROUND(C7/2*Global_Params!$B$31,0)) -> 0 | W7: =IF(T7=0,0,ROUND(D7/2*Global_Params!$B$31,0)) -> 0 | X7: =IF(T7=0,0,Global_Params!$B$32) -> 0 | Y7: =T7*Global_Params!$B$33 -> 0
A8: 1 | B8: 4 | C8: =MIN(Maps!$C$5-2,MAX(C7+2,ROUND(Maps!$C$5*Growth_Curve!$B$8/2,0)*2)) -> 16 | D8: =MIN(Maps!$D$5,MAX(D7,ROUND(Maps!$D$5*Growth_Curve!$B$8/2,0)*2)) -> 10 | E8: =C8*D8 -> 160 | F8: =E8-E7 -> 48 | G8: =ROUND(C8/2,0)+Global_Params!$B$16 -> 10 | H8: =ROUND(D8/2,0)+Global_Params!$B$16 -> 7 | I8: R | J8: =ROUND(Global_Params!$B$17*(1+Global_Params!$B$18*(B8-1))*Maps!$H$5,0) -> 154 | K8: =J8-L8-M8 -> 125 | L8: =ROUND(J8*(Global_Params!$B$19+(Global_Params!$B$20-Global_Params!$B$19)*(B8-1)/(Global_Params!$B$7-1)),0) -> 29 | M8: =ROUND(J8*IF(Maps!$G$5="Yes",Global_Params!$B$21,0),0) -> 0 | N8: =MAX(2,ROUND(E8/45,0)) -> 4 | O8: =MAX(1,MIN(Global_Params!$B$26,ROUND(F8/50,0))) -> 1 | P8: =ROUND(N8*0.6,0) -> 2 | Q8: =ROUND(E8/100*Global_Params!$B$25,0) -> 67 | R8: =Maps!$F$5 -> Flowers | S8: =Growth_Curve!$B$8 -> 0.66 | T8: =IF(B8<Global_Params!$B$30,0,MAX(1,ROUND(E8/260,0))) -> 0 | U8: =IF(T8=0,"-","L") -> - | V8: =IF(T8=0,0,ROUND(C8/2*Global_Params!$B$31,0)) -> 0 | W8: =IF(T8=0,0,ROUND(D8/2*Global_Params!$B$31,0)) -> 0 | X8: =IF(T8=0,0,Global_Params!$B$32) -> 0 | Y8: =T8*Global_Params!$B$33 -> 0
A9: 1 | B9: 5 | C9: =MIN(Maps!$C$5-2,MAX(C8+2,ROUND(Maps!$C$5*Growth_Curve!$B$9/2,0)*2)) -> 18 | D9: =MIN(Maps!$D$5,MAX(D8,ROUND(Maps!$D$5*Growth_Curve!$B$9/2,0)*2)) -> 12 | E9: =C9*D9 -> 216 | F9: =E9-E8 -> 56 | G9: =ROUND(C9/2,0)+Global_Params!$B$16 -> 11 | H9: =ROUND(D9/2,0)+Global_Params!$B$16 -> 8 | I9: L | J9: =ROUND(Global_Params!$B$17*(1+Global_Params!$B$18*(B9-1))*Maps!$H$5,0) -> 172 | K9: =J9-L9-M9 -> 135 | L9: =ROUND(J9*(Global_Params!$B$19+(Global_Params!$B$20-Global_Params!$B$19)*(B9-1)/(Global_Params!$B$7-1)),0) -> 37 | M9: =ROUND(J9*IF(Maps!$G$5="Yes",Global_Params!$B$21,0),0) -> 0 | N9: =MAX(2,ROUND(E9/45,0)) -> 5 | O9: =MAX(1,MIN(Global_Params!$B$26,ROUND(F9/50,0))) -> 1 | P9: =ROUND(N9*0.6,0) -> 3 | Q9: =ROUND(E9/100*Global_Params!$B$25,0) -> 91 | R9: =Maps!$F$5 -> Flowers | S9: =Growth_Curve!$B$9 -> 0.79 | T9: =IF(B9<Global_Params!$B$30,0,MAX(1,ROUND(E9/260,0))) -> 1 | U9: =IF(T9=0,"-","R") -> R | V9: =IF(T9=0,0,ROUND(C9/2*Global_Params!$B$31,0)) -> 7 | W9: =IF(T9=0,0,ROUND(D9/2*Global_Params!$B$31,0)) -> 5 | X9: =IF(T9=0,0,Global_Params!$B$32) -> 4 | Y9: =T9*Global_Params!$B$33 -> 10
A10: 1 | B10: 6 | C10: =MIN(Maps!$C$5-2,MAX(C9+2,ROUND(Maps!$C$5*Growth_Curve!$B$10/2,0)*2)) -> 22 | D10: =MIN(Maps!$D$5,MAX(D9,ROUND(Maps!$D$5*Growth_Curve!$B$10/2,0)*2)) -> 14 | E10: =C10*D10 -> 308 | F10: =E10-E9 -> 92 | G10: =ROUND(C10/2,0)+Global_Params!$B$16 -> 13 | H10: =ROUND(D10/2,0)+Global_Params!$B$16 -> 9 | I10: R | J10: =ROUND(Global_Params!$B$17*(1+Global_Params!$B$18*(B10-1))*Maps!$H$5,0) -> 190 | K10: =J10-L10-M10 -> 144 | L10: =ROUND(J10*(Global_Params!$B$19+(Global_Params!$B$20-Global_Params!$B$19)*(B10-1)/(Global_Params!$B$7-1)),0) -> 46 | M10: =ROUND(J10*IF(Maps!$G$5="Yes",Global_Params!$B$21,0),0) -> 0 | N10: =MAX(2,ROUND(E10/45,0)) -> 7 | O10: =MAX(1,MIN(Global_Params!$B$26,ROUND(F10/50,0))) -> 2 | P10: =ROUND(N10*0.6,0) -> 4 | Q10: =ROUND(E10/100*Global_Params!$B$25,0) -> 129 | R10: =Maps!$F$5 -> Flowers | S10: =Growth_Curve!$B$10 -> 0.89 | T10: =IF(B10<Global_Params!$B$30,0,MAX(1,ROUND(E10/260,0))) -> 1 | U10: =IF(T10=0,"-","L") -> L | V10: =IF(T10=0,0,ROUND(C10/2*Global_Params!$B$31,0)) -> 9 | W10: =IF(T10=0,0,ROUND(D10/2*Global_Params!$B$31,0)) -> 6 | X10: =IF(T10=0,0,Global_Params!$B$32) -> 4 | Y10: =T10*Global_Params!$B$33 -> 10
A11: 1 | B11: 7 | C11: =MIN(Maps!$C$5-2,MAX(C10+2,ROUND(Maps!$C$5*Growth_Curve!$B$11/2,0)*2)) -> 22 | D11: =MIN(Maps!$D$5,MAX(D10,ROUND(Maps!$D$5*Growth_Curve!$B$11/2,0)*2)) -> 16 | E11: =C11*D11 -> 352 | F11: =E11-E10 -> 44 | G11: =ROUND(C11/2,0)+Global_Params!$B$16 -> 13 | H11: =ROUND(D11/2,0)+Global_Params!$B$16 -> 10 | I11: T | J11: =ROUND(Global_Params!$B$17*(1+Global_Params!$B$18*(B11-1))*Maps!$H$5,0) -> 208 | K11: =J11-L11-M11 -> 152 | L11: =ROUND(J11*(Global_Params!$B$19+(Global_Params!$B$20-Global_Params!$B$19)*(B11-1)/(Global_Params!$B$7-1)),0) -> 56 | M11: =ROUND(J11*IF(Maps!$G$5="Yes",Global_Params!$B$21,0),0) -> 0 | N11: =MAX(2,ROUND(E11/45,0)) -> 8 | O11: =MAX(1,MIN(Global_Params!$B$26,ROUND(F11/50,0))) -> 1 | P11: =ROUND(N11*0.6,0) -> 5 | Q11: =ROUND(E11/100*Global_Params!$B$25,0) -> 148 | R11: =Maps!$F$5 -> Flowers | S11: =Growth_Curve!$B$11 -> 0.96 | T11: =IF(B11<Global_Params!$B$30,0,MAX(1,ROUND(E11/260,0))) -> 1 | U11: =IF(T11=0,"-","B") -> B | V11: =IF(T11=0,0,ROUND(C11/2*Global_Params!$B$31,0)) -> 9 | W11: =IF(T11=0,0,ROUND(D11/2*Global_Params!$B$31,0)) -> 6 | X11: =IF(T11=0,0,Global_Params!$B$32) -> 4 | Y11: =T11*Global_Params!$B$33 -> 10
A12: 1 | B12: 8 | C12: =Maps!$C$5 -> 24 | D12: =Maps!$D$5 -> 16 | E12: =C12*D12 -> 384 | F12: =E12-E11 -> 32 | G12: =ROUND(C12/2,0)+Global_Params!$B$16 -> 14 | H12: =ROUND(D12/2,0)+Global_Params!$B$16 -> 10 | I12: B | J12: =ROUND(Global_Params!$B$17*(1+Global_Params!$B$18*(B12-1))*Maps!$H$5,0) -> 226 | K12: =J12-L12-M12 -> 158 | L12: =ROUND(J12*(Global_Params!$B$19+(Global_Params!$B$20-Global_Params!$B$19)*(B12-1)/(Global_Params!$B$7-1)),0) -> 68 | M12: =ROUND(J12*IF(Maps!$G$5="Yes",Global_Params!$B$21,0),0) -> 0 | N12: =MAX(2,ROUND(E12/45,0)) -> 9 | O12: =MAX(1,MIN(Global_Params!$B$26,ROUND(F12/50,0))) -> 1 | P12: =ROUND(N12*0.6,0) -> 5 | Q12: =ROUND(E12/100*Global_Params!$B$25,0) -> 161 | R12: =Maps!$F$5 -> Flowers | S12: =Growth_Curve!$B$12 -> 1 | T12: =IF(B12<Global_Params!$B$30,0,MAX(1,ROUND(E12/260,0))) -> 1 | U12: =IF(T12=0,"-","T") -> T | V12: =IF(T12=0,0,ROUND(C12/2*Global_Params!$B$31,0)) -> 10 | W12: =IF(T12=0,0,ROUND(D12/2*Global_Params!$B$31,0)) -> 6 | X12: =IF(T12=0,0,Global_Params!$B$32) -> 4 | Y12: =T12*Global_Params!$B$33 -> 10
A13: 2 | B13: 1 | C13: =MIN(Maps!$C$6-2,ROUND(Maps!$C$6*Growth_Curve!$B$5/2,0)*2) -> 12 | D13: =MIN(Maps!$D$6,ROUND(Maps!$D$6*Growth_Curve!$B$5/2,0)*2) -> 8 | E13: =C13*D13 -> 96 | F13: =E13 -> 96 | G13: =ROUND(C13/2,0)+Global_Params!$B$16 -> 8 | H13: =ROUND(D13/2,0)+Global_Params!$B$16 -> 6 | I13: R | J13: =ROUND(Global_Params!$B$17*(1+Global_Params!$B$18*(B13-1))*Maps!$H$6,0) -> 110 | K13: =J13-L13-M13 -> 99 | L13: =ROUND(J13*(Global_Params!$B$19+(Global_Params!$B$20-Global_Params!$B$19)*(B13-1)/(Global_Params!$B$7-1)),0) -> 11 | M13: =ROUND(J13*IF(Maps!$G$6="Yes",Global_Params!$B$21,0),0) -> 0 | N13: =MAX(2,ROUND(E13/45,0)) -> 2 | O13: =1 -> 1 | P13: =ROUND(N13*0.6,0) -> 1 | Q13: =ROUND(E13/100*Global_Params!$B$25,0) -> 40 | R13: =Maps!$F$6 -> Flowers | S13: =Growth_Curve!$B$5 -> 0.4 | T13: =IF(B13<Global_Params!$B$30,0,MAX(1,ROUND(E13/260,0))) -> 0 | U13: =IF(T13=0,"-","L") -> - | V13: =IF(T13=0,0,ROUND(C13/2*Global_Params!$B$31,0)) -> 0 | W13: =IF(T13=0,0,ROUND(D13/2*Global_Params!$B$31,0)) -> 0 | X13: =IF(T13=0,0,Global_Params!$B$32) -> 0 | Y13: =T13*Global_Params!$B$33 -> 0
A14: 2 | B14: 2 | C14: =MIN(Maps!$C$6-2,MAX(C13+2,ROUND(Maps!$C$6*Growth_Curve!$B$6/2,0)*2)) -> 14 | D14: =MIN(Maps!$D$6,MAX(D13,ROUND(Maps!$D$6*Growth_Curve!$B$6/2,0)*2)) -> 8 | E14: =C14*D14 -> 112 | F14: =E14-E13 -> 16 | G14: =ROUND(C14/2,0)+Global_Params!$B$16 -> 9 | H14: =ROUND(D14/2,0)+Global_Params!$B$16 -> 6 | I14: L | J14: =ROUND(Global_Params!$B$17*(1+Global_Params!$B$18*(B14-1))*Maps!$H$6,0) -> 130 | K14: =J14-L14-M14 -> 113 | L14: =ROUND(J14*(Global_Params!$B$19+(Global_Params!$B$20-Global_Params!$B$19)*(B14-1)/(Global_Params!$B$7-1)),0) -> 17 | M14: =ROUND(J14*IF(Maps!$G$6="Yes",Global_Params!$B$21,0),0) -> 0 | N14: =MAX(2,ROUND(E14/45,0)) -> 2 | O14: =MAX(1,MIN(Global_Params!$B$26,ROUND(F14/50,0))) -> 1 | P14: =ROUND(N14*0.6,0) -> 1 | Q14: =ROUND(E14/100*Global_Params!$B$25,0) -> 47 | R14: =Maps!$F$6 -> Flowers | S14: =Growth_Curve!$B$6 -> 0.46 | T14: =IF(B14<Global_Params!$B$30,0,MAX(1,ROUND(E14/260,0))) -> 0 | U14: =IF(T14=0,"-","R") -> - | V14: =IF(T14=0,0,ROUND(C14/2*Global_Params!$B$31,0)) -> 0 | W14: =IF(T14=0,0,ROUND(D14/2*Global_Params!$B$31,0)) -> 0 | X14: =IF(T14=0,0,Global_Params!$B$32) -> 0 | Y14: =T14*Global_Params!$B$33 -> 0
A15: 2 | B15: 3 | C15: =MIN(Maps!$C$6-2,MAX(C14+2,ROUND(Maps!$C$6*Growth_Curve!$B$7/2,0)*2)) -> 16 | D15: =MIN(Maps!$D$6,MAX(D14,ROUND(Maps!$D$6*Growth_Curve!$B$7/2,0)*2)) -> 10 | E15: =C15*D15 -> 160 | F15: =E15-E14 -> 48 | G15: =ROUND(C15/2,0)+Global_Params!$B$16 -> 10 | H15: =ROUND(D15/2,0)+Global_Params!$B$16 -> 7 | I15: R | J15: =ROUND(Global_Params!$B$17*(1+Global_Params!$B$18*(B15-1))*Maps!$H$6,0) -> 150 | K15: =J15-L15-M15 -> 126 | L15: =ROUND(J15*(Global_Params!$B$19+(Global_Params!$B$20-Global_Params!$B$19)*(B15-1)/(Global_Params!$B$7-1)),0) -> 24 | M15: =ROUND(J15*IF(Maps!$G$6="Yes",Global_Params!$B$21,0),0) -> 0 | N15: =MAX(2,ROUND(E15/45,0)) -> 4 | O15: =MAX(1,MIN(Global_Params!$B$26,ROUND(F15/50,0))) -> 1 | P15: =ROUND(N15*0.6,0) -> 2 | Q15: =ROUND(E15/100*Global_Params!$B$25,0) -> 67 | R15: =Maps!$F$6 -> Flowers | S15: =Growth_Curve!$B$7 -> 0.54 | T15: =IF(B15<Global_Params!$B$30,0,MAX(1,ROUND(E15/260,0))) -> 0 | U15: =IF(T15=0,"-","L") -> - | V15: =IF(T15=0,0,ROUND(C15/2*Global_Params!$B$31,0)) -> 0 | W15: =IF(T15=0,0,ROUND(D15/2*Global_Params!$B$31,0)) -> 0 | X15: =IF(T15=0,0,Global_Params!$B$32) -> 0 | Y15: =T15*Global_Params!$B$33 -> 0
A16: 2 | B16: 4 | C16: =MIN(Maps!$C$6-2,MAX(C15+2,ROUND(Maps!$C$6*Growth_Curve!$B$8/2,0)*2)) -> 20 | D16: =MIN(Maps!$D$6,MAX(D15,ROUND(Maps!$D$6*Growth_Curve!$B$8/2,0)*2)) -> 12 | E16: =C16*D16 -> 240 | F16: =E16-E15 -> 80 | G16: =ROUND(C16/2,0)+Global_Params!$B$16 -> 12 | H16: =ROUND(D16/2,0)+Global_Params!$B$16 -> 8 | I16: L | J16: =ROUND(Global_Params!$B$17*(1+Global_Params!$B$18*(B16-1))*Maps!$H$6,0) -> 169 | K16: =J16-L16-M16 -> 138 | L16: =ROUND(J16*(Global_Params!$B$19+(Global_Params!$B$20-Global_Params!$B$19)*(B16-1)/(Global_Params!$B$7-1)),0) -> 31 | M16: =ROUND(J16*IF(Maps!$G$6="Yes",Global_Params!$B$21,0),0) -> 0 | N16: =MAX(2,ROUND(E16/45,0)) -> 5 | O16: =MAX(1,MIN(Global_Params!$B$26,ROUND(F16/50,0))) -> 2 | P16: =ROUND(N16*0.6,0) -> 3 | Q16: =ROUND(E16/100*Global_Params!$B$25,0) -> 101 | R16: =Maps!$F$6 -> Flowers | S16: =Growth_Curve!$B$8 -> 0.66 | T16: =IF(B16<Global_Params!$B$30,0,MAX(1,ROUND(E16/260,0))) -> 0 | U16: =IF(T16=0,"-","R") -> - | V16: =IF(T16=0,0,ROUND(C16/2*Global_Params!$B$31,0)) -> 0 | W16: =IF(T16=0,0,ROUND(D16/2*Global_Params!$B$31,0)) -> 0 | X16: =IF(T16=0,0,Global_Params!$B$32) -> 0 | Y16: =T16*Global_Params!$B$33 -> 0
A17: 2 | B17: 5 | C17: =MIN(Maps!$C$6-2,MAX(C16+2,ROUND(Maps!$C$6*Growth_Curve!$B$9/2,0)*2)) -> 24 | D17: =MIN(Maps!$D$6,MAX(D16,ROUND(Maps!$D$6*Growth_Curve!$B$9/2,0)*2)) -> 14 | E17: =C17*D17 -> 336 | F17: =E17-E16 -> 96 | G17: =ROUND(C17/2,0)+Global_Params!$B$16 -> 14 | H17: =ROUND(D17/2,0)+Global_Params!$B$16 -> 9 | I17: R | J17: =ROUND(Global_Params!$B$17*(1+Global_Params!$B$18*(B17-1))*Maps!$H$6,0) -> 189 | K17: =J17-L17-M17 -> 148 | L17: =ROUND(J17*(Global_Params!$B$19+(Global_Params!$B$20-Global_Params!$B$19)*(B17-1)/(Global_Params!$B$7-1)),0) -> 41 | M17: =ROUND(J17*IF(Maps!$G$6="Yes",Global_Params!$B$21,0),0) -> 0 | N17: =MAX(2,ROUND(E17/45,0)) -> 7 | O17: =MAX(1,MIN(Global_Params!$B$26,ROUND(F17/50,0))) -> 2 | P17: =ROUND(N17*0.6,0) -> 4 | Q17: =ROUND(E17/100*Global_Params!$B$25,0) -> 141 | R17: =Maps!$F$6 -> Flowers | S17: =Growth_Curve!$B$9 -> 0.79 | T17: =IF(B17<Global_Params!$B$30,0,MAX(1,ROUND(E17/260,0))) -> 1 | U17: =IF(T17=0,"-","L") -> L | V17: =IF(T17=0,0,ROUND(C17/2*Global_Params!$B$31,0)) -> 10 | W17: =IF(T17=0,0,ROUND(D17/2*Global_Params!$B$31,0)) -> 6 | X17: =IF(T17=0,0,Global_Params!$B$32) -> 4 | Y17: =T17*Global_Params!$B$33 -> 10
A18: 2 | B18: 6 | C18: =MIN(Maps!$C$6-2,MAX(C17+2,ROUND(Maps!$C$6*Growth_Curve!$B$10/2,0)*2)) -> 26 | D18: =MIN(Maps!$D$6,MAX(D17,ROUND(Maps!$D$6*Growth_Curve!$B$10/2,0)*2)) -> 16 | E18: =C18*D18 -> 416 | F18: =E18-E17 -> 80 | G18: =ROUND(C18/2,0)+Global_Params!$B$16 -> 15 | H18: =ROUND(D18/2,0)+Global_Params!$B$16 -> 10 | I18: T | J18: =ROUND(Global_Params!$B$17*(1+Global_Params!$B$18*(B18-1))*Maps!$H$6,0) -> 209 | K18: =J18-L18-M18 -> 158 | L18: =ROUND(J18*(Global_Params!$B$19+(Global_Params!$B$20-Global_Params!$B$19)*(B18-1)/(Global_Params!$B$7-1)),0) -> 51 | M18: =ROUND(J18*IF(Maps!$G$6="Yes",Global_Params!$B$21,0),0) -> 0 | N18: =MAX(2,ROUND(E18/45,0)) -> 9 | O18: =MAX(1,MIN(Global_Params!$B$26,ROUND(F18/50,0))) -> 2 | P18: =ROUND(N18*0.6,0) -> 5 | Q18: =ROUND(E18/100*Global_Params!$B$25,0) -> 175 | R18: =Maps!$F$6 -> Flowers | S18: =Growth_Curve!$B$10 -> 0.89 | T18: =IF(B18<Global_Params!$B$30,0,MAX(1,ROUND(E18/260,0))) -> 2 | U18: =IF(T18=0,"-","B") -> B | V18: =IF(T18=0,0,ROUND(C18/2*Global_Params!$B$31,0)) -> 10 | W18: =IF(T18=0,0,ROUND(D18/2*Global_Params!$B$31,0)) -> 6 | X18: =IF(T18=0,0,Global_Params!$B$32) -> 4 | Y18: =T18*Global_Params!$B$33 -> 20
A19: 2 | B19: 7 | C19: =MIN(Maps!$C$6-2,MAX(C18+2,ROUND(Maps!$C$6*Growth_Curve!$B$11/2,0)*2)) -> 28 | D19: =MIN(Maps!$D$6,MAX(D18,ROUND(Maps!$D$6*Growth_Curve!$B$11/2,0)*2)) -> 18 | E19: =C19*D19 -> 504 | F19: =E19-E18 -> 88 | G19: =ROUND(C19/2,0)+Global_Params!$B$16 -> 16 | H19: =ROUND(D19/2,0)+Global_Params!$B$16 -> 11 | I19: B | J19: =ROUND(Global_Params!$B$17*(1+Global_Params!$B$18*(B19-1))*Maps!$H$6,0) -> 229 | K19: =J19-L19-M19 -> 167 | L19: =ROUND(J19*(Global_Params!$B$19+(Global_Params!$B$20-Global_Params!$B$19)*(B19-1)/(Global_Params!$B$7-1)),0) -> 62 | M19: =ROUND(J19*IF(Maps!$G$6="Yes",Global_Params!$B$21,0),0) -> 0 | N19: =MAX(2,ROUND(E19/45,0)) -> 11 | O19: =MAX(1,MIN(Global_Params!$B$26,ROUND(F19/50,0))) -> 2 | P19: =ROUND(N19*0.6,0) -> 7 | Q19: =ROUND(E19/100*Global_Params!$B$25,0) -> 212 | R19: =Maps!$F$6 -> Flowers | S19: =Growth_Curve!$B$11 -> 0.96 | T19: =IF(B19<Global_Params!$B$30,0,MAX(1,ROUND(E19/260,0))) -> 2 | U19: =IF(T19=0,"-","T") -> T | V19: =IF(T19=0,0,ROUND(C19/2*Global_Params!$B$31,0)) -> 11 | W19: =IF(T19=0,0,ROUND(D19/2*Global_Params!$B$31,0)) -> 7 | X19: =IF(T19=0,0,Global_Params!$B$32) -> 4 | Y19: =T19*Global_Params!$B$33 -> 20
A20: 2 | B20: 8 | C20: =Maps!$C$6 -> 30 | D20: =Maps!$D$6 -> 18 | E20: =C20*D20 -> 540 | F20: =E20-E19 -> 36 | G20: =ROUND(C20/2,0)+Global_Params!$B$16 -> 17 | H20: =ROUND(D20/2,0)+Global_Params!$B$16 -> 11 | I20: L | J20: =ROUND(Global_Params!$B$17*(1+Global_Params!$B$18*(B20-1))*Maps!$H$6,0) -> 249 | K20: =J20-L20-M20 -> 174 | L20: =ROUND(J20*(Global_Params!$B$19+(Global_Params!$B$20-Global_Params!$B$19)*(B20-1)/(Global_Params!$B$7-1)),0) -> 75 | M20: =ROUND(J20*IF(Maps!$G$6="Yes",Global_Params!$B$21,0),0) -> 0 | N20: =MAX(2,ROUND(E20/45,0)) -> 12 | O20: =MAX(1,MIN(Global_Params!$B$26,ROUND(F20/50,0))) -> 1 | P20: =ROUND(N20*0.6,0) -> 7 | Q20: =ROUND(E20/100*Global_Params!$B$25,0) -> 227 | R20: =Maps!$F$6 -> Flowers | S20: =Growth_Curve!$B$12 -> 1 | T20: =IF(B20<Global_Params!$B$30,0,MAX(1,ROUND(E20/260,0))) -> 2 | U20: =IF(T20=0,"-","R") -> R | V20: =IF(T20=0,0,ROUND(C20/2*Global_Params!$B$31,0)) -> 12 | W20: =IF(T20=0,0,ROUND(D20/2*Global_Params!$B$31,0)) -> 7 | X20: =IF(T20=0,0,Global_Params!$B$32) -> 4 | Y20: =T20*Global_Params!$B$33 -> 20
A21: 3 | B21: 1 | C21: =MIN(Maps!$C$7-2,ROUND(Maps!$C$7*Growth_Curve!$B$5/2,0)*2) -> 14 | D21: =MIN(Maps!$D$7,ROUND(Maps!$D$7*Growth_Curve!$B$5/2,0)*2) -> 8 | E21: =C21*D21 -> 112 | F21: =E21 -> 112 | G21: =ROUND(C21/2,0)+Global_Params!$B$16 -> 9 | H21: =ROUND(D21/2,0)+Global_Params!$B$16 -> 6 | I21: L | J21: =ROUND(Global_Params!$B$17*(1+Global_Params!$B$18*(B21-1))*Maps!$H$7,0) -> 120 | K21: =J21-L21-M21 -> 90 | L21: =ROUND(J21*(Global_Params!$B$19+(Global_Params!$B$20-Global_Params!$B$19)*(B21-1)/(Global_Params!$B$7-1)),0) -> 12 | M21: =ROUND(J21*IF(Maps!$G$7="Yes",Global_Params!$B$21,0),0) -> 18 | N21: =MAX(2,ROUND(E21/45,0)) -> 2 | O21: =1 -> 1 | P21: =ROUND(N21*0.6,0) -> 1 | Q21: =ROUND(E21/100*Global_Params!$B$25,0) -> 47 | R21: =Maps!$F$7 -> Minerals | S21: =Growth_Curve!$B$5 -> 0.4 | T21: =IF(B21<Global_Params!$B$30,0,MAX(1,ROUND(E21/260,0))) -> 0 | U21: =IF(T21=0,"-","R") -> - | V21: =IF(T21=0,0,ROUND(C21/2*Global_Params!$B$31,0)) -> 0 | W21: =IF(T21=0,0,ROUND(D21/2*Global_Params!$B$31,0)) -> 0 | X21: =IF(T21=0,0,Global_Params!$B$32) -> 0 | Y21: =T21*Global_Params!$B$33 -> 0
A22: 3 | B22: 2 | C22: =MIN(Maps!$C$7-2,MAX(C21+2,ROUND(Maps!$C$7*Growth_Curve!$B$6/2,0)*2)) -> 16 | D22: =MIN(Maps!$D$7,MAX(D21,ROUND(Maps!$D$7*Growth_Curve!$B$6/2,0)*2)) -> 10 | E22: =C22*D22 -> 160 | F22: =E22-E21 -> 48 | G22: =ROUND(C22/2,0)+Global_Params!$B$16 -> 10 | H22: =ROUND(D22/2,0)+Global_Params!$B$16 -> 7 | I22: R | J22: =ROUND(Global_Params!$B$17*(1+Global_Params!$B$18*(B22-1))*Maps!$H$7,0) -> 142 | K22: =J22-L22-M22 -> 103 | L22: =ROUND(J22*(Global_Params!$B$19+(Global_Params!$B$20-Global_Params!$B$19)*(B22-1)/(Global_Params!$B$7-1)),0) -> 18 | M22: =ROUND(J22*IF(Maps!$G$7="Yes",Global_Params!$B$21,0),0) -> 21 | N22: =MAX(2,ROUND(E22/45,0)) -> 4 | O22: =MAX(1,MIN(Global_Params!$B$26,ROUND(F22/50,0))) -> 1 | P22: =ROUND(N22*0.6,0) -> 2 | Q22: =ROUND(E22/100*Global_Params!$B$25,0) -> 67 | R22: =Maps!$F$7 -> Minerals | S22: =Growth_Curve!$B$6 -> 0.46 | T22: =IF(B22<Global_Params!$B$30,0,MAX(1,ROUND(E22/260,0))) -> 0 | U22: =IF(T22=0,"-","L") -> - | V22: =IF(T22=0,0,ROUND(C22/2*Global_Params!$B$31,0)) -> 0 | W22: =IF(T22=0,0,ROUND(D22/2*Global_Params!$B$31,0)) -> 0 | X22: =IF(T22=0,0,Global_Params!$B$32) -> 0 | Y22: =T22*Global_Params!$B$33 -> 0
A23: 3 | B23: 3 | C23: =MIN(Maps!$C$7-2,MAX(C22+2,ROUND(Maps!$C$7*Growth_Curve!$B$7/2,0)*2)) -> 18 | D23: =MIN(Maps!$D$7,MAX(D22,ROUND(Maps!$D$7*Growth_Curve!$B$7/2,0)*2)) -> 10 | E23: =C23*D23 -> 180 | F23: =E23-E22 -> 20 | G23: =ROUND(C23/2,0)+Global_Params!$B$16 -> 11 | H23: =ROUND(D23/2,0)+Global_Params!$B$16 -> 7 | I23: L | J23: =ROUND(Global_Params!$B$17*(1+Global_Params!$B$18*(B23-1))*Maps!$H$7,0) -> 163 | K23: =J23-L23-M23 -> 113 | L23: =ROUND(J23*(Global_Params!$B$19+(Global_Params!$B$20-Global_Params!$B$19)*(B23-1)/(Global_Params!$B$7-1)),0) -> 26 | M23: =ROUND(J23*IF(Maps!$G$7="Yes",Global_Params!$B$21,0),0) -> 24 | N23: =MAX(2,ROUND(E23/45,0)) -> 4 | O23: =MAX(1,MIN(Global_Params!$B$26,ROUND(F23/50,0))) -> 1 | P23: =ROUND(N23*0.6,0) -> 2 | Q23: =ROUND(E23/100*Global_Params!$B$25,0) -> 76 | R23: =Maps!$F$7 -> Minerals | S23: =Growth_Curve!$B$7 -> 0.54 | T23: =IF(B23<Global_Params!$B$30,0,MAX(1,ROUND(E23/260,0))) -> 0 | U23: =IF(T23=0,"-","R") -> - | V23: =IF(T23=0,0,ROUND(C23/2*Global_Params!$B$31,0)) -> 0 | W23: =IF(T23=0,0,ROUND(D23/2*Global_Params!$B$31,0)) -> 0 | X23: =IF(T23=0,0,Global_Params!$B$32) -> 0 | Y23: =T23*Global_Params!$B$33 -> 0
A24: 3 | B24: 4 | C24: =MIN(Maps!$C$7-2,MAX(C23+2,ROUND(Maps!$C$7*Growth_Curve!$B$8/2,0)*2)) -> 22 | D24: =MIN(Maps!$D$7,MAX(D23,ROUND(Maps!$D$7*Growth_Curve!$B$8/2,0)*2)) -> 14 | E24: =C24*D24 -> 308 | F24: =E24-E23 -> 128 | G24: =ROUND(C24/2,0)+Global_Params!$B$16 -> 13 | H24: =ROUND(D24/2,0)+Global_Params!$B$16 -> 9 | I24: R | J24: =ROUND(Global_Params!$B$17*(1+Global_Params!$B$18*(B24-1))*Maps!$H$7,0) -> 185 | K24: =J24-L24-M24 -> 123 | L24: =ROUND(J24*(Global_Params!$B$19+(Global_Params!$B$20-Global_Params!$B$19)*(B24-1)/(Global_Params!$B$7-1)),0) -> 34 | M24: =ROUND(J24*IF(Maps!$G$7="Yes",Global_Params!$B$21,0),0) -> 28 | N24: =MAX(2,ROUND(E24/45,0)) -> 7 | O24: =MAX(1,MIN(Global_Params!$B$26,ROUND(F24/50,0))) -> 3 | P24: =ROUND(N24*0.6,0) -> 4 | Q24: =ROUND(E24/100*Global_Params!$B$25,0) -> 129 | R24: =Maps!$F$7 -> Minerals | S24: =Growth_Curve!$B$8 -> 0.66 | T24: =IF(B24<Global_Params!$B$30,0,MAX(1,ROUND(E24/260,0))) -> 0 | U24: =IF(T24=0,"-","L") -> - | V24: =IF(T24=0,0,ROUND(C24/2*Global_Params!$B$31,0)) -> 0 | W24: =IF(T24=0,0,ROUND(D24/2*Global_Params!$B$31,0)) -> 0 | X24: =IF(T24=0,0,Global_Params!$B$32) -> 0 | Y24: =T24*Global_Params!$B$33 -> 0
A25: 3 | B25: 5 | C25: =MIN(Maps!$C$7-2,MAX(C24+2,ROUND(Maps!$C$7*Growth_Curve!$B$9/2,0)*2)) -> 26 | D25: =MIN(Maps!$D$7,MAX(D24,ROUND(Maps!$D$7*Growth_Curve!$B$9/2,0)*2)) -> 16 | E25: =C25*D25 -> 416 | F25: =E25-E24 -> 108 | G25: =ROUND(C25/2,0)+Global_Params!$B$16 -> 15 | H25: =ROUND(D25/2,0)+Global_Params!$B$16 -> 10 | I25: T | J25: =ROUND(Global_Params!$B$17*(1+Global_Params!$B$18*(B25-1))*Maps!$H$7,0) -> 206 | K25: =J25-L25-M25 -> 131 | L25: =ROUND(J25*(Global_Params!$B$19+(Global_Params!$B$20-Global_Params!$B$19)*(B25-1)/(Global_Params!$B$7-1)),0) -> 44 | M25: =ROUND(J25*IF(Maps!$G$7="Yes",Global_Params!$B$21,0),0) -> 31 | N25: =MAX(2,ROUND(E25/45,0)) -> 9 | O25: =MAX(1,MIN(Global_Params!$B$26,ROUND(F25/50,0))) -> 2 | P25: =ROUND(N25*0.6,0) -> 5 | Q25: =ROUND(E25/100*Global_Params!$B$25,0) -> 175 | R25: =Maps!$F$7 -> Minerals | S25: =Growth_Curve!$B$9 -> 0.79 | T25: =IF(B25<Global_Params!$B$30,0,MAX(1,ROUND(E25/260,0))) -> 2 | U25: =IF(T25=0,"-","B") -> B | V25: =IF(T25=0,0,ROUND(C25/2*Global_Params!$B$31,0)) -> 10 | W25: =IF(T25=0,0,ROUND(D25/2*Global_Params!$B$31,0)) -> 6 | X25: =IF(T25=0,0,Global_Params!$B$32) -> 4 | Y25: =T25*Global_Params!$B$33 -> 20
A26: 3 | B26: 6 | C26: =MIN(Maps!$C$7-2,MAX(C25+2,ROUND(Maps!$C$7*Growth_Curve!$B$10/2,0)*2)) -> 30 | D26: =MIN(Maps!$D$7,MAX(D25,ROUND(Maps!$D$7*Growth_Curve!$B$10/2,0)*2)) -> 18 | E26: =C26*D26 -> 540 | F26: =E26-E25 -> 124 | G26: =ROUND(C26/2,0)+Global_Params!$B$16 -> 17 | H26: =ROUND(D26/2,0)+Global_Params!$B$16 -> 11 | I26: B | J26: =ROUND(Global_Params!$B$17*(1+Global_Params!$B$18*(B26-1))*Maps!$H$7,0) -> 228 | K26: =J26-L26-M26 -> 139 | L26: =ROUND(J26*(Global_Params!$B$19+(Global_Params!$B$20-Global_Params!$B$19)*(B26-1)/(Global_Params!$B$7-1)),0) -> 55 | M26: =ROUND(J26*IF(Maps!$G$7="Yes",Global_Params!$B$21,0),0) -> 34 | N26: =MAX(2,ROUND(E26/45,0)) -> 12 | O26: =MAX(1,MIN(Global_Params!$B$26,ROUND(F26/50,0))) -> 2 | P26: =ROUND(N26*0.6,0) -> 7 | Q26: =ROUND(E26/100*Global_Params!$B$25,0) -> 227 | R26: =Maps!$F$7 -> Minerals | S26: =Growth_Curve!$B$10 -> 0.89 | T26: =IF(B26<Global_Params!$B$30,0,MAX(1,ROUND(E26/260,0))) -> 2 | U26: =IF(T26=0,"-","T") -> T | V26: =IF(T26=0,0,ROUND(C26/2*Global_Params!$B$31,0)) -> 12 | W26: =IF(T26=0,0,ROUND(D26/2*Global_Params!$B$31,0)) -> 7 | X26: =IF(T26=0,0,Global_Params!$B$32) -> 4 | Y26: =T26*Global_Params!$B$33 -> 20
A27: 3 | B27: 7 | C27: =MIN(Maps!$C$7-2,MAX(C26+2,ROUND(Maps!$C$7*Growth_Curve!$B$11/2,0)*2)) -> 32 | D27: =MIN(Maps!$D$7,MAX(D26,ROUND(Maps!$D$7*Growth_Curve!$B$11/2,0)*2)) -> 20 | E27: =C27*D27 -> 640 | F27: =E27-E26 -> 100 | G27: =ROUND(C27/2,0)+Global_Params!$B$16 -> 18 | H27: =ROUND(D27/2,0)+Global_Params!$B$16 -> 12 | I27: L | J27: =ROUND(Global_Params!$B$17*(1+Global_Params!$B$18*(B27-1))*Maps!$H$7,0) -> 250 | K27: =J27-L27-M27 -> 144 | L27: =ROUND(J27*(Global_Params!$B$19+(Global_Params!$B$20-Global_Params!$B$19)*(B27-1)/(Global_Params!$B$7-1)),0) -> 68 | M27: =ROUND(J27*IF(Maps!$G$7="Yes",Global_Params!$B$21,0),0) -> 38 | N27: =MAX(2,ROUND(E27/45,0)) -> 14 | O27: =MAX(1,MIN(Global_Params!$B$26,ROUND(F27/50,0))) -> 2 | P27: =ROUND(N27*0.6,0) -> 8 | Q27: =ROUND(E27/100*Global_Params!$B$25,0) -> 269 | R27: =Maps!$F$7 -> Minerals | S27: =Growth_Curve!$B$11 -> 0.96 | T27: =IF(B27<Global_Params!$B$30,0,MAX(1,ROUND(E27/260,0))) -> 2 | U27: =IF(T27=0,"-","R") -> R | V27: =IF(T27=0,0,ROUND(C27/2*Global_Params!$B$31,0)) -> 13 | W27: =IF(T27=0,0,ROUND(D27/2*Global_Params!$B$31,0)) -> 8 | X27: =IF(T27=0,0,Global_Params!$B$32) -> 4 | Y27: =T27*Global_Params!$B$33 -> 20
A28: 3 | B28: 8 | C28: =Maps!$C$7 -> 34 | D28: =Maps!$D$7 -> 20 | E28: =C28*D28 -> 680 | F28: =E28-E27 -> 40 | G28: =ROUND(C28/2,0)+Global_Params!$B$16 -> 19 | H28: =ROUND(D28/2,0)+Global_Params!$B$16 -> 12 | I28: R | J28: =ROUND(Global_Params!$B$17*(1+Global_Params!$B$18*(B28-1))*Maps!$H$7,0) -> 271 | K28: =J28-L28-M28 -> 149 | L28: =ROUND(J28*(Global_Params!$B$19+(Global_Params!$B$20-Global_Params!$B$19)*(B28-1)/(Global_Params!$B$7-1)),0) -> 81 | M28: =ROUND(J28*IF(Maps!$G$7="Yes",Global_Params!$B$21,0),0) -> 41 | N28: =MAX(2,ROUND(E28/45,0)) -> 15 | O28: =MAX(1,MIN(Global_Params!$B$26,ROUND(F28/50,0))) -> 1 | P28: =ROUND(N28*0.6,0) -> 9 | Q28: =ROUND(E28/100*Global_Params!$B$25,0) -> 286 | R28: =Maps!$F$7 -> Minerals | S28: =Growth_Curve!$B$12 -> 1 | T28: =IF(B28<Global_Params!$B$30,0,MAX(1,ROUND(E28/260,0))) -> 3 | U28: =IF(T28=0,"-","L") -> L | V28: =IF(T28=0,0,ROUND(C28/2*Global_Params!$B$31,0)) -> 14 | W28: =IF(T28=0,0,ROUND(D28/2*Global_Params!$B$31,0)) -> 8 | X28: =IF(T28=0,0,Global_Params!$B$32) -> 4 | Y28: =T28*Global_Params!$B$33 -> 30
A29: 4 | B29: 1 | C29: =MIN(Maps!$C$8-2,ROUND(Maps!$C$8*Growth_Curve!$B$5/2,0)*2) -> 16 | D29: =MIN(Maps!$D$8,ROUND(Maps!$D$8*Growth_Curve!$B$5/2,0)*2) -> 8 | E29: =C29*D29 -> 128 | F29: =E29 -> 128 | G29: =ROUND(C29/2,0)+Global_Params!$B$16 -> 10 | H29: =ROUND(D29/2,0)+Global_Params!$B$16 -> 6 | I29: R | J29: =ROUND(Global_Params!$B$17*(1+Global_Params!$B$18*(B29-1))*Maps!$H$8,0) -> 130 | K29: =J29-L29-M29 -> 117 | L29: =ROUND(J29*(Global_Params!$B$19+(Global_Params!$B$20-Global_Params!$B$19)*(B29-1)/(Global_Params!$B$7-1)),0) -> 13 | M29: =ROUND(J29*IF(Maps!$G$8="Yes",Global_Params!$B$21,0),0) -> 0 | N29: =MAX(2,ROUND(E29/45,0)) -> 3 | O29: =1 -> 1 | P29: =ROUND(N29*0.6,0) -> 2 | Q29: =ROUND(E29/100*Global_Params!$B$25,0) -> 54 | R29: =Maps!$F$8 -> Minerals | S29: =Growth_Curve!$B$5 -> 0.4 | T29: =IF(B29<Global_Params!$B$30,0,MAX(1,ROUND(E29/260,0))) -> 0 | U29: =IF(T29=0,"-","L") -> - | V29: =IF(T29=0,0,ROUND(C29/2*Global_Params!$B$31,0)) -> 0 | W29: =IF(T29=0,0,ROUND(D29/2*Global_Params!$B$31,0)) -> 0 | X29: =IF(T29=0,0,Global_Params!$B$32) -> 0 | Y29: =T29*Global_Params!$B$33 -> 0
A30: 4 | B30: 2 | C30: =MIN(Maps!$C$8-2,MAX(C29+2,ROUND(Maps!$C$8*Growth_Curve!$B$6/2,0)*2)) -> 18 | D30: =MIN(Maps!$D$8,MAX(D29,ROUND(Maps!$D$8*Growth_Curve!$B$6/2,0)*2)) -> 10 | E30: =C30*D30 -> 180 | F30: =E30-E29 -> 52 | G30: =ROUND(C30/2,0)+Global_Params!$B$16 -> 11 | H30: =ROUND(D30/2,0)+Global_Params!$B$16 -> 7 | I30: L | J30: =ROUND(Global_Params!$B$17*(1+Global_Params!$B$18*(B30-1))*Maps!$H$8,0) -> 153 | K30: =J30-L30-M30 -> 133 | L30: =ROUND(J30*(Global_Params!$B$19+(Global_Params!$B$20-Global_Params!$B$19)*(B30-1)/(Global_Params!$B$7-1)),0) -> 20 | M30: =ROUND(J30*IF(Maps!$G$8="Yes",Global_Params!$B$21,0),0) -> 0 | N30: =MAX(2,ROUND(E30/45,0)) -> 4 | O30: =MAX(1,MIN(Global_Params!$B$26,ROUND(F30/50,0))) -> 1 | P30: =ROUND(N30*0.6,0) -> 2 | Q30: =ROUND(E30/100*Global_Params!$B$25,0) -> 76 | R30: =Maps!$F$8 -> Minerals | S30: =Growth_Curve!$B$6 -> 0.46 | T30: =IF(B30<Global_Params!$B$30,0,MAX(1,ROUND(E30/260,0))) -> 0 | U30: =IF(T30=0,"-","R") -> - | V30: =IF(T30=0,0,ROUND(C30/2*Global_Params!$B$31,0)) -> 0 | W30: =IF(T30=0,0,ROUND(D30/2*Global_Params!$B$31,0)) -> 0 | X30: =IF(T30=0,0,Global_Params!$B$32) -> 0 | Y30: =T30*Global_Params!$B$33 -> 0
A31: 4 | B31: 3 | C31: =MIN(Maps!$C$8-2,MAX(C30+2,ROUND(Maps!$C$8*Growth_Curve!$B$7/2,0)*2)) -> 22 | D31: =MIN(Maps!$D$8,MAX(D30,ROUND(Maps!$D$8*Growth_Curve!$B$7/2,0)*2)) -> 12 | E31: =C31*D31 -> 264 | F31: =E31-E30 -> 84 | G31: =ROUND(C31/2,0)+Global_Params!$B$16 -> 13 | H31: =ROUND(D31/2,0)+Global_Params!$B$16 -> 8 | I31: R | J31: =ROUND(Global_Params!$B$17*(1+Global_Params!$B$18*(B31-1))*Maps!$H$8,0) -> 177 | K31: =J31-L31-M31 -> 149 | L31: =ROUND(J31*(Global_Params!$B$19+(Global_Params!$B$20-Global_Params!$B$19)*(B31-1)/(Global_Params!$B$7-1)),0) -> 28 | M31: =ROUND(J31*IF(Maps!$G$8="Yes",Global_Params!$B$21,0),0) -> 0 | N31: =MAX(2,ROUND(E31/45,0)) -> 6 | O31: =MAX(1,MIN(Global_Params!$B$26,ROUND(F31/50,0))) -> 2 | P31: =ROUND(N31*0.6,0) -> 4 | Q31: =ROUND(E31/100*Global_Params!$B$25,0) -> 111 | R31: =Maps!$F$8 -> Minerals | S31: =Growth_Curve!$B$7 -> 0.54 | T31: =IF(B31<Global_Params!$B$30,0,MAX(1,ROUND(E31/260,0))) -> 0 | U31: =IF(T31=0,"-","L") -> - | V31: =IF(T31=0,0,ROUND(C31/2*Global_Params!$B$31,0)) -> 0 | W31: =IF(T31=0,0,ROUND(D31/2*Global_Params!$B$31,0)) -> 0 | X31: =IF(T31=0,0,Global_Params!$B$32) -> 0 | Y31: =T31*Global_Params!$B$33 -> 0
A32: 4 | B32: 4 | C32: =MIN(Maps!$C$8-2,MAX(C31+2,ROUND(Maps!$C$8*Growth_Curve!$B$8/2,0)*2)) -> 26 | D32: =MIN(Maps!$D$8,MAX(D31,ROUND(Maps!$D$8*Growth_Curve!$B$8/2,0)*2)) -> 14 | E32: =C32*D32 -> 364 | F32: =E32-E31 -> 100 | G32: =ROUND(C32/2,0)+Global_Params!$B$16 -> 15 | H32: =ROUND(D32/2,0)+Global_Params!$B$16 -> 9 | I32: T | J32: =ROUND(Global_Params!$B$17*(1+Global_Params!$B$18*(B32-1))*Maps!$H$8,0) -> 200 | K32: =J32-L32-M32 -> 163 | L32: =ROUND(J32*(Global_Params!$B$19+(Global_Params!$B$20-Global_Params!$B$19)*(B32-1)/(Global_Params!$B$7-1)),0) -> 37 | M32: =ROUND(J32*IF(Maps!$G$8="Yes",Global_Params!$B$21,0),0) -> 0 | N32: =MAX(2,ROUND(E32/45,0)) -> 8 | O32: =MAX(1,MIN(Global_Params!$B$26,ROUND(F32/50,0))) -> 2 | P32: =ROUND(N32*0.6,0) -> 5 | Q32: =ROUND(E32/100*Global_Params!$B$25,0) -> 153 | R32: =Maps!$F$8 -> Minerals | S32: =Growth_Curve!$B$8 -> 0.66 | T32: =IF(B32<Global_Params!$B$30,0,MAX(1,ROUND(E32/260,0))) -> 0 | U32: =IF(T32=0,"-","B") -> - | V32: =IF(T32=0,0,ROUND(C32/2*Global_Params!$B$31,0)) -> 0 | W32: =IF(T32=0,0,ROUND(D32/2*Global_Params!$B$31,0)) -> 0 | X32: =IF(T32=0,0,Global_Params!$B$32) -> 0 | Y32: =T32*Global_Params!$B$33 -> 0
A33: 4 | B33: 5 | C33: =MIN(Maps!$C$8-2,MAX(C32+2,ROUND(Maps!$C$8*Growth_Curve!$B$9/2,0)*2)) -> 32 | D33: =MIN(Maps!$D$8,MAX(D32,ROUND(Maps!$D$8*Growth_Curve!$B$9/2,0)*2)) -> 18 | E33: =C33*D33 -> 576 | F33: =E33-E32 -> 212 | G33: =ROUND(C33/2,0)+Global_Params!$B$16 -> 18 | H33: =ROUND(D33/2,0)+Global_Params!$B$16 -> 11 | I33: B | J33: =ROUND(Global_Params!$B$17*(1+Global_Params!$B$18*(B33-1))*Maps!$H$8,0) -> 224 | K33: =J33-L33-M33 -> 176 | L33: =ROUND(J33*(Global_Params!$B$19+(Global_Params!$B$20-Global_Params!$B$19)*(B33-1)/(Global_Params!$B$7-1)),0) -> 48 | M33: =ROUND(J33*IF(Maps!$G$8="Yes",Global_Params!$B$21,0),0) -> 0 | N33: =MAX(2,ROUND(E33/45,0)) -> 13 | O33: =MAX(1,MIN(Global_Params!$B$26,ROUND(F33/50,0))) -> 3 | P33: =ROUND(N33*0.6,0) -> 8 | Q33: =ROUND(E33/100*Global_Params!$B$25,0) -> 242 | R33: =Maps!$F$8 -> Minerals | S33: =Growth_Curve!$B$9 -> 0.79 | T33: =IF(B33<Global_Params!$B$30,0,MAX(1,ROUND(E33/260,0))) -> 2 | U33: =IF(T33=0,"-","T") -> T | V33: =IF(T33=0,0,ROUND(C33/2*Global_Params!$B$31,0)) -> 13 | W33: =IF(T33=0,0,ROUND(D33/2*Global_Params!$B$31,0)) -> 7 | X33: =IF(T33=0,0,Global_Params!$B$32) -> 4 | Y33: =T33*Global_Params!$B$33 -> 20
A34: 4 | B34: 6 | C34: =MIN(Maps!$C$8-2,MAX(C33+2,ROUND(Maps!$C$8*Growth_Curve!$B$10/2,0)*2)) -> 36 | D34: =MIN(Maps!$D$8,MAX(D33,ROUND(Maps!$D$8*Growth_Curve!$B$10/2,0)*2)) -> 20 | E34: =C34*D34 -> 720 | F34: =E34-E33 -> 144 | G34: =ROUND(C34/2,0)+Global_Params!$B$16 -> 20 | H34: =ROUND(D34/2,0)+Global_Params!$B$16 -> 12 | I34: L | J34: =ROUND(Global_Params!$B$17*(1+Global_Params!$B$18*(B34-1))*Maps!$H$8,0) -> 247 | K34: =J34-L34-M34 -> 187 | L34: =ROUND(J34*(Global_Params!$B$19+(Global_Params!$B$20-Global_Params!$B$19)*(B34-1)/(Global_Params!$B$7-1)),0) -> 60 | M34: =ROUND(J34*IF(Maps!$G$8="Yes",Global_Params!$B$21,0),0) -> 0 | N34: =MAX(2,ROUND(E34/45,0)) -> 16 | O34: =MAX(1,MIN(Global_Params!$B$26,ROUND(F34/50,0))) -> 3 | P34: =ROUND(N34*0.6,0) -> 10 | Q34: =ROUND(E34/100*Global_Params!$B$25,0) -> 302 | R34: =Maps!$F$8 -> Minerals | S34: =Growth_Curve!$B$10 -> 0.89 | T34: =IF(B34<Global_Params!$B$30,0,MAX(1,ROUND(E34/260,0))) -> 3 | U34: =IF(T34=0,"-","R") -> R | V34: =IF(T34=0,0,ROUND(C34/2*Global_Params!$B$31,0)) -> 14 | W34: =IF(T34=0,0,ROUND(D34/2*Global_Params!$B$31,0)) -> 8 | X34: =IF(T34=0,0,Global_Params!$B$32) -> 4 | Y34: =T34*Global_Params!$B$33 -> 30
A35: 4 | B35: 7 | C35: =MIN(Maps!$C$8-2,MAX(C34+2,ROUND(Maps!$C$8*Growth_Curve!$B$11/2,0)*2)) -> 38 | D35: =MIN(Maps!$D$8,MAX(D34,ROUND(Maps!$D$8*Growth_Curve!$B$11/2,0)*2)) -> 22 | E35: =C35*D35 -> 836 | F35: =E35-E34 -> 116 | G35: =ROUND(C35/2,0)+Global_Params!$B$16 -> 21 | H35: =ROUND(D35/2,0)+Global_Params!$B$16 -> 13 | I35: R | J35: =ROUND(Global_Params!$B$17*(1+Global_Params!$B$18*(B35-1))*Maps!$H$8,0) -> 270 | K35: =J35-L35-M35 -> 197 | L35: =ROUND(J35*(Global_Params!$B$19+(Global_Params!$B$20-Global_Params!$B$19)*(B35-1)/(Global_Params!$B$7-1)),0) -> 73 | M35: =ROUND(J35*IF(Maps!$G$8="Yes",Global_Params!$B$21,0),0) -> 0 | N35: =MAX(2,ROUND(E35/45,0)) -> 19 | O35: =MAX(1,MIN(Global_Params!$B$26,ROUND(F35/50,0))) -> 2 | P35: =ROUND(N35*0.6,0) -> 11 | Q35: =ROUND(E35/100*Global_Params!$B$25,0) -> 351 | R35: =Maps!$F$8 -> Minerals | S35: =Growth_Curve!$B$11 -> 0.96 | T35: =IF(B35<Global_Params!$B$30,0,MAX(1,ROUND(E35/260,0))) -> 3 | U35: =IF(T35=0,"-","L") -> L | V35: =IF(T35=0,0,ROUND(C35/2*Global_Params!$B$31,0)) -> 15 | W35: =IF(T35=0,0,ROUND(D35/2*Global_Params!$B$31,0)) -> 9 | X35: =IF(T35=0,0,Global_Params!$B$32) -> 4 | Y35: =T35*Global_Params!$B$33 -> 30
A36: 4 | B36: 8 | C36: =Maps!$C$8 -> 40 | D36: =Maps!$D$8 -> 22 | E36: =C36*D36 -> 880 | F36: =E36-E35 -> 44 | G36: =ROUND(C36/2,0)+Global_Params!$B$16 -> 22 | H36: =ROUND(D36/2,0)+Global_Params!$B$16 -> 13 | I36: L | J36: =ROUND(Global_Params!$B$17*(1+Global_Params!$B$18*(B36-1))*Maps!$H$8,0) -> 294 | K36: =J36-L36-M36 -> 206 | L36: =ROUND(J36*(Global_Params!$B$19+(Global_Params!$B$20-Global_Params!$B$19)*(B36-1)/(Global_Params!$B$7-1)),0) -> 88 | M36: =ROUND(J36*IF(Maps!$G$8="Yes",Global_Params!$B$21,0),0) -> 0 | N36: =MAX(2,ROUND(E36/45,0)) -> 20 | O36: =MAX(1,MIN(Global_Params!$B$26,ROUND(F36/50,0))) -> 1 | P36: =ROUND(N36*0.6,0) -> 12 | Q36: =ROUND(E36/100*Global_Params!$B$25,0) -> 370 | R36: =Maps!$F$8 -> Minerals | S36: =Growth_Curve!$B$12 -> 1 | T36: =IF(B36<Global_Params!$B$30,0,MAX(1,ROUND(E36/260,0))) -> 3 | U36: =IF(T36=0,"-","R") -> R | V36: =IF(T36=0,0,ROUND(C36/2*Global_Params!$B$31,0)) -> 16 | W36: =IF(T36=0,0,ROUND(D36/2*Global_Params!$B$31,0)) -> 9 | X36: =IF(T36=0,0,Global_Params!$B$32) -> 4 | Y36: =T36*Global_Params!$B$33 -> 30
A37: 5 | B37: 1 | C37: =MIN(Maps!$C$9-2,ROUND(Maps!$C$9*Growth_Curve!$B$5/2,0)*2) -> 18 | D37: =MIN(Maps!$D$9,ROUND(Maps!$D$9*Growth_Curve!$B$5/2,0)*2) -> 10 | E37: =C37*D37 -> 180 | F37: =E37 -> 180 | G37: =ROUND(C37/2,0)+Global_Params!$B$16 -> 11 | H37: =ROUND(D37/2,0)+Global_Params!$B$16 -> 7 | I37: L | J37: =ROUND(Global_Params!$B$17*(1+Global_Params!$B$18*(B37-1))*Maps!$H$9,0) -> 140 | K37: =J37-L37-M37 -> 105 | L37: =ROUND(J37*(Global_Params!$B$19+(Global_Params!$B$20-Global_Params!$B$19)*(B37-1)/(Global_Params!$B$7-1)),0) -> 14 | M37: =ROUND(J37*IF(Maps!$G$9="Yes",Global_Params!$B$21,0),0) -> 21 | N37: =MAX(2,ROUND(E37/45,0)) -> 4 | O37: =1 -> 1 | P37: =ROUND(N37*0.6,0) -> 2 | Q37: =ROUND(E37/100*Global_Params!$B$25,0) -> 76 | R37: =Maps!$F$9 -> Crystals | S37: =Growth_Curve!$B$5 -> 0.4 | T37: =IF(B37<Global_Params!$B$30,0,MAX(1,ROUND(E37/260,0))) -> 0 | U37: =IF(T37=0,"-","R") -> - | V37: =IF(T37=0,0,ROUND(C37/2*Global_Params!$B$31,0)) -> 0 | W37: =IF(T37=0,0,ROUND(D37/2*Global_Params!$B$31,0)) -> 0 | X37: =IF(T37=0,0,Global_Params!$B$32) -> 0 | Y37: =T37*Global_Params!$B$33 -> 0
A38: 5 | B38: 2 | C38: =MIN(Maps!$C$9-2,MAX(C37+2,ROUND(Maps!$C$9*Growth_Curve!$B$6/2,0)*2)) -> 20 | D38: =MIN(Maps!$D$9,MAX(D37,ROUND(Maps!$D$9*Growth_Curve!$B$6/2,0)*2)) -> 12 | E38: =C38*D38 -> 240 | F38: =E38-E37 -> 60 | G38: =ROUND(C38/2,0)+Global_Params!$B$16 -> 12 | H38: =ROUND(D38/2,0)+Global_Params!$B$16 -> 8 | I38: R | J38: =ROUND(Global_Params!$B$17*(1+Global_Params!$B$18*(B38-1))*Maps!$H$9,0) -> 165 | K38: =J38-L38-M38 -> 119 | L38: =ROUND(J38*(Global_Params!$B$19+(Global_Params!$B$20-Global_Params!$B$19)*(B38-1)/(Global_Params!$B$7-1)),0) -> 21 | M38: =ROUND(J38*IF(Maps!$G$9="Yes",Global_Params!$B$21,0),0) -> 25 | N38: =MAX(2,ROUND(E38/45,0)) -> 5 | O38: =MAX(1,MIN(Global_Params!$B$26,ROUND(F38/50,0))) -> 1 | P38: =ROUND(N38*0.6,0) -> 3 | Q38: =ROUND(E38/100*Global_Params!$B$25,0) -> 101 | R38: =Maps!$F$9 -> Crystals | S38: =Growth_Curve!$B$6 -> 0.46 | T38: =IF(B38<Global_Params!$B$30,0,MAX(1,ROUND(E38/260,0))) -> 0 | U38: =IF(T38=0,"-","L") -> - | V38: =IF(T38=0,0,ROUND(C38/2*Global_Params!$B$31,0)) -> 0 | W38: =IF(T38=0,0,ROUND(D38/2*Global_Params!$B$31,0)) -> 0 | X38: =IF(T38=0,0,Global_Params!$B$32) -> 0 | Y38: =T38*Global_Params!$B$33 -> 0
A39: 5 | B39: 3 | C39: =MIN(Maps!$C$9-2,MAX(C38+2,ROUND(Maps!$C$9*Growth_Curve!$B$7/2,0)*2)) -> 24 | D39: =MIN(Maps!$D$9,MAX(D38,ROUND(Maps!$D$9*Growth_Curve!$B$7/2,0)*2)) -> 12 | E39: =C39*D39 -> 288 | F39: =E39-E38 -> 48 | G39: =ROUND(C39/2,0)+Global_Params!$B$16 -> 14 | H39: =ROUND(D39/2,0)+Global_Params!$B$16 -> 8 | I39: T | J39: =ROUND(Global_Params!$B$17*(1+Global_Params!$B$18*(B39-1))*Maps!$H$9,0) -> 190 | K39: =J39-L39-M39 -> 131 | L39: =ROUND(J39*(Global_Params!$B$19+(Global_Params!$B$20-Global_Params!$B$19)*(B39-1)/(Global_Params!$B$7-1)),0) -> 30 | M39: =ROUND(J39*IF(Maps!$G$9="Yes",Global_Params!$B$21,0),0) -> 29 | N39: =MAX(2,ROUND(E39/45,0)) -> 6 | O39: =MAX(1,MIN(Global_Params!$B$26,ROUND(F39/50,0))) -> 1 | P39: =ROUND(N39*0.6,0) -> 4 | Q39: =ROUND(E39/100*Global_Params!$B$25,0) -> 121 | R39: =Maps!$F$9 -> Crystals | S39: =Growth_Curve!$B$7 -> 0.54 | T39: =IF(B39<Global_Params!$B$30,0,MAX(1,ROUND(E39/260,0))) -> 0 | U39: =IF(T39=0,"-","B") -> - | V39: =IF(T39=0,0,ROUND(C39/2*Global_Params!$B$31,0)) -> 0 | W39: =IF(T39=0,0,ROUND(D39/2*Global_Params!$B$31,0)) -> 0 | X39: =IF(T39=0,0,Global_Params!$B$32) -> 0 | Y39: =T39*Global_Params!$B$33 -> 0
A40: 5 | B40: 4 | C40: =MIN(Maps!$C$9-2,MAX(C39+2,ROUND(Maps!$C$9*Growth_Curve!$B$8/2,0)*2)) -> 30 | D40: =MIN(Maps!$D$9,MAX(D39,ROUND(Maps!$D$9*Growth_Curve!$B$8/2,0)*2)) -> 16 | E40: =C40*D40 -> 480 | F40: =E40-E39 -> 192 | G40: =ROUND(C40/2,0)+Global_Params!$B$16 -> 17 | H40: =ROUND(D40/2,0)+Global_Params!$B$16 -> 10 | I40: B | J40: =ROUND(Global_Params!$B$17*(1+Global_Params!$B$18*(B40-1))*Maps!$H$9,0) -> 216 | K40: =J40-L40-M40 -> 144 | L40: =ROUND(J40*(Global_Params!$B$19+(Global_Params!$B$20-Global_Params!$B$19)*(B40-1)/(Global_Params!$B$7-1)),0) -> 40 | M40: =ROUND(J40*IF(Maps!$G$9="Yes",Global_Params!$B$21,0),0) -> 32 | N40: =MAX(2,ROUND(E40/45,0)) -> 11 | O40: =MAX(1,MIN(Global_Params!$B$26,ROUND(F40/50,0))) -> 3 | P40: =ROUND(N40*0.6,0) -> 7 | Q40: =ROUND(E40/100*Global_Params!$B$25,0) -> 202 | R40: =Maps!$F$9 -> Crystals | S40: =Growth_Curve!$B$8 -> 0.66 | T40: =IF(B40<Global_Params!$B$30,0,MAX(1,ROUND(E40/260,0))) -> 0 | U40: =IF(T40=0,"-","T") -> - | V40: =IF(T40=0,0,ROUND(C40/2*Global_Params!$B$31,0)) -> 0 | W40: =IF(T40=0,0,ROUND(D40/2*Global_Params!$B$31,0)) -> 0 | X40: =IF(T40=0,0,Global_Params!$B$32) -> 0 | Y40: =T40*Global_Params!$B$33 -> 0
A41: 5 | B41: 5 | C41: =MIN(Maps!$C$9-2,MAX(C40+2,ROUND(Maps!$C$9*Growth_Curve!$B$9/2,0)*2)) -> 34 | D41: =MIN(Maps!$D$9,MAX(D40,ROUND(Maps!$D$9*Growth_Curve!$B$9/2,0)*2)) -> 18 | E41: =C41*D41 -> 612 | F41: =E41-E40 -> 132 | G41: =ROUND(C41/2,0)+Global_Params!$B$16 -> 19 | H41: =ROUND(D41/2,0)+Global_Params!$B$16 -> 11 | I41: L | J41: =ROUND(Global_Params!$B$17*(1+Global_Params!$B$18*(B41-1))*Maps!$H$9,0) -> 241 | K41: =J41-L41-M41 -> 153 | L41: =ROUND(J41*(Global_Params!$B$19+(Global_Params!$B$20-Global_Params!$B$19)*(B41-1)/(Global_Params!$B$7-1)),0) -> 52 | M41: =ROUND(J41*IF(Maps!$G$9="Yes",Global_Params!$B$21,0),0) -> 36 | N41: =MAX(2,ROUND(E41/45,0)) -> 14 | O41: =MAX(1,MIN(Global_Params!$B$26,ROUND(F41/50,0))) -> 3 | P41: =ROUND(N41*0.6,0) -> 8 | Q41: =ROUND(E41/100*Global_Params!$B$25,0) -> 257 | R41: =Maps!$F$9 -> Crystals | S41: =Growth_Curve!$B$9 -> 0.79 | T41: =IF(B41<Global_Params!$B$30,0,MAX(1,ROUND(E41/260,0))) -> 2 | U41: =IF(T41=0,"-","R") -> R | V41: =IF(T41=0,0,ROUND(C41/2*Global_Params!$B$31,0)) -> 14 | W41: =IF(T41=0,0,ROUND(D41/2*Global_Params!$B$31,0)) -> 7 | X41: =IF(T41=0,0,Global_Params!$B$32) -> 4 | Y41: =T41*Global_Params!$B$33 -> 20
A42: 5 | B42: 6 | C42: =MIN(Maps!$C$9-2,MAX(C41+2,ROUND(Maps!$C$9*Growth_Curve!$B$10/2,0)*2)) -> 40 | D42: =MIN(Maps!$D$9,MAX(D41,ROUND(Maps!$D$9*Growth_Curve!$B$10/2,0)*2)) -> 22 | E42: =C42*D42 -> 880 | F42: =E42-E41 -> 268 | G42: =ROUND(C42/2,0)+Global_Params!$B$16 -> 22 | H42: =ROUND(D42/2,0)+Global_Params!$B$16 -> 13 | I42: R | J42: =ROUND(Global_Params!$B$17*(1+Global_Params!$B$18*(B42-1))*Maps!$H$9,0) -> 266 | K42: =J42-L42-M42 -> 161 | L42: =ROUND(J42*(Global_Params!$B$19+(Global_Params!$B$20-Global_Params!$B$19)*(B42-1)/(Global_Params!$B$7-1)),0) -> 65 | M42: =ROUND(J42*IF(Maps!$G$9="Yes",Global_Params!$B$21,0),0) -> 40 | N42: =MAX(2,ROUND(E42/45,0)) -> 20 | O42: =MAX(1,MIN(Global_Params!$B$26,ROUND(F42/50,0))) -> 3 | P42: =ROUND(N42*0.6,0) -> 12 | Q42: =ROUND(E42/100*Global_Params!$B$25,0) -> 370 | R42: =Maps!$F$9 -> Crystals | S42: =Growth_Curve!$B$10 -> 0.89 | T42: =IF(B42<Global_Params!$B$30,0,MAX(1,ROUND(E42/260,0))) -> 3 | U42: =IF(T42=0,"-","L") -> L | V42: =IF(T42=0,0,ROUND(C42/2*Global_Params!$B$31,0)) -> 16 | W42: =IF(T42=0,0,ROUND(D42/2*Global_Params!$B$31,0)) -> 9 | X42: =IF(T42=0,0,Global_Params!$B$32) -> 4 | Y42: =T42*Global_Params!$B$33 -> 30
A43: 5 | B43: 7 | C43: =MIN(Maps!$C$9-2,MAX(C42+2,ROUND(Maps!$C$9*Growth_Curve!$B$11/2,0)*2)) -> 42 | D43: =MIN(Maps!$D$9,MAX(D42,ROUND(Maps!$D$9*Growth_Curve!$B$11/2,0)*2)) -> 24 | E43: =C43*D43 -> 1008 | F43: =E43-E42 -> 128 | G43: =ROUND(C43/2,0)+Global_Params!$B$16 -> 23 | H43: =ROUND(D43/2,0)+Global_Params!$B$16 -> 14 | I43: L | J43: =ROUND(Global_Params!$B$17*(1+Global_Params!$B$18*(B43-1))*Maps!$H$9,0) -> 291 | K43: =J43-L43-M43 -> 168 | L43: =ROUND(J43*(Global_Params!$B$19+(Global_Params!$B$20-Global_Params!$B$19)*(B43-1)/(Global_Params!$B$7-1)),0) -> 79 | M43: =ROUND(J43*IF(Maps!$G$9="Yes",Global_Params!$B$21,0),0) -> 44 | N43: =MAX(2,ROUND(E43/45,0)) -> 22 | O43: =MAX(1,MIN(Global_Params!$B$26,ROUND(F43/50,0))) -> 3 | P43: =ROUND(N43*0.6,0) -> 13 | Q43: =ROUND(E43/100*Global_Params!$B$25,0) -> 423 | R43: =Maps!$F$9 -> Crystals | S43: =Growth_Curve!$B$11 -> 0.96 | T43: =IF(B43<Global_Params!$B$30,0,MAX(1,ROUND(E43/260,0))) -> 4 | U43: =IF(T43=0,"-","R") -> R | V43: =IF(T43=0,0,ROUND(C43/2*Global_Params!$B$31,0)) -> 17 | W43: =IF(T43=0,0,ROUND(D43/2*Global_Params!$B$31,0)) -> 10 | X43: =IF(T43=0,0,Global_Params!$B$32) -> 4 | Y43: =T43*Global_Params!$B$33 -> 40
A44: 5 | B44: 8 | C44: =Maps!$C$9 -> 44 | D44: =Maps!$D$9 -> 24 | E44: =C44*D44 -> 1056 | F44: =E44-E43 -> 48 | G44: =ROUND(C44/2,0)+Global_Params!$B$16 -> 24 | H44: =ROUND(D44/2,0)+Global_Params!$B$16 -> 14 | I44: R | J44: =ROUND(Global_Params!$B$17*(1+Global_Params!$B$18*(B44-1))*Maps!$H$9,0) -> 316 | K44: =J44-L44-M44 -> 174 | L44: =ROUND(J44*(Global_Params!$B$19+(Global_Params!$B$20-Global_Params!$B$19)*(B44-1)/(Global_Params!$B$7-1)),0) -> 95 | M44: =ROUND(J44*IF(Maps!$G$9="Yes",Global_Params!$B$21,0),0) -> 47 | N44: =MAX(2,ROUND(E44/45,0)) -> 23 | O44: =MAX(1,MIN(Global_Params!$B$26,ROUND(F44/50,0))) -> 1 | P44: =ROUND(N44*0.6,0) -> 14 | Q44: =ROUND(E44/100*Global_Params!$B$25,0) -> 444 | R44: =Maps!$F$9 -> Crystals | S44: =Growth_Curve!$B$12 -> 1 | T44: =IF(B44<Global_Params!$B$30,0,MAX(1,ROUND(E44/260,0))) -> 4 | U44: =IF(T44=0,"-","L") -> L | V44: =IF(T44=0,0,ROUND(C44/2*Global_Params!$B$31,0)) -> 18 | W44: =IF(T44=0,0,ROUND(D44/2*Global_Params!$B$31,0)) -> 10 | X44: =IF(T44=0,0,Global_Params!$B$32) -> 4 | Y44: =T44*Global_Params!$B$33 -> 40
A45: 6 | B45: 1 | C45: =MIN(Maps!$C$10-2,ROUND(Maps!$C$10*Growth_Curve!$B$5/2,0)*2) -> 20 | D45: =MIN(Maps!$D$10,ROUND(Maps!$D$10*Growth_Curve!$B$5/2,0)*2) -> 10 | E45: =C45*D45 -> 200 | F45: =E45 -> 200 | G45: =ROUND(C45/2,0)+Global_Params!$B$16 -> 12 | H45: =ROUND(D45/2,0)+Global_Params!$B$16 -> 7 | I45: R | J45: =ROUND(Global_Params!$B$17*(1+Global_Params!$B$18*(B45-1))*Maps!$H$10,0) -> 150 | K45: =J45-L45-M45 -> 112 | L45: =ROUND(J45*(Global_Params!$B$19+(Global_Params!$B$20-Global_Params!$B$19)*(B45-1)/(Global_Params!$B$7-1)),0) -> 15 | M45: =ROUND(J45*IF(Maps!$G$10="Yes",Global_Params!$B$21,0),0) -> 23 | N45: =MAX(2,ROUND(E45/45,0)) -> 4 | O45: =1 -> 1 | P45: =ROUND(N45*0.6,0) -> 2 | Q45: =ROUND(E45/100*Global_Params!$B$25,0) -> 84 | R45: =Maps!$F$10 -> Flowers | S45: =Growth_Curve!$B$5 -> 0.4 | T45: =IF(B45<Global_Params!$B$30,0,MAX(1,ROUND(E45/260,0))) -> 0 | U45: =IF(T45=0,"-","L") -> - | V45: =IF(T45=0,0,ROUND(C45/2*Global_Params!$B$31,0)) -> 0 | W45: =IF(T45=0,0,ROUND(D45/2*Global_Params!$B$31,0)) -> 0 | X45: =IF(T45=0,0,Global_Params!$B$32) -> 0 | Y45: =T45*Global_Params!$B$33 -> 0
A46: 6 | B46: 2 | C46: =MIN(Maps!$C$10-2,MAX(C45+2,ROUND(Maps!$C$10*Growth_Curve!$B$6/2,0)*2)) -> 24 | D46: =MIN(Maps!$D$10,MAX(D45,ROUND(Maps!$D$10*Growth_Curve!$B$6/2,0)*2)) -> 12 | E46: =C46*D46 -> 288 | F46: =E46-E45 -> 88 | G46: =ROUND(C46/2,0)+Global_Params!$B$16 -> 14 | H46: =ROUND(D46/2,0)+Global_Params!$B$16 -> 8 | I46: T | J46: =ROUND(Global_Params!$B$17*(1+Global_Params!$B$18*(B46-1))*Maps!$H$10,0) -> 177 | K46: =J46-L46-M46 -> 127 | L46: =ROUND(J46*(Global_Params!$B$19+(Global_Params!$B$20-Global_Params!$B$19)*(B46-1)/(Global_Params!$B$7-1)),0) -> 23 | M46: =ROUND(J46*IF(Maps!$G$10="Yes",Global_Params!$B$21,0),0) -> 27 | N46: =MAX(2,ROUND(E46/45,0)) -> 6 | O46: =MAX(1,MIN(Global_Params!$B$26,ROUND(F46/50,0))) -> 2 | P46: =ROUND(N46*0.6,0) -> 4 | Q46: =ROUND(E46/100*Global_Params!$B$25,0) -> 121 | R46: =Maps!$F$10 -> Flowers | S46: =Growth_Curve!$B$6 -> 0.46 | T46: =IF(B46<Global_Params!$B$30,0,MAX(1,ROUND(E46/260,0))) -> 0 | U46: =IF(T46=0,"-","B") -> - | V46: =IF(T46=0,0,ROUND(C46/2*Global_Params!$B$31,0)) -> 0 | W46: =IF(T46=0,0,ROUND(D46/2*Global_Params!$B$31,0)) -> 0 | X46: =IF(T46=0,0,Global_Params!$B$32) -> 0 | Y46: =T46*Global_Params!$B$33 -> 0
A47: 6 | B47: 3 | C47: =MIN(Maps!$C$10-2,MAX(C46+2,ROUND(Maps!$C$10*Growth_Curve!$B$7/2,0)*2)) -> 28 | D47: =MIN(Maps!$D$10,MAX(D46,ROUND(Maps!$D$10*Growth_Curve!$B$7/2,0)*2)) -> 14 | E47: =C47*D47 -> 392 | F47: =E47-E46 -> 104 | G47: =ROUND(C47/2,0)+Global_Params!$B$16 -> 16 | H47: =ROUND(D47/2,0)+Global_Params!$B$16 -> 9 | I47: B | J47: =ROUND(Global_Params!$B$17*(1+Global_Params!$B$18*(B47-1))*Maps!$H$10,0) -> 204 | K47: =J47-L47-M47 -> 141 | L47: =ROUND(J47*(Global_Params!$B$19+(Global_Params!$B$20-Global_Params!$B$19)*(B47-1)/(Global_Params!$B$7-1)),0) -> 32 | M47: =ROUND(J47*IF(Maps!$G$10="Yes",Global_Params!$B$21,0),0) -> 31 | N47: =MAX(2,ROUND(E47/45,0)) -> 9 | O47: =MAX(1,MIN(Global_Params!$B$26,ROUND(F47/50,0))) -> 2 | P47: =ROUND(N47*0.6,0) -> 5 | Q47: =ROUND(E47/100*Global_Params!$B$25,0) -> 165 | R47: =Maps!$F$10 -> Flowers | S47: =Growth_Curve!$B$7 -> 0.54 | T47: =IF(B47<Global_Params!$B$30,0,MAX(1,ROUND(E47/260,0))) -> 0 | U47: =IF(T47=0,"-","T") -> - | V47: =IF(T47=0,0,ROUND(C47/2*Global_Params!$B$31,0)) -> 0 | W47: =IF(T47=0,0,ROUND(D47/2*Global_Params!$B$31,0)) -> 0 | X47: =IF(T47=0,0,Global_Params!$B$32) -> 0 | Y47: =T47*Global_Params!$B$33 -> 0
A48: 6 | B48: 4 | C48: =MIN(Maps!$C$10-2,MAX(C47+2,ROUND(Maps!$C$10*Growth_Curve!$B$8/2,0)*2)) -> 34 | D48: =MIN(Maps!$D$10,MAX(D47,ROUND(Maps!$D$10*Growth_Curve!$B$8/2,0)*2)) -> 18 | E48: =C48*D48 -> 612 | F48: =E48-E47 -> 220 | G48: =ROUND(C48/2,0)+Global_Params!$B$16 -> 19 | H48: =ROUND(D48/2,0)+Global_Params!$B$16 -> 11 | I48: L | J48: =ROUND(Global_Params!$B$17*(1+Global_Params!$B$18*(B48-1))*Maps!$H$10,0) -> 231 | K48: =J48-L48-M48 -> 153 | L48: =ROUND(J48*(Global_Params!$B$19+(Global_Params!$B$20-Global_Params!$B$19)*(B48-1)/(Global_Params!$B$7-1)),0) -> 43 | M48: =ROUND(J48*IF(Maps!$G$10="Yes",Global_Params!$B$21,0),0) -> 35 | N48: =MAX(2,ROUND(E48/45,0)) -> 14 | O48: =MAX(1,MIN(Global_Params!$B$26,ROUND(F48/50,0))) -> 3 | P48: =ROUND(N48*0.6,0) -> 8 | Q48: =ROUND(E48/100*Global_Params!$B$25,0) -> 257 | R48: =Maps!$F$10 -> Flowers | S48: =Growth_Curve!$B$8 -> 0.66 | T48: =IF(B48<Global_Params!$B$30,0,MAX(1,ROUND(E48/260,0))) -> 0 | U48: =IF(T48=0,"-","R") -> - | V48: =IF(T48=0,0,ROUND(C48/2*Global_Params!$B$31,0)) -> 0 | W48: =IF(T48=0,0,ROUND(D48/2*Global_Params!$B$31,0)) -> 0 | X48: =IF(T48=0,0,Global_Params!$B$32) -> 0 | Y48: =T48*Global_Params!$B$33 -> 0
A49: 6 | B49: 5 | C49: =MIN(Maps!$C$10-2,MAX(C48+2,ROUND(Maps!$C$10*Growth_Curve!$B$9/2,0)*2)) -> 40 | D49: =MIN(Maps!$D$10,MAX(D48,ROUND(Maps!$D$10*Growth_Curve!$B$9/2,0)*2)) -> 20 | E49: =C49*D49 -> 800 | F49: =E49-E48 -> 188 | G49: =ROUND(C49/2,0)+Global_Params!$B$16 -> 22 | H49: =ROUND(D49/2,0)+Global_Params!$B$16 -> 12 | I49: R | J49: =ROUND(Global_Params!$B$17*(1+Global_Params!$B$18*(B49-1))*Maps!$H$10,0) -> 258 | K49: =J49-L49-M49 -> 164 | L49: =ROUND(J49*(Global_Params!$B$19+(Global_Params!$B$20-Global_Params!$B$19)*(B49-1)/(Global_Params!$B$7-1)),0) -> 55 | M49: =ROUND(J49*IF(Maps!$G$10="Yes",Global_Params!$B$21,0),0) -> 39 | N49: =MAX(2,ROUND(E49/45,0)) -> 18 | O49: =MAX(1,MIN(Global_Params!$B$26,ROUND(F49/50,0))) -> 3 | P49: =ROUND(N49*0.6,0) -> 11 | Q49: =ROUND(E49/100*Global_Params!$B$25,0) -> 336 | R49: =Maps!$F$10 -> Flowers | S49: =Growth_Curve!$B$9 -> 0.79 | T49: =IF(B49<Global_Params!$B$30,0,MAX(1,ROUND(E49/260,0))) -> 3 | U49: =IF(T49=0,"-","L") -> L | V49: =IF(T49=0,0,ROUND(C49/2*Global_Params!$B$31,0)) -> 16 | W49: =IF(T49=0,0,ROUND(D49/2*Global_Params!$B$31,0)) -> 8 | X49: =IF(T49=0,0,Global_Params!$B$32) -> 4 | Y49: =T49*Global_Params!$B$33 -> 30
A50: 6 | B50: 6 | C50: =MIN(Maps!$C$10-2,MAX(C49+2,ROUND(Maps!$C$10*Growth_Curve!$B$10/2,0)*2)) -> 44 | D50: =MIN(Maps!$D$10,MAX(D49,ROUND(Maps!$D$10*Growth_Curve!$B$10/2,0)*2)) -> 24 | E50: =C50*D50 -> 1056 | F50: =E50-E49 -> 256 | G50: =ROUND(C50/2,0)+Global_Params!$B$16 -> 24 | H50: =ROUND(D50/2,0)+Global_Params!$B$16 -> 14 | I50: L | J50: =ROUND(Global_Params!$B$17*(1+Global_Params!$B$18*(B50-1))*Maps!$H$10,0) -> 285 | K50: =J50-L50-M50 -> 173 | L50: =ROUND(J50*(Global_Params!$B$19+(Global_Params!$B$20-Global_Params!$B$19)*(B50-1)/(Global_Params!$B$7-1)),0) -> 69 | M50: =ROUND(J50*IF(Maps!$G$10="Yes",Global_Params!$B$21,0),0) -> 43 | N50: =MAX(2,ROUND(E50/45,0)) -> 23 | O50: =MAX(1,MIN(Global_Params!$B$26,ROUND(F50/50,0))) -> 3 | P50: =ROUND(N50*0.6,0) -> 14 | Q50: =ROUND(E50/100*Global_Params!$B$25,0) -> 444 | R50: =Maps!$F$10 -> Flowers | S50: =Growth_Curve!$B$10 -> 0.89 | T50: =IF(B50<Global_Params!$B$30,0,MAX(1,ROUND(E50/260,0))) -> 4 | U50: =IF(T50=0,"-","R") -> R | V50: =IF(T50=0,0,ROUND(C50/2*Global_Params!$B$31,0)) -> 18 | W50: =IF(T50=0,0,ROUND(D50/2*Global_Params!$B$31,0)) -> 10 | X50: =IF(T50=0,0,Global_Params!$B$32) -> 4 | Y50: =T50*Global_Params!$B$33 -> 40
A51: 6 | B51: 7 | C51: =MIN(Maps!$C$10-2,MAX(C50+2,ROUND(Maps!$C$10*Growth_Curve!$B$11/2,0)*2)) -> 48 | D51: =MIN(Maps!$D$10,MAX(D50,ROUND(Maps!$D$10*Growth_Curve!$B$11/2,0)*2)) -> 24 | E51: =C51*D51 -> 1152 | F51: =E51-E50 -> 96 | G51: =ROUND(C51/2,0)+Global_Params!$B$16 -> 26 | H51: =ROUND(D51/2,0)+Global_Params!$B$16 -> 14 | I51: R | J51: =ROUND(Global_Params!$B$17*(1+Global_Params!$B$18*(B51-1))*Maps!$H$10,0) -> 312 | K51: =J51-L51-M51 -> 180 | L51: =ROUND(J51*(Global_Params!$B$19+(Global_Params!$B$20-Global_Params!$B$19)*(B51-1)/(Global_Params!$B$7-1)),0) -> 85 | M51: =ROUND(J51*IF(Maps!$G$10="Yes",Global_Params!$B$21,0),0) -> 47 | N51: =MAX(2,ROUND(E51/45,0)) -> 26 | O51: =MAX(1,MIN(Global_Params!$B$26,ROUND(F51/50,0))) -> 2 | P51: =ROUND(N51*0.6,0) -> 16 | Q51: =ROUND(E51/100*Global_Params!$B$25,0) -> 484 | R51: =Maps!$F$10 -> Flowers | S51: =Growth_Curve!$B$11 -> 0.96 | T51: =IF(B51<Global_Params!$B$30,0,MAX(1,ROUND(E51/260,0))) -> 4 | U51: =IF(T51=0,"-","L") -> L | V51: =IF(T51=0,0,ROUND(C51/2*Global_Params!$B$31,0)) -> 19 | W51: =IF(T51=0,0,ROUND(D51/2*Global_Params!$B$31,0)) -> 10 | X51: =IF(T51=0,0,Global_Params!$B$32) -> 4 | Y51: =T51*Global_Params!$B$33 -> 40
A52: 6 | B52: 8 | C52: =Maps!$C$10 -> 50 | D52: =Maps!$D$10 -> 26 | E52: =C52*D52 -> 1300 | F52: =E52-E51 -> 148 | G52: =ROUND(C52/2,0)+Global_Params!$B$16 -> 27 | H52: =ROUND(D52/2,0)+Global_Params!$B$16 -> 15 | I52: L | J52: =ROUND(Global_Params!$B$17*(1+Global_Params!$B$18*(B52-1))*Maps!$H$10,0) -> 339 | K52: =J52-L52-M52 -> 186 | L52: =ROUND(J52*(Global_Params!$B$19+(Global_Params!$B$20-Global_Params!$B$19)*(B52-1)/(Global_Params!$B$7-1)),0) -> 102 | M52: =ROUND(J52*IF(Maps!$G$10="Yes",Global_Params!$B$21,0),0) -> 51 | N52: =MAX(2,ROUND(E52/45,0)) -> 29 | O52: =MAX(1,MIN(Global_Params!$B$26,ROUND(F52/50,0))) -> 3 | P52: =ROUND(N52*0.6,0) -> 17 | Q52: =ROUND(E52/100*Global_Params!$B$25,0) -> 546 | R52: =Maps!$F$10 -> Flowers | S52: =Growth_Curve!$B$12 -> 1 | T52: =IF(B52<Global_Params!$B$30,0,MAX(1,ROUND(E52/260,0))) -> 5 | U52: =IF(T52=0,"-","R") -> R | V52: =IF(T52=0,0,ROUND(C52/2*Global_Params!$B$31,0)) -> 20 | W52: =IF(T52=0,0,ROUND(D52/2*Global_Params!$B$31,0)) -> 10 | X52: =IF(T52=0,0,Global_Params!$B$32) -> 4 | Y52: =T52*Global_Params!$B$33 -> 50
A53: 7 | B53: 1 | C53: =MIN(Maps!$C$11-2,ROUND(Maps!$C$11*Growth_Curve!$B$5/2,0)*2) -> 22 | D53: =MIN(Maps!$D$11,ROUND(Maps!$D$11*Growth_Curve!$B$5/2,0)*2) -> 12 | E53: =C53*D53 -> 264 | F53: =E53 -> 264 | G53: =ROUND(C53/2,0)+Global_Params!$B$16 -> 13 | H53: =ROUND(D53/2,0)+Global_Params!$B$16 -> 8 | I53: T | J53: =ROUND(Global_Params!$B$17*(1+Global_Params!$B$18*(B53-1))*Maps!$H$11,0) -> 160 | K53: =J53-L53-M53 -> 144 | L53: =ROUND(J53*(Global_Params!$B$19+(Global_Params!$B$20-Global_Params!$B$19)*(B53-1)/(Global_Params!$B$7-1)),0) -> 16 | M53: =ROUND(J53*IF(Maps!$G$11="Yes",Global_Params!$B$21,0),0) -> 0 | N53: =MAX(2,ROUND(E53/45,0)) -> 6 | O53: =1 -> 1 | P53: =ROUND(N53*0.6,0) -> 4 | Q53: =ROUND(E53/100*Global_Params!$B$25,0) -> 111 | R53: =Maps!$F$11 -> Minerals | S53: =Growth_Curve!$B$5 -> 0.4 | T53: =IF(B53<Global_Params!$B$30,0,MAX(1,ROUND(E53/260,0))) -> 0 | U53: =IF(T53=0,"-","B") -> - | V53: =IF(T53=0,0,ROUND(C53/2*Global_Params!$B$31,0)) -> 0 | W53: =IF(T53=0,0,ROUND(D53/2*Global_Params!$B$31,0)) -> 0 | X53: =IF(T53=0,0,Global_Params!$B$32) -> 0 | Y53: =T53*Global_Params!$B$33 -> 0
A54: 7 | B54: 2 | C54: =MIN(Maps!$C$11-2,MAX(C53+2,ROUND(Maps!$C$11*Growth_Curve!$B$6/2,0)*2)) -> 24 | D54: =MIN(Maps!$D$11,MAX(D53,ROUND(Maps!$D$11*Growth_Curve!$B$6/2,0)*2)) -> 12 | E54: =C54*D54 -> 288 | F54: =E54-E53 -> 24 | G54: =ROUND(C54/2,0)+Global_Params!$B$16 -> 14 | H54: =ROUND(D54/2,0)+Global_Params!$B$16 -> 8 | I54: B | J54: =ROUND(Global_Params!$B$17*(1+Global_Params!$B$18*(B54-1))*Maps!$H$11,0) -> 189 | K54: =J54-L54-M54 -> 165 | L54: =ROUND(J54*(Global_Params!$B$19+(Global_Params!$B$20-Global_Params!$B$19)*(B54-1)/(Global_Params!$B$7-1)),0) -> 24 | M54: =ROUND(J54*IF(Maps!$G$11="Yes",Global_Params!$B$21,0),0) -> 0 | N54: =MAX(2,ROUND(E54/45,0)) -> 6 | O54: =MAX(1,MIN(Global_Params!$B$26,ROUND(F54/50,0))) -> 1 | P54: =ROUND(N54*0.6,0) -> 4 | Q54: =ROUND(E54/100*Global_Params!$B$25,0) -> 121 | R54: =Maps!$F$11 -> Minerals | S54: =Growth_Curve!$B$6 -> 0.46 | T54: =IF(B54<Global_Params!$B$30,0,MAX(1,ROUND(E54/260,0))) -> 0 | U54: =IF(T54=0,"-","T") -> - | V54: =IF(T54=0,0,ROUND(C54/2*Global_Params!$B$31,0)) -> 0 | W54: =IF(T54=0,0,ROUND(D54/2*Global_Params!$B$31,0)) -> 0 | X54: =IF(T54=0,0,Global_Params!$B$32) -> 0 | Y54: =T54*Global_Params!$B$33 -> 0
A55: 7 | B55: 3 | C55: =MIN(Maps!$C$11-2,MAX(C54+2,ROUND(Maps!$C$11*Growth_Curve!$B$7/2,0)*2)) -> 30 | D55: =MIN(Maps!$D$11,MAX(D54,ROUND(Maps!$D$11*Growth_Curve!$B$7/2,0)*2)) -> 16 | E55: =C55*D55 -> 480 | F55: =E55-E54 -> 192 | G55: =ROUND(C55/2,0)+Global_Params!$B$16 -> 17 | H55: =ROUND(D55/2,0)+Global_Params!$B$16 -> 10 | I55: L | J55: =ROUND(Global_Params!$B$17*(1+Global_Params!$B$18*(B55-1))*Maps!$H$11,0) -> 218 | K55: =J55-L55-M55 -> 184 | L55: =ROUND(J55*(Global_Params!$B$19+(Global_Params!$B$20-Global_Params!$B$19)*(B55-1)/(Global_Params!$B$7-1)),0) -> 34 | M55: =ROUND(J55*IF(Maps!$G$11="Yes",Global_Params!$B$21,0),0) -> 0 | N55: =MAX(2,ROUND(E55/45,0)) -> 11 | O55: =MAX(1,MIN(Global_Params!$B$26,ROUND(F55/50,0))) -> 3 | P55: =ROUND(N55*0.6,0) -> 7 | Q55: =ROUND(E55/100*Global_Params!$B$25,0) -> 202 | R55: =Maps!$F$11 -> Minerals | S55: =Growth_Curve!$B$7 -> 0.54 | T55: =IF(B55<Global_Params!$B$30,0,MAX(1,ROUND(E55/260,0))) -> 0 | U55: =IF(T55=0,"-","R") -> - | V55: =IF(T55=0,0,ROUND(C55/2*Global_Params!$B$31,0)) -> 0 | W55: =IF(T55=0,0,ROUND(D55/2*Global_Params!$B$31,0)) -> 0 | X55: =IF(T55=0,0,Global_Params!$B$32) -> 0 | Y55: =T55*Global_Params!$B$33 -> 0
A56: 7 | B56: 4 | C56: =MIN(Maps!$C$11-2,MAX(C55+2,ROUND(Maps!$C$11*Growth_Curve!$B$8/2,0)*2)) -> 36 | D56: =MIN(Maps!$D$11,MAX(D55,ROUND(Maps!$D$11*Growth_Curve!$B$8/2,0)*2)) -> 18 | E56: =C56*D56 -> 648 | F56: =E56-E55 -> 168 | G56: =ROUND(C56/2,0)+Global_Params!$B$16 -> 20 | H56: =ROUND(D56/2,0)+Global_Params!$B$16 -> 11 | I56: R | J56: =ROUND(Global_Params!$B$17*(1+Global_Params!$B$18*(B56-1))*Maps!$H$11,0) -> 246 | K56: =J56-L56-M56 -> 200 | L56: =ROUND(J56*(Global_Params!$B$19+(Global_Params!$B$20-Global_Params!$B$19)*(B56-1)/(Global_Params!$B$7-1)),0) -> 46 | M56: =ROUND(J56*IF(Maps!$G$11="Yes",Global_Params!$B$21,0),0) -> 0 | N56: =MAX(2,ROUND(E56/45,0)) -> 14 | O56: =MAX(1,MIN(Global_Params!$B$26,ROUND(F56/50,0))) -> 3 | P56: =ROUND(N56*0.6,0) -> 8 | Q56: =ROUND(E56/100*Global_Params!$B$25,0) -> 272 | R56: =Maps!$F$11 -> Minerals | S56: =Growth_Curve!$B$8 -> 0.66 | T56: =IF(B56<Global_Params!$B$30,0,MAX(1,ROUND(E56/260,0))) -> 0 | U56: =IF(T56=0,"-","L") -> - | V56: =IF(T56=0,0,ROUND(C56/2*Global_Params!$B$31,0)) -> 0 | W56: =IF(T56=0,0,ROUND(D56/2*Global_Params!$B$31,0)) -> 0 | X56: =IF(T56=0,0,Global_Params!$B$32) -> 0 | Y56: =T56*Global_Params!$B$33 -> 0
A57: 7 | B57: 5 | C57: =MIN(Maps!$C$11-2,MAX(C56+2,ROUND(Maps!$C$11*Growth_Curve!$B$9/2,0)*2)) -> 42 | D57: =MIN(Maps!$D$11,MAX(D56,ROUND(Maps!$D$11*Growth_Curve!$B$9/2,0)*2)) -> 22 | E57: =C57*D57 -> 924 | F57: =E57-E56 -> 276 | G57: =ROUND(C57/2,0)+Global_Params!$B$16 -> 23 | H57: =ROUND(D57/2,0)+Global_Params!$B$16 -> 13 | I57: L | J57: =ROUND(Global_Params!$B$17*(1+Global_Params!$B$18*(B57-1))*Maps!$H$11,0) -> 275 | K57: =J57-L57-M57 -> 216 | L57: =ROUND(J57*(Global_Params!$B$19+(Global_Params!$B$20-Global_Params!$B$19)*(B57-1)/(Global_Params!$B$7-1)),0) -> 59 | M57: =ROUND(J57*IF(Maps!$G$11="Yes",Global_Params!$B$21,0),0) -> 0 | N57: =MAX(2,ROUND(E57/45,0)) -> 21 | O57: =MAX(1,MIN(Global_Params!$B$26,ROUND(F57/50,0))) -> 3 | P57: =ROUND(N57*0.6,0) -> 13 | Q57: =ROUND(E57/100*Global_Params!$B$25,0) -> 388 | R57: =Maps!$F$11 -> Minerals | S57: =Growth_Curve!$B$9 -> 0.79 | T57: =IF(B57<Global_Params!$B$30,0,MAX(1,ROUND(E57/260,0))) -> 4 | U57: =IF(T57=0,"-","R") -> R | V57: =IF(T57=0,0,ROUND(C57/2*Global_Params!$B$31,0)) -> 17 | W57: =IF(T57=0,0,ROUND(D57/2*Global_Params!$B$31,0)) -> 9 | X57: =IF(T57=0,0,Global_Params!$B$32) -> 4 | Y57: =T57*Global_Params!$B$33 -> 40
A58: 7 | B58: 6 | C58: =MIN(Maps!$C$11-2,MAX(C57+2,ROUND(Maps!$C$11*Growth_Curve!$B$10/2,0)*2)) -> 48 | D58: =MIN(Maps!$D$11,MAX(D57,ROUND(Maps!$D$11*Growth_Curve!$B$10/2,0)*2)) -> 24 | E58: =C58*D58 -> 1152 | F58: =E58-E57 -> 228 | G58: =ROUND(C58/2,0)+Global_Params!$B$16 -> 26 | H58: =ROUND(D58/2,0)+Global_Params!$B$16 -> 14 | I58: R | J58: =ROUND(Global_Params!$B$17*(1+Global_Params!$B$18*(B58-1))*Maps!$H$11,0) -> 304 | K58: =J58-L58-M58 -> 230 | L58: =ROUND(J58*(Global_Params!$B$19+(Global_Params!$B$20-Global_Params!$B$19)*(B58-1)/(Global_Params!$B$7-1)),0) -> 74 | M58: =ROUND(J58*IF(Maps!$G$11="Yes",Global_Params!$B$21,0),0) -> 0 | N58: =MAX(2,ROUND(E58/45,0)) -> 26 | O58: =MAX(1,MIN(Global_Params!$B$26,ROUND(F58/50,0))) -> 3 | P58: =ROUND(N58*0.6,0) -> 16 | Q58: =ROUND(E58/100*Global_Params!$B$25,0) -> 484 | R58: =Maps!$F$11 -> Minerals | S58: =Growth_Curve!$B$10 -> 0.89 | T58: =IF(B58<Global_Params!$B$30,0,MAX(1,ROUND(E58/260,0))) -> 4 | U58: =IF(T58=0,"-","L") -> L | V58: =IF(T58=0,0,ROUND(C58/2*Global_Params!$B$31,0)) -> 19 | W58: =IF(T58=0,0,ROUND(D58/2*Global_Params!$B$31,0)) -> 10 | X58: =IF(T58=0,0,Global_Params!$B$32) -> 4 | Y58: =T58*Global_Params!$B$33 -> 40
A59: 7 | B59: 7 | C59: =MIN(Maps!$C$11-2,MAX(C58+2,ROUND(Maps!$C$11*Growth_Curve!$B$11/2,0)*2)) -> 52 | D59: =MIN(Maps!$D$11,MAX(D58,ROUND(Maps!$D$11*Growth_Curve!$B$11/2,0)*2)) -> 26 | E59: =C59*D59 -> 1352 | F59: =E59-E58 -> 200 | G59: =ROUND(C59/2,0)+Global_Params!$B$16 -> 28 | H59: =ROUND(D59/2,0)+Global_Params!$B$16 -> 15 | I59: L | J59: =ROUND(Global_Params!$B$17*(1+Global_Params!$B$18*(B59-1))*Maps!$H$11,0) -> 333 | K59: =J59-L59-M59 -> 243 | L59: =ROUND(J59*(Global_Params!$B$19+(Global_Params!$B$20-Global_Params!$B$19)*(B59-1)/(Global_Params!$B$7-1)),0) -> 90 | M59: =ROUND(J59*IF(Maps!$G$11="Yes",Global_Params!$B$21,0),0) -> 0 | N59: =MAX(2,ROUND(E59/45,0)) -> 30 | O59: =MAX(1,MIN(Global_Params!$B$26,ROUND(F59/50,0))) -> 3 | P59: =ROUND(N59*0.6,0) -> 18 | Q59: =ROUND(E59/100*Global_Params!$B$25,0) -> 568 | R59: =Maps!$F$11 -> Minerals | S59: =Growth_Curve!$B$11 -> 0.96 | T59: =IF(B59<Global_Params!$B$30,0,MAX(1,ROUND(E59/260,0))) -> 5 | U59: =IF(T59=0,"-","R") -> R | V59: =IF(T59=0,0,ROUND(C59/2*Global_Params!$B$31,0)) -> 21 | W59: =IF(T59=0,0,ROUND(D59/2*Global_Params!$B$31,0)) -> 10 | X59: =IF(T59=0,0,Global_Params!$B$32) -> 4 | Y59: =T59*Global_Params!$B$33 -> 50
A60: 7 | B60: 8 | C60: =Maps!$C$11 -> 54 | D60: =Maps!$D$11 -> 28 | E60: =C60*D60 -> 1512 | F60: =E60-E59 -> 160 | G60: =ROUND(C60/2,0)+Global_Params!$B$16 -> 29 | H60: =ROUND(D60/2,0)+Global_Params!$B$16 -> 16 | I60: R | J60: =ROUND(Global_Params!$B$17*(1+Global_Params!$B$18*(B60-1))*Maps!$H$11,0) -> 362 | K60: =J60-L60-M60 -> 253 | L60: =ROUND(J60*(Global_Params!$B$19+(Global_Params!$B$20-Global_Params!$B$19)*(B60-1)/(Global_Params!$B$7-1)),0) -> 109 | M60: =ROUND(J60*IF(Maps!$G$11="Yes",Global_Params!$B$21,0),0) -> 0 | N60: =MAX(2,ROUND(E60/45,0)) -> 34 | O60: =MAX(1,MIN(Global_Params!$B$26,ROUND(F60/50,0))) -> 3 | P60: =ROUND(N60*0.6,0) -> 20 | Q60: =ROUND(E60/100*Global_Params!$B$25,0) -> 635 | R60: =Maps!$F$11 -> Minerals | S60: =Growth_Curve!$B$12 -> 1 | T60: =IF(B60<Global_Params!$B$30,0,MAX(1,ROUND(E60/260,0))) -> 6 | U60: =IF(T60=0,"-","L") -> L | V60: =IF(T60=0,0,ROUND(C60/2*Global_Params!$B$31,0)) -> 22 | W60: =IF(T60=0,0,ROUND(D60/2*Global_Params!$B$31,0)) -> 11 | X60: =IF(T60=0,0,Global_Params!$B$32) -> 4 | Y60: =T60*Global_Params!$B$33 -> 60
A61: 8 | B61: 1 | C61: =MIN(Maps!$C$12-2,ROUND(Maps!$C$12*Growth_Curve!$B$5/2,0)*2) -> 24 | D61: =MIN(Maps!$D$12,ROUND(Maps!$D$12*Growth_Curve!$B$5/2,0)*2) -> 12 | E61: =C61*D61 -> 288 | F61: =E61 -> 288 | G61: =ROUND(C61/2,0)+Global_Params!$B$16 -> 14 | H61: =ROUND(D61/2,0)+Global_Params!$B$16 -> 8 | I61: B | J61: =ROUND(Global_Params!$B$17*(1+Global_Params!$B$18*(B61-1))*Maps!$H$12,0) -> 170 | K61: =J61-L61-M61 -> 127 | L61: =ROUND(J61*(Global_Params!$B$19+(Global_Params!$B$20-Global_Params!$B$19)*(B61-1)/(Global_Params!$B$7-1)),0) -> 17 | M61: =ROUND(J61*IF(Maps!$G$12="Yes",Global_Params!$B$21,0),0) -> 26 | N61: =MAX(2,ROUND(E61/45,0)) -> 6 | O61: =1 -> 1 | P61: =ROUND(N61*0.6,0) -> 4 | Q61: =ROUND(E61/100*Global_Params!$B$25,0) -> 121 | R61: =Maps!$F$12 -> Crystals | S61: =Growth_Curve!$B$5 -> 0.4 | T61: =IF(B61<Global_Params!$B$30,0,MAX(1,ROUND(E61/260,0))) -> 0 | U61: =IF(T61=0,"-","T") -> - | V61: =IF(T61=0,0,ROUND(C61/2*Global_Params!$B$31,0)) -> 0 | W61: =IF(T61=0,0,ROUND(D61/2*Global_Params!$B$31,0)) -> 0 | X61: =IF(T61=0,0,Global_Params!$B$32) -> 0 | Y61: =T61*Global_Params!$B$33 -> 0
A62: 8 | B62: 2 | C62: =MIN(Maps!$C$12-2,MAX(C61+2,ROUND(Maps!$C$12*Growth_Curve!$B$6/2,0)*2)) -> 28 | D62: =MIN(Maps!$D$12,MAX(D61,ROUND(Maps!$D$12*Growth_Curve!$B$6/2,0)*2)) -> 14 | E62: =C62*D62 -> 392 | F62: =E62-E61 -> 104 | G62: =ROUND(C62/2,0)+Global_Params!$B$16 -> 16 | H62: =ROUND(D62/2,0)+Global_Params!$B$16 -> 9 | I62: L | J62: =ROUND(Global_Params!$B$17*(1+Global_Params!$B$18*(B62-1))*Maps!$H$12,0) -> 201 | K62: =J62-L62-M62 -> 145 | L62: =ROUND(J62*(Global_Params!$B$19+(Global_Params!$B$20-Global_Params!$B$19)*(B62-1)/(Global_Params!$B$7-1)),0) -> 26 | M62: =ROUND(J62*IF(Maps!$G$12="Yes",Global_Params!$B$21,0),0) -> 30 | N62: =MAX(2,ROUND(E62/45,0)) -> 9 | O62: =MAX(1,MIN(Global_Params!$B$26,ROUND(F62/50,0))) -> 2 | P62: =ROUND(N62*0.6,0) -> 5 | Q62: =ROUND(E62/100*Global_Params!$B$25,0) -> 165 | R62: =Maps!$F$12 -> Crystals | S62: =Growth_Curve!$B$6 -> 0.46 | T62: =IF(B62<Global_Params!$B$30,0,MAX(1,ROUND(E62/260,0))) -> 0 | U62: =IF(T62=0,"-","R") -> - | V62: =IF(T62=0,0,ROUND(C62/2*Global_Params!$B$31,0)) -> 0 | W62: =IF(T62=0,0,ROUND(D62/2*Global_Params!$B$31,0)) -> 0 | X62: =IF(T62=0,0,Global_Params!$B$32) -> 0 | Y62: =T62*Global_Params!$B$33 -> 0
A63: 8 | B63: 3 | C63: =MIN(Maps!$C$12-2,MAX(C62+2,ROUND(Maps!$C$12*Growth_Curve!$B$7/2,0)*2)) -> 32 | D63: =MIN(Maps!$D$12,MAX(D62,ROUND(Maps!$D$12*Growth_Curve!$B$7/2,0)*2)) -> 16 | E63: =C63*D63 -> 512 | F63: =E63-E62 -> 120 | G63: =ROUND(C63/2,0)+Global_Params!$B$16 -> 18 | H63: =ROUND(D63/2,0)+Global_Params!$B$16 -> 10 | I63: R | J63: =ROUND(Global_Params!$B$17*(1+Global_Params!$B$18*(B63-1))*Maps!$H$12,0) -> 231 | K63: =J63-L63-M63 -> 160 | L63: =ROUND(J63*(Global_Params!$B$19+(Global_Params!$B$20-Global_Params!$B$19)*(B63-1)/(Global_Params!$B$7-1)),0) -> 36 | M63: =ROUND(J63*IF(Maps!$G$12="Yes",Global_Params!$B$21,0),0) -> 35 | N63: =MAX(2,ROUND(E63/45,0)) -> 11 | O63: =MAX(1,MIN(Global_Params!$B$26,ROUND(F63/50,0))) -> 2 | P63: =ROUND(N63*0.6,0) -> 7 | Q63: =ROUND(E63/100*Global_Params!$B$25,0) -> 215 | R63: =Maps!$F$12 -> Crystals | S63: =Growth_Curve!$B$7 -> 0.54 | T63: =IF(B63<Global_Params!$B$30,0,MAX(1,ROUND(E63/260,0))) -> 0 | U63: =IF(T63=0,"-","L") -> - | V63: =IF(T63=0,0,ROUND(C63/2*Global_Params!$B$31,0)) -> 0 | W63: =IF(T63=0,0,ROUND(D63/2*Global_Params!$B$31,0)) -> 0 | X63: =IF(T63=0,0,Global_Params!$B$32) -> 0 | Y63: =T63*Global_Params!$B$33 -> 0
A64: 8 | B64: 4 | C64: =MIN(Maps!$C$12-2,MAX(C63+2,ROUND(Maps!$C$12*Growth_Curve!$B$8/2,0)*2)) -> 40 | D64: =MIN(Maps!$D$12,MAX(D63,ROUND(Maps!$D$12*Growth_Curve!$B$8/2,0)*2)) -> 20 | E64: =C64*D64 -> 800 | F64: =E64-E63 -> 288 | G64: =ROUND(C64/2,0)+Global_Params!$B$16 -> 22 | H64: =ROUND(D64/2,0)+Global_Params!$B$16 -> 12 | I64: L | J64: =ROUND(Global_Params!$B$17*(1+Global_Params!$B$18*(B64-1))*Maps!$H$12,0) -> 262 | K64: =J64-L64-M64 -> 174 | L64: =ROUND(J64*(Global_Params!$B$19+(Global_Params!$B$20-Global_Params!$B$19)*(B64-1)/(Global_Params!$B$7-1)),0) -> 49 | M64: =ROUND(J64*IF(Maps!$G$12="Yes",Global_Params!$B$21,0),0) -> 39 | N64: =MAX(2,ROUND(E64/45,0)) -> 18 | O64: =MAX(1,MIN(Global_Params!$B$26,ROUND(F64/50,0))) -> 3 | P64: =ROUND(N64*0.6,0) -> 11 | Q64: =ROUND(E64/100*Global_Params!$B$25,0) -> 336 | R64: =Maps!$F$12 -> Crystals | S64: =Growth_Curve!$B$8 -> 0.66 | T64: =IF(B64<Global_Params!$B$30,0,MAX(1,ROUND(E64/260,0))) -> 0 | U64: =IF(T64=0,"-","R") -> - | V64: =IF(T64=0,0,ROUND(C64/2*Global_Params!$B$31,0)) -> 0 | W64: =IF(T64=0,0,ROUND(D64/2*Global_Params!$B$31,0)) -> 0 | X64: =IF(T64=0,0,Global_Params!$B$32) -> 0 | Y64: =T64*Global_Params!$B$33 -> 0
A65: 8 | B65: 5 | C65: =MIN(Maps!$C$12-2,MAX(C64+2,ROUND(Maps!$C$12*Growth_Curve!$B$9/2,0)*2)) -> 48 | D65: =MIN(Maps!$D$12,MAX(D64,ROUND(Maps!$D$12*Growth_Curve!$B$9/2,0)*2)) -> 24 | E65: =C65*D65 -> 1152 | F65: =E65-E64 -> 352 | G65: =ROUND(C65/2,0)+Global_Params!$B$16 -> 26 | H65: =ROUND(D65/2,0)+Global_Params!$B$16 -> 14 | I65: R | J65: =ROUND(Global_Params!$B$17*(1+Global_Params!$B$18*(B65-1))*Maps!$H$12,0) -> 292 | K65: =J65-L65-M65 -> 185 | L65: =ROUND(J65*(Global_Params!$B$19+(Global_Params!$B$20-Global_Params!$B$19)*(B65-1)/(Global_Params!$B$7-1)),0) -> 63 | M65: =ROUND(J65*IF(Maps!$G$12="Yes",Global_Params!$B$21,0),0) -> 44 | N65: =MAX(2,ROUND(E65/45,0)) -> 26 | O65: =MAX(1,MIN(Global_Params!$B$26,ROUND(F65/50,0))) -> 3 | P65: =ROUND(N65*0.6,0) -> 16 | Q65: =ROUND(E65/100*Global_Params!$B$25,0) -> 484 | R65: =Maps!$F$12 -> Crystals | S65: =Growth_Curve!$B$9 -> 0.79 | T65: =IF(B65<Global_Params!$B$30,0,MAX(1,ROUND(E65/260,0))) -> 4 | U65: =IF(T65=0,"-","L") -> L | V65: =IF(T65=0,0,ROUND(C65/2*Global_Params!$B$31,0)) -> 19 | W65: =IF(T65=0,0,ROUND(D65/2*Global_Params!$B$31,0)) -> 10 | X65: =IF(T65=0,0,Global_Params!$B$32) -> 4 | Y65: =T65*Global_Params!$B$33 -> 40
A66: 8 | B66: 6 | C66: =MIN(Maps!$C$12-2,MAX(C65+2,ROUND(Maps!$C$12*Growth_Curve!$B$10/2,0)*2)) -> 54 | D66: =MIN(Maps!$D$12,MAX(D65,ROUND(Maps!$D$12*Growth_Curve!$B$10/2,0)*2)) -> 26 | E66: =C66*D66 -> 1404 | F66: =E66-E65 -> 252 | G66: =ROUND(C66/2,0)+Global_Params!$B$16 -> 29 | H66: =ROUND(D66/2,0)+Global_Params!$B$16 -> 15 | I66: L | J66: =ROUND(Global_Params!$B$17*(1+Global_Params!$B$18*(B66-1))*Maps!$H$12,0) -> 323 | K66: =J66-L66-M66 -> 197 | L66: =ROUND(J66*(Global_Params!$B$19+(Global_Params!$B$20-Global_Params!$B$19)*(B66-1)/(Global_Params!$B$7-1)),0) -> 78 | M66: =ROUND(J66*IF(Maps!$G$12="Yes",Global_Params!$B$21,0),0) -> 48 | N66: =MAX(2,ROUND(E66/45,0)) -> 31 | O66: =MAX(1,MIN(Global_Params!$B$26,ROUND(F66/50,0))) -> 3 | P66: =ROUND(N66*0.6,0) -> 19 | Q66: =ROUND(E66/100*Global_Params!$B$25,0) -> 590 | R66: =Maps!$F$12 -> Crystals | S66: =Growth_Curve!$B$10 -> 0.89 | T66: =IF(B66<Global_Params!$B$30,0,MAX(1,ROUND(E66/260,0))) -> 5 | U66: =IF(T66=0,"-","R") -> R | V66: =IF(T66=0,0,ROUND(C66/2*Global_Params!$B$31,0)) -> 22 | W66: =IF(T66=0,0,ROUND(D66/2*Global_Params!$B$31,0)) -> 10 | X66: =IF(T66=0,0,Global_Params!$B$32) -> 4 | Y66: =T66*Global_Params!$B$33 -> 50
A67: 8 | B67: 7 | C67: =MIN(Maps!$C$12-2,MAX(C66+2,ROUND(Maps!$C$12*Growth_Curve!$B$11/2,0)*2)) -> 58 | D67: =MIN(Maps!$D$12,MAX(D66,ROUND(Maps!$D$12*Growth_Curve!$B$11/2,0)*2)) -> 28 | E67: =C67*D67 -> 1624 | F67: =E67-E66 -> 220 | G67: =ROUND(C67/2,0)+Global_Params!$B$16 -> 31 | H67: =ROUND(D67/2,0)+Global_Params!$B$16 -> 16 | I67: R | J67: =ROUND(Global_Params!$B$17*(1+Global_Params!$B$18*(B67-1))*Maps!$H$12,0) -> 354 | K67: =J67-L67-M67 -> 205 | L67: =ROUND(J67*(Global_Params!$B$19+(Global_Params!$B$20-Global_Params!$B$19)*(B67-1)/(Global_Params!$B$7-1)),0) -> 96 | M67: =ROUND(J67*IF(Maps!$G$12="Yes",Global_Params!$B$21,0),0) -> 53 | N67: =MAX(2,ROUND(E67/45,0)) -> 36 | O67: =MAX(1,MIN(Global_Params!$B$26,ROUND(F67/50,0))) -> 3 | P67: =ROUND(N67*0.6,0) -> 22 | Q67: =ROUND(E67/100*Global_Params!$B$25,0) -> 682 | R67: =Maps!$F$12 -> Crystals | S67: =Growth_Curve!$B$11 -> 0.96 | T67: =IF(B67<Global_Params!$B$30,0,MAX(1,ROUND(E67/260,0))) -> 6 | U67: =IF(T67=0,"-","L") -> L | V67: =IF(T67=0,0,ROUND(C67/2*Global_Params!$B$31,0)) -> 23 | W67: =IF(T67=0,0,ROUND(D67/2*Global_Params!$B$31,0)) -> 11 | X67: =IF(T67=0,0,Global_Params!$B$32) -> 4 | Y67: =T67*Global_Params!$B$33 -> 60
A68: 8 | B68: 8 | C68: =Maps!$C$12 -> 60 | D68: =Maps!$D$12 -> 30 | E68: =C68*D68 -> 1800 | F68: =E68-E67 -> 176 | G68: =ROUND(C68/2,0)+Global_Params!$B$16 -> 32 | H68: =ROUND(D68/2,0)+Global_Params!$B$16 -> 17 | I68: T | J68: =ROUND(Global_Params!$B$17*(1+Global_Params!$B$18*(B68-1))*Maps!$H$12,0) -> 384 | K68: =J68-L68-M68 -> 211 | L68: =ROUND(J68*(Global_Params!$B$19+(Global_Params!$B$20-Global_Params!$B$19)*(B68-1)/(Global_Params!$B$7-1)),0) -> 115 | M68: =ROUND(J68*IF(Maps!$G$12="Yes",Global_Params!$B$21,0),0) -> 58 | N68: =MAX(2,ROUND(E68/45,0)) -> 40 | O68: =MAX(1,MIN(Global_Params!$B$26,ROUND(F68/50,0))) -> 3 | P68: =ROUND(N68*0.6,0) -> 24 | Q68: =ROUND(E68/100*Global_Params!$B$25,0) -> 756 | R68: =Maps!$F$12 -> Crystals | S68: =Growth_Curve!$B$12 -> 1 | T68: =IF(B68<Global_Params!$B$30,0,MAX(1,ROUND(E68/260,0))) -> 7 | U68: =IF(T68=0,"-","B") -> B | V68: =IF(T68=0,0,ROUND(C68/2*Global_Params!$B$31,0)) -> 24 | W68: =IF(T68=0,0,ROUND(D68/2*Global_Params!$B$31,0)) -> 12 | X68: =IF(T68=0,0,Global_Params!$B$32) -> 4 | Y68: =T68*Global_Params!$B$33 -> 70
A69: 9 | B69: 1 | C69: =MIN(Maps!$C$13-2,ROUND(Maps!$C$13*Growth_Curve!$B$5/2,0)*2) -> 26 | D69: =MIN(Maps!$D$13,ROUND(Maps!$D$13*Growth_Curve!$B$5/2,0)*2) -> 12 | E69: =C69*D69 -> 312 | F69: =E69 -> 312 | G69: =ROUND(C69/2,0)+Global_Params!$B$16 -> 15 | H69: =ROUND(D69/2,0)+Global_Params!$B$16 -> 8 | I69: L | J69: =ROUND(Global_Params!$B$17*(1+Global_Params!$B$18*(B69-1))*Maps!$H$13,0) -> 180 | K69: =J69-L69-M69 -> 135 | L69: =ROUND(J69*(Global_Params!$B$19+(Global_Params!$B$20-Global_Params!$B$19)*(B69-1)/(Global_Params!$B$7-1)),0) -> 18 | M69: =ROUND(J69*IF(Maps!$G$13="Yes",Global_Params!$B$21,0),0) -> 27 | N69: =MAX(2,ROUND(E69/45,0)) -> 7 | O69: =1 -> 1 | P69: =ROUND(N69*0.6,0) -> 4 | Q69: =ROUND(E69/100*Global_Params!$B$25,0) -> 131 | R69: =Maps!$F$13 -> Crystals | S69: =Growth_Curve!$B$5 -> 0.4 | T69: =IF(B69<Global_Params!$B$30,0,MAX(1,ROUND(E69/260,0))) -> 0 | U69: =IF(T69=0,"-","R") -> - | V69: =IF(T69=0,0,ROUND(C69/2*Global_Params!$B$31,0)) -> 0 | W69: =IF(T69=0,0,ROUND(D69/2*Global_Params!$B$31,0)) -> 0 | X69: =IF(T69=0,0,Global_Params!$B$32) -> 0 | Y69: =T69*Global_Params!$B$33 -> 0
A70: 9 | B70: 2 | C70: =MIN(Maps!$C$13-2,MAX(C69+2,ROUND(Maps!$C$13*Growth_Curve!$B$6/2,0)*2)) -> 30 | D70: =MIN(Maps!$D$13,MAX(D69,ROUND(Maps!$D$13*Growth_Curve!$B$6/2,0)*2)) -> 14 | E70: =C70*D70 -> 420 | F70: =E70-E69 -> 108 | G70: =ROUND(C70/2,0)+Global_Params!$B$16 -> 17 | H70: =ROUND(D70/2,0)+Global_Params!$B$16 -> 9 | I70: R | J70: =ROUND(Global_Params!$B$17*(1+Global_Params!$B$18*(B70-1))*Maps!$H$13,0) -> 212 | K70: =J70-L70-M70 -> 153 | L70: =ROUND(J70*(Global_Params!$B$19+(Global_Params!$B$20-Global_Params!$B$19)*(B70-1)/(Global_Params!$B$7-1)),0) -> 27 | M70: =ROUND(J70*IF(Maps!$G$13="Yes",Global_Params!$B$21,0),0) -> 32 | N70: =MAX(2,ROUND(E70/45,0)) -> 9 | O70: =MAX(1,MIN(Global_Params!$B$26,ROUND(F70/50,0))) -> 2 | P70: =ROUND(N70*0.6,0) -> 5 | Q70: =ROUND(E70/100*Global_Params!$B$25,0) -> 176 | R70: =Maps!$F$13 -> Crystals | S70: =Growth_Curve!$B$6 -> 0.46 | T70: =IF(B70<Global_Params!$B$30,0,MAX(1,ROUND(E70/260,0))) -> 0 | U70: =IF(T70=0,"-","L") -> - | V70: =IF(T70=0,0,ROUND(C70/2*Global_Params!$B$31,0)) -> 0 | W70: =IF(T70=0,0,ROUND(D70/2*Global_Params!$B$31,0)) -> 0 | X70: =IF(T70=0,0,Global_Params!$B$32) -> 0 | Y70: =T70*Global_Params!$B$33 -> 0
A71: 9 | B71: 3 | C71: =MIN(Maps!$C$13-2,MAX(C70+2,ROUND(Maps!$C$13*Growth_Curve!$B$7/2,0)*2)) -> 34 | D71: =MIN(Maps!$D$13,MAX(D70,ROUND(Maps!$D$13*Growth_Curve!$B$7/2,0)*2)) -> 18 | E71: =C71*D71 -> 612 | F71: =E71-E70 -> 192 | G71: =ROUND(C71/2,0)+Global_Params!$B$16 -> 19 | H71: =ROUND(D71/2,0)+Global_Params!$B$16 -> 11 | I71: L | J71: =ROUND(Global_Params!$B$17*(1+Global_Params!$B$18*(B71-1))*Maps!$H$13,0) -> 245 | K71: =J71-L71-M71 -> 169 | L71: =ROUND(J71*(Global_Params!$B$19+(Global_Params!$B$20-Global_Params!$B$19)*(B71-1)/(Global_Params!$B$7-1)),0) -> 39 | M71: =ROUND(J71*IF(Maps!$G$13="Yes",Global_Params!$B$21,0),0) -> 37 | N71: =MAX(2,ROUND(E71/45,0)) -> 14 | O71: =MAX(1,MIN(Global_Params!$B$26,ROUND(F71/50,0))) -> 3 | P71: =ROUND(N71*0.6,0) -> 8 | Q71: =ROUND(E71/100*Global_Params!$B$25,0) -> 257 | R71: =Maps!$F$13 -> Crystals | S71: =Growth_Curve!$B$7 -> 0.54 | T71: =IF(B71<Global_Params!$B$30,0,MAX(1,ROUND(E71/260,0))) -> 0 | U71: =IF(T71=0,"-","R") -> - | V71: =IF(T71=0,0,ROUND(C71/2*Global_Params!$B$31,0)) -> 0 | W71: =IF(T71=0,0,ROUND(D71/2*Global_Params!$B$31,0)) -> 0 | X71: =IF(T71=0,0,Global_Params!$B$32) -> 0 | Y71: =T71*Global_Params!$B$33 -> 0
A72: 9 | B72: 4 | C72: =MIN(Maps!$C$13-2,MAX(C71+2,ROUND(Maps!$C$13*Growth_Curve!$B$8/2,0)*2)) -> 42 | D72: =MIN(Maps!$D$13,MAX(D71,ROUND(Maps!$D$13*Growth_Curve!$B$8/2,0)*2)) -> 22 | E72: =C72*D72 -> 924 | F72: =E72-E71 -> 312 | G72: =ROUND(C72/2,0)+Global_Params!$B$16 -> 23 | H72: =ROUND(D72/2,0)+Global_Params!$B$16 -> 13 | I72: R | J72: =ROUND(Global_Params!$B$17*(1+Global_Params!$B$18*(B72-1))*Maps!$H$13,0) -> 277 | K72: =J72-L72-M72 -> 184 | L72: =ROUND(J72*(Global_Params!$B$19+(Global_Params!$B$20-Global_Params!$B$19)*(B72-1)/(Global_Params!$B$7-1)),0) -> 51 | M72: =ROUND(J72*IF(Maps!$G$13="Yes",Global_Params!$B$21,0),0) -> 42 | N72: =MAX(2,ROUND(E72/45,0)) -> 21 | O72: =MAX(1,MIN(Global_Params!$B$26,ROUND(F72/50,0))) -> 3 | P72: =ROUND(N72*0.6,0) -> 13 | Q72: =ROUND(E72/100*Global_Params!$B$25,0) -> 388 | R72: =Maps!$F$13 -> Crystals | S72: =Growth_Curve!$B$8 -> 0.66 | T72: =IF(B72<Global_Params!$B$30,0,MAX(1,ROUND(E72/260,0))) -> 0 | U72: =IF(T72=0,"-","L") -> - | V72: =IF(T72=0,0,ROUND(C72/2*Global_Params!$B$31,0)) -> 0 | W72: =IF(T72=0,0,ROUND(D72/2*Global_Params!$B$31,0)) -> 0 | X72: =IF(T72=0,0,Global_Params!$B$32) -> 0 | Y72: =T72*Global_Params!$B$33 -> 0
A73: 9 | B73: 5 | C73: =MIN(Maps!$C$13-2,MAX(C72+2,ROUND(Maps!$C$13*Growth_Curve!$B$9/2,0)*2)) -> 50 | D73: =MIN(Maps!$D$13,MAX(D72,ROUND(Maps!$D$13*Growth_Curve!$B$9/2,0)*2)) -> 26 | E73: =C73*D73 -> 1300 | F73: =E73-E72 -> 376 | G73: =ROUND(C73/2,0)+Global_Params!$B$16 -> 27 | H73: =ROUND(D73/2,0)+Global_Params!$B$16 -> 15 | I73: L | J73: =ROUND(Global_Params!$B$17*(1+Global_Params!$B$18*(B73-1))*Maps!$H$13,0) -> 310 | K73: =J73-L73-M73 -> 197 | L73: =ROUND(J73*(Global_Params!$B$19+(Global_Params!$B$20-Global_Params!$B$19)*(B73-1)/(Global_Params!$B$7-1)),0) -> 66 | M73: =ROUND(J73*IF(Maps!$G$13="Yes",Global_Params!$B$21,0),0) -> 47 | N73: =MAX(2,ROUND(E73/45,0)) -> 29 | O73: =MAX(1,MIN(Global_Params!$B$26,ROUND(F73/50,0))) -> 3 | P73: =ROUND(N73*0.6,0) -> 17 | Q73: =ROUND(E73/100*Global_Params!$B$25,0) -> 546 | R73: =Maps!$F$13 -> Crystals | S73: =Growth_Curve!$B$9 -> 0.79 | T73: =IF(B73<Global_Params!$B$30,0,MAX(1,ROUND(E73/260,0))) -> 5 | U73: =IF(T73=0,"-","R") -> R | V73: =IF(T73=0,0,ROUND(C73/2*Global_Params!$B$31,0)) -> 20 | W73: =IF(T73=0,0,ROUND(D73/2*Global_Params!$B$31,0)) -> 10 | X73: =IF(T73=0,0,Global_Params!$B$32) -> 4 | Y73: =T73*Global_Params!$B$33 -> 50
A74: 9 | B74: 6 | C74: =MIN(Maps!$C$13-2,MAX(C73+2,ROUND(Maps!$C$13*Growth_Curve!$B$10/2,0)*2)) -> 56 | D74: =MIN(Maps!$D$13,MAX(D73,ROUND(Maps!$D$13*Growth_Curve!$B$10/2,0)*2)) -> 28 | E74: =C74*D74 -> 1568 | F74: =E74-E73 -> 268 | G74: =ROUND(C74/2,0)+Global_Params!$B$16 -> 30 | H74: =ROUND(D74/2,0)+Global_Params!$B$16 -> 16 | I74: R | J74: =ROUND(Global_Params!$B$17*(1+Global_Params!$B$18*(B74-1))*Maps!$H$13,0) -> 342 | K74: =J74-L74-M74 -> 208 | L74: =ROUND(J74*(Global_Params!$B$19+(Global_Params!$B$20-Global_Params!$B$19)*(B74-1)/(Global_Params!$B$7-1)),0) -> 83 | M74: =ROUND(J74*IF(Maps!$G$13="Yes",Global_Params!$B$21,0),0) -> 51 | N74: =MAX(2,ROUND(E74/45,0)) -> 35 | O74: =MAX(1,MIN(Global_Params!$B$26,ROUND(F74/50,0))) -> 3 | P74: =ROUND(N74*0.6,0) -> 21 | Q74: =ROUND(E74/100*Global_Params!$B$25,0) -> 659 | R74: =Maps!$F$13 -> Crystals | S74: =Growth_Curve!$B$10 -> 0.89 | T74: =IF(B74<Global_Params!$B$30,0,MAX(1,ROUND(E74/260,0))) -> 6 | U74: =IF(T74=0,"-","L") -> L | V74: =IF(T74=0,0,ROUND(C74/2*Global_Params!$B$31,0)) -> 22 | W74: =IF(T74=0,0,ROUND(D74/2*Global_Params!$B$31,0)) -> 11 | X74: =IF(T74=0,0,Global_Params!$B$32) -> 4 | Y74: =T74*Global_Params!$B$33 -> 60
A75: 9 | B75: 7 | C75: =MIN(Maps!$C$13-2,MAX(C74+2,ROUND(Maps!$C$13*Growth_Curve!$B$11/2,0)*2)) -> 62 | D75: =MIN(Maps!$D$13,MAX(D74,ROUND(Maps!$D$13*Growth_Curve!$B$11/2,0)*2)) -> 30 | E75: =C75*D75 -> 1860 | F75: =E75-E74 -> 292 | G75: =ROUND(C75/2,0)+Global_Params!$B$16 -> 33 | H75: =ROUND(D75/2,0)+Global_Params!$B$16 -> 17 | I75: T | J75: =ROUND(Global_Params!$B$17*(1+Global_Params!$B$18*(B75-1))*Maps!$H$13,0) -> 374 | K75: =J75-L75-M75 -> 216 | L75: =ROUND(J75*(Global_Params!$B$19+(Global_Params!$B$20-Global_Params!$B$19)*(B75-1)/(Global_Params!$B$7-1)),0) -> 102 | M75: =ROUND(J75*IF(Maps!$G$13="Yes",Global_Params!$B$21,0),0) -> 56 | N75: =MAX(2,ROUND(E75/45,0)) -> 41 | O75: =MAX(1,MIN(Global_Params!$B$26,ROUND(F75/50,0))) -> 3 | P75: =ROUND(N75*0.6,0) -> 25 | Q75: =ROUND(E75/100*Global_Params!$B$25,0) -> 781 | R75: =Maps!$F$13 -> Crystals | S75: =Growth_Curve!$B$11 -> 0.96 | T75: =IF(B75<Global_Params!$B$30,0,MAX(1,ROUND(E75/260,0))) -> 7 | U75: =IF(T75=0,"-","B") -> B | V75: =IF(T75=0,0,ROUND(C75/2*Global_Params!$B$31,0)) -> 25 | W75: =IF(T75=0,0,ROUND(D75/2*Global_Params!$B$31,0)) -> 12 | X75: =IF(T75=0,0,Global_Params!$B$32) -> 4 | Y75: =T75*Global_Params!$B$33 -> 70
A76: 9 | B76: 8 | C76: =Maps!$C$13 -> 64 | D76: =Maps!$D$13 -> 32 | E76: =C76*D76 -> 2048 | F76: =E76-E75 -> 188 | G76: =ROUND(C76/2,0)+Global_Params!$B$16 -> 34 | H76: =ROUND(D76/2,0)+Global_Params!$B$16 -> 18 | I76: B | J76: =ROUND(Global_Params!$B$17*(1+Global_Params!$B$18*(B76-1))*Maps!$H$13,0) -> 407 | K76: =J76-L76-M76 -> 224 | L76: =ROUND(J76*(Global_Params!$B$19+(Global_Params!$B$20-Global_Params!$B$19)*(B76-1)/(Global_Params!$B$7-1)),0) -> 122 | M76: =ROUND(J76*IF(Maps!$G$13="Yes",Global_Params!$B$21,0),0) -> 61 | N76: =MAX(2,ROUND(E76/45,0)) -> 46 | O76: =MAX(1,MIN(Global_Params!$B$26,ROUND(F76/50,0))) -> 3 | P76: =ROUND(N76*0.6,0) -> 28 | Q76: =ROUND(E76/100*Global_Params!$B$25,0) -> 860 | R76: =Maps!$F$13 -> Crystals | S76: =Growth_Curve!$B$12 -> 1 | T76: =IF(B76<Global_Params!$B$30,0,MAX(1,ROUND(E76/260,0))) -> 8 | U76: =IF(T76=0,"-","T") -> T | V76: =IF(T76=0,0,ROUND(C76/2*Global_Params!$B$31,0)) -> 26 | W76: =IF(T76=0,0,ROUND(D76/2*Global_Params!$B$31,0)) -> 13 | X76: =IF(T76=0,0,Global_Params!$B$32) -> 4 | Y76: =T76*Global_Params!$B$33 -> 80
A78: Primary_Nodes = 1 node per ~45 playable tiles (density knob — edit the divisor).
A79: Premium_Nodes = fresh seed in EACH ring, so the greed star never goes stale.
A80: Side_Focus cycles L/R with a T/B break at waves 7-8, offset per map so no two maps feel identical.
A81: Playable_W is forced to grow >=2 tiles every wave, so EVERY wave opens a real ring. Wave 8 always equals the full map.
A82: QUEST appears only in waves 5-8. Quest_Side is the OPPOSITE of Side_Focus: premium is paid for in blood, quest is paid for in tempo.
A83: Quest_Band_Min_X/Y = the inner edge of the far band, measured from map center. Nodes scatter beyond it by up to Quest_Jitter tiles.

Sheet Score_Model
A1: Map Score Model
A2: Worked example. Map 5 / Faction 5 (the greed faction). Edit the blue cells.
A4: Item | B4: Value | C4: Notes
A5: INPUTS
A6: Map_ID | B6: 5 | C6: Row 9 in Maps.
A7: Faction_ID | B7: 5 | C7: Row 9 in Factions.
A8: Primary_Units_Collected | B8: 380 | C8: Player choice. Cap is roughly total nodes x units/node.
A9: Premium_Units_Collected | B9: 90 | C9: The greed number. Every unit here was a risk taken.
A10: Gold_Spent_On_Towers | B10: 950 | C10: Subtracted at full rate.
A11: Gold_Spent_On_Harvesters | B11: 300 | C11: Subtracted at the harvester rate below.
A12: Harvester_Spend_Rate | B12: 0.5 | C12: Harvester spend is only HALF-subtracted — it is investment, not waste.
A13: Actual_Clear_Time_Sec | B13: 1400 | C13: Beat Maps!I9 to earn the time bonus.
A15: DERIVED
A16: Faction_Yield_Mult | B16: {=INDEX(Factions!$F$5:$F$13,MATCH($B$7,Factions!$A$5:$A$13,0))} -> 1.2 | C16: From Factions.
A17: Map_Primary_Resource | B17: {=INDEX(Maps!$F$5:$F$13,MATCH($B$6,Maps!$A$5:$A$13,0))} -> Crystals | C17: The MAP sets this.
A18: Faction_Premium_Resource | B18: {=INDEX(Factions!$C$5:$C$13,MATCH($B$7,Factions!$A$5:$A$13,0))} -> Flowers | C18: The FACTION sets this.
A19: Primary_Value_Per_Unit | B19: =SUMIFS(Resources!$C$5:$C$10,Resources!$A$5:$A$10,$B$17,Resources!$B$5:$B$10,"Primary") -> 9 | C19: Looked up by name + tier.
A20: Premium_Value_Per_Unit | B20: =SUMIFS(Resources!$C$5:$C$10,Resources!$A$5:$A$10,$B$18,Resources!$B$5:$B$10,"Premium") -> 14 | C20: Looked up by name + tier.
A21: Map_Par_Time_Sec | B21: {=INDEX(Maps!$I$5:$I$13,MATCH($B$6,Maps!$A$5:$A$13,0))} -> 3548 | C21: Whole-map par (8 waves).
A23: SCORE
A24: Gold_From_Primary | B24: =ROUND($B$8*$B$19*$B$16*Global_Params!$B$23,0) -> 4104 | C24: The safe income.
A25: Gold_From_Premium | B25: =ROUND($B$9*$B$20*$B$16*Global_Params!$B$23,0) -> 1512 | C25: The reward for overextending.
A26: Less: Resource_Spent | B26: =-($B$10+$B$11*$B$12) -> -1100 | C26: Towers at full rate, harvesters at the discounted rate. See the note below.
A27: Time_Bonus | B27: =ROUND(MAX(0,($B$21-$B$13)/$B$21)*Global_Params!$B$24,0) -> 242 | C27: Zero if you go over par. Directly punishes farming the primary respawn.
A28: MAP SCORE (gold) | B28: =$B$24+$B$25+$B$26+$B$27 -> 4758 | C28: Banked as gold. Spend it in Harvester_Upgrades.
A30: STAR GATE (separate track)
A31: Wave 1 stars | B31: 3 | C31: 0-5, per Star_Rubric.
A32: Wave 2 stars | B32: 4 | C32: 0-5, per Star_Rubric.
A33: Wave 3 stars | B33: 3 | C33: 0-5, per Star_Rubric.
A34: Wave 4 stars | B34: 2 | C34: 0-5, per Star_Rubric.
A35: Wave 5 stars | B35: 4 | C35: 0-5, per Star_Rubric.
A36: Wave 6 stars | B36: 3 | C36: 0-5, per Star_Rubric.
A37: Wave 7 stars | B37: 3 | C37: 0-5, per Star_Rubric.
A38: Wave 8 stars | B38: 5 | C38: 0-5, per Star_Rubric.
A39: AVERAGE STARS | B39: =AVERAGE(B31:B38) -> 3.375 | C39: This is the map score the player sees after the final wave score.
A40: NEXT MAP UNLOCKED? | B40: =IF(B39>=Global_Params!$B$8,"UNLOCKED","REPLAY") -> UNLOCKED | C40: Gate is 3.0. Gold is kept either way — only progression is gated.
A43: LOYALTY TRACK (third track)
A44: Quest_Nodes_Harvested | B44: 6 | C44: Waves 5-8 only. Far edge, opposite the spawn side.
A45: Quest_Giver_Faction | B45: {=INDEX(Maps!$J$5:$J$13,MATCH($B$6,Maps!$A$5:$A$13,0))} -> 9 | C45: Whose loyalty this map's quest earns.
A46: Loyalty_Gained | B46: =B44*Global_Params!$B$33 -> 60 | C46: Quest resource pays in LOYALTY, never in gold.
A47: Rival_Faction | B47: {=INDEX(Factions!$E$5:$E$13,MATCH(B45,Factions!$A$5:$A$13,0))} -> none | C47: 'none' for the unaligned faction.
A48: Loyalty_Lost_With_Rival | B48: =IF(B47="none",0,ROUND(B46*Global_Params!$B$34,0)) -> 0 | C48: Courting one faction burns the other. This is the build choice, not a penalty.
A50: THREE TRACKS, ONE SCREEN. Stars gate PROGRESSION. Gold gates POWER. Loyalty gates TECH.
A51: Quest resource earns NO gold. It costs harvester time that would otherwise buy gold or a time bonus.
A52: That is the entire point: loyalty is bought with tempo, premium is bought with blood, primary is free.
A53: Sequence on wave 8: wave star score -> final map score -> dialog. The dialog can react to the whole run.
A54: WHY HARVESTER SPEND IS HALF-SUBTRACTED: 'collected minus spent' taxes defense. At a full 1.0 rate players
A55: underbuild, eat leaks, and lose star 1 anyway. The 0.5 rate says: towers are cost, harvesters are investment.
A56: If you want the pure formula you specified, set Harvester_Spend_Rate to 1.00 and watch the underbuild.

Sheet Resource_Roles
A1: Resource Roles — 9 maps x 9 factions
A2: THREE resource types, THREE roles, every pairing. Primary (economy, low) / Premium (economy, high) / Quest (loyalty). The clash fix makes this mapping total: no pairing is ever missing a role.
A4: Map | B4: Faction | C4: Map_Primary | D4: Faction_Premium | E4: Premium_Effective | F4: Swapped? | G4: Quest_Resource | H4: Valid?
A5: =Maps!$B$5 -> Map_01 | B5: =Factions!$B$5 -> Faction_01 | C5: =Maps!$F$5 -> Flowers | D5: =Factions!$C$5 -> Crystals | E5: =IF(D5=C5,Factions!$D$5,D5) -> Crystals | F5: =IF(D5=C5,"SWAPPED","-") -> - | G5: =IF(AND(C5<>"Flowers",E5<>"Flowers"),"Flowers",IF(AND(C5<>"Crystals",E5<>"Crystals"),"Crystals","Minerals")) -> Minerals | H5: =IF(OR(C5=E5,C5=G5,E5=G5),"BROKEN","ok") -> ok
A6: =Maps!$B$5 -> Map_01 | B6: =Factions!$B$6 -> Faction_02 | C6: =Maps!$F$5 -> Flowers | D6: =Factions!$C$6 -> Flowers | E6: =IF(D6=C6,Factions!$D$6,D6) -> Crystals | F6: =IF(D6=C6,"SWAPPED","-") -> SWAPPED | G6: =IF(AND(C6<>"Flowers",E6<>"Flowers"),"Flowers",IF(AND(C6<>"Crystals",E6<>"Crystals"),"Crystals","Minerals")) -> Minerals | H6: =IF(OR(C6=E6,C6=G6,E6=G6),"BROKEN","ok") -> ok
A7: =Maps!$B$5 -> Map_01 | B7: =Factions!$B$7 -> Faction_03 | C7: =Maps!$F$5 -> Flowers | D7: =Factions!$C$7 -> Minerals | E7: =IF(D7=C7,Factions!$D$7,D7) -> Minerals | F7: =IF(D7=C7,"SWAPPED","-") -> - | G7: =IF(AND(C7<>"Flowers",E7<>"Flowers"),"Flowers",IF(AND(C7<>"Crystals",E7<>"Crystals"),"Crystals","Minerals")) -> Crystals | H7: =IF(OR(C7=E7,C7=G7,E7=G7),"BROKEN","ok") -> ok
A8: =Maps!$B$5 -> Map_01 | B8: =Factions!$B$8 -> Faction_04 | C8: =Maps!$F$5 -> Flowers | D8: =Factions!$C$8 -> Crystals | E8: =IF(D8=C8,Factions!$D$8,D8) -> Crystals | F8: =IF(D8=C8,"SWAPPED","-") -> - | G8: =IF(AND(C8<>"Flowers",E8<>"Flowers"),"Flowers",IF(AND(C8<>"Crystals",E8<>"Crystals"),"Crystals","Minerals")) -> Minerals | H8: =IF(OR(C8=E8,C8=G8,E8=G8),"BROKEN","ok") -> ok
A9: =Maps!$B$5 -> Map_01 | B9: =Factions!$B$9 -> Faction_05 | C9: =Maps!$F$5 -> Flowers | D9: =Factions!$C$9 -> Flowers | E9: =IF(D9=C9,Factions!$D$9,D9) -> Minerals | F9: =IF(D9=C9,"SWAPPED","-") -> SWAPPED | G9: =IF(AND(C9<>"Flowers",E9<>"Flowers"),"Flowers",IF(AND(C9<>"Crystals",E9<>"Crystals"),"Crystals","Minerals")) -> Crystals | H9: =IF(OR(C9=E9,C9=G9,E9=G9),"BROKEN","ok") -> ok
A10: =Maps!$B$5 -> Map_01 | B10: =Factions!$B$10 -> Faction_06 | C10: =Maps!$F$5 -> Flowers | D10: =Factions!$C$10 -> Minerals | E10: =IF(D10=C10,Factions!$D$10,D10) -> Minerals | F10: =IF(D10=C10,"SWAPPED","-") -> - | G10: =IF(AND(C10<>"Flowers",E10<>"Flowers"),"Flowers",IF(AND(C10<>"Crystals",E10<>"Crystals"),"Crystals","Minerals")) -> Crystals | H10: =IF(OR(C10=E10,C10=G10,E10=G10),"BROKEN","ok") -> ok
A11: =Maps!$B$5 -> Map_01 | B11: =Factions!$B$11 -> Faction_07 | C11: =Maps!$F$5 -> Flowers | D11: =Factions!$C$11 -> Crystals | E11: =IF(D11=C11,Factions!$D$11,D11) -> Crystals | F11: =IF(D11=C11,"SWAPPED","-") -> - | G11: =IF(AND(C11<>"Flowers",E11<>"Flowers"),"Flowers",IF(AND(C11<>"Crystals",E11<>"Crystals"),"Crystals","Minerals")) -> Minerals | H11: =IF(OR(C11=E11,C11=G11,E11=G11),"BROKEN","ok") -> ok
A12: =Maps!$B$5 -> Map_01 | B12: =Factions!$B$12 -> Faction_08 | C12: =Maps!$F$5 -> Flowers | D12: =Factions!$C$12 -> Flowers | E12: =IF(D12=C12,Factions!$D$12,D12) -> Crystals | F12: =IF(D12=C12,"SWAPPED","-") -> SWAPPED | G12: =IF(AND(C12<>"Flowers",E12<>"Flowers"),"Flowers",IF(AND(C12<>"Crystals",E12<>"Crystals"),"Crystals","Minerals")) -> Minerals | H12: =IF(OR(C12=E12,C12=G12,E12=G12),"BROKEN","ok") -> ok
A13: =Maps!$B$5 -> Map_01 | B13: =Factions!$B$13 -> Faction_09 | C13: =Maps!$F$5 -> Flowers | D13: =Factions!$C$13 -> Minerals | E13: =IF(D13=C13,Factions!$D$13,D13) -> Minerals | F13: =IF(D13=C13,"SWAPPED","-") -> - | G13: =IF(AND(C13<>"Flowers",E13<>"Flowers"),"Flowers",IF(AND(C13<>"Crystals",E13<>"Crystals"),"Crystals","Minerals")) -> Crystals | H13: =IF(OR(C13=E13,C13=G13,E13=G13),"BROKEN","ok") -> ok
A14: =Maps!$B$6 -> Map_02 | B14: =Factions!$B$5 -> Faction_01 | C14: =Maps!$F$6 -> Flowers | D14: =Factions!$C$5 -> Crystals | E14: =IF(D14=C14,Factions!$D$5,D14) -> Crystals | F14: =IF(D14=C14,"SWAPPED","-") -> - | G14: =IF(AND(C14<>"Flowers",E14<>"Flowers"),"Flowers",IF(AND(C14<>"Crystals",E14<>"Crystals"),"Crystals","Minerals")) -> Minerals | H14: =IF(OR(C14=E14,C14=G14,E14=G14),"BROKEN","ok") -> ok
A15: =Maps!$B$6 -> Map_02 | B15: =Factions!$B$6 -> Faction_02 | C15: =Maps!$F$6 -> Flowers | D15: =Factions!$C$6 -> Flowers | E15: =IF(D15=C15,Factions!$D$6,D15) -> Crystals | F15: =IF(D15=C15,"SWAPPED","-") -> SWAPPED | G15: =IF(AND(C15<>"Flowers",E15<>"Flowers"),"Flowers",IF(AND(C15<>"Crystals",E15<>"Crystals"),"Crystals","Minerals")) -> Minerals | H15: =IF(OR(C15=E15,C15=G15,E15=G15),"BROKEN","ok") -> ok
A16: =Maps!$B$6 -> Map_02 | B16: =Factions!$B$7 -> Faction_03 | C16: =Maps!$F$6 -> Flowers | D16: =Factions!$C$7 -> Minerals | E16: =IF(D16=C16,Factions!$D$7,D16) -> Minerals | F16: =IF(D16=C16,"SWAPPED","-") -> - | G16: =IF(AND(C16<>"Flowers",E16<>"Flowers"),"Flowers",IF(AND(C16<>"Crystals",E16<>"Crystals"),"Crystals","Minerals")) -> Crystals | H16: =IF(OR(C16=E16,C16=G16,E16=G16),"BROKEN","ok") -> ok
A17: =Maps!$B$6 -> Map_02 | B17: =Factions!$B$8 -> Faction_04 | C17: =Maps!$F$6 -> Flowers | D17: =Factions!$C$8 -> Crystals | E17: =IF(D17=C17,Factions!$D$8,D17) -> Crystals | F17: =IF(D17=C17,"SWAPPED","-") -> - | G17: =IF(AND(C17<>"Flowers",E17<>"Flowers"),"Flowers",IF(AND(C17<>"Crystals",E17<>"Crystals"),"Crystals","Minerals")) -> Minerals | H17: =IF(OR(C17=E17,C17=G17,E17=G17),"BROKEN","ok") -> ok
A18: =Maps!$B$6 -> Map_02 | B18: =Factions!$B$9 -> Faction_05 | C18: =Maps!$F$6 -> Flowers | D18: =Factions!$C$9 -> Flowers | E18: =IF(D18=C18,Factions!$D$9,D18) -> Minerals | F18: =IF(D18=C18,"SWAPPED","-") -> SWAPPED | G18: =IF(AND(C18<>"Flowers",E18<>"Flowers"),"Flowers",IF(AND(C18<>"Crystals",E18<>"Crystals"),"Crystals","Minerals")) -> Crystals | H18: =IF(OR(C18=E18,C18=G18,E18=G18),"BROKEN","ok") -> ok
A19: =Maps!$B$6 -> Map_02 | B19: =Factions!$B$10 -> Faction_06 | C19: =Maps!$F$6 -> Flowers | D19: =Factions!$C$10 -> Minerals | E19: =IF(D19=C19,Factions!$D$10,D19) -> Minerals | F19: =IF(D19=C19,"SWAPPED","-") -> - | G19: =IF(AND(C19<>"Flowers",E19<>"Flowers"),"Flowers",IF(AND(C19<>"Crystals",E19<>"Crystals"),"Crystals","Minerals")) -> Crystals | H19: =IF(OR(C19=E19,C19=G19,E19=G19),"BROKEN","ok") -> ok
A20: =Maps!$B$6 -> Map_02 | B20: =Factions!$B$11 -> Faction_07 | C20: =Maps!$F$6 -> Flowers | D20: =Factions!$C$11 -> Crystals | E20: =IF(D20=C20,Factions!$D$11,D20) -> Crystals | F20: =IF(D20=C20,"SWAPPED","-") -> - | G20: =IF(AND(C20<>"Flowers",E20<>"Flowers"),"Flowers",IF(AND(C20<>"Crystals",E20<>"Crystals"),"Crystals","Minerals")) -> Minerals | H20: =IF(OR(C20=E20,C20=G20,E20=G20),"BROKEN","ok") -> ok
A21: =Maps!$B$6 -> Map_02 | B21: =Factions!$B$12 -> Faction_08 | C21: =Maps!$F$6 -> Flowers | D21: =Factions!$C$12 -> Flowers | E21: =IF(D21=C21,Factions!$D$12,D21) -> Crystals | F21: =IF(D21=C21,"SWAPPED","-") -> SWAPPED | G21: =IF(AND(C21<>"Flowers",E21<>"Flowers"),"Flowers",IF(AND(C21<>"Crystals",E21<>"Crystals"),"Crystals","Minerals")) -> Minerals | H21: =IF(OR(C21=E21,C21=G21,E21=G21),"BROKEN","ok") -> ok
A22: =Maps!$B$6 -> Map_02 | B22: =Factions!$B$13 -> Faction_09 | C22: =Maps!$F$6 -> Flowers | D22: =Factions!$C$13 -> Minerals | E22: =IF(D22=C22,Factions!$D$13,D22) -> Minerals | F22: =IF(D22=C22,"SWAPPED","-") -> - | G22: =IF(AND(C22<>"Flowers",E22<>"Flowers"),"Flowers",IF(AND(C22<>"Crystals",E22<>"Crystals"),"Crystals","Minerals")) -> Crystals | H22: =IF(OR(C22=E22,C22=G22,E22=G22),"BROKEN","ok") -> ok
A23: =Maps!$B$7 -> Map_03 | B23: =Factions!$B$5 -> Faction_01 | C23: =Maps!$F$7 -> Minerals | D23: =Factions!$C$5 -> Crystals | E23: =IF(D23=C23,Factions!$D$5,D23) -> Crystals | F23: =IF(D23=C23,"SWAPPED","-") -> - | G23: =IF(AND(C23<>"Flowers",E23<>"Flowers"),"Flowers",IF(AND(C23<>"Crystals",E23<>"Crystals"),"Crystals","Minerals")) -> Flowers | H23: =IF(OR(C23=E23,C23=G23,E23=G23),"BROKEN","ok") -> ok
A24: =Maps!$B$7 -> Map_03 | B24: =Factions!$B$6 -> Faction_02 | C24: =Maps!$F$7 -> Minerals | D24: =Factions!$C$6 -> Flowers | E24: =IF(D24=C24,Factions!$D$6,D24) -> Flowers | F24: =IF(D24=C24,"SWAPPED","-") -> - | G24: =IF(AND(C24<>"Flowers",E24<>"Flowers"),"Flowers",IF(AND(C24<>"Crystals",E24<>"Crystals"),"Crystals","Minerals")) -> Crystals | H24: =IF(OR(C24=E24,C24=G24,E24=G24),"BROKEN","ok") -> ok
A25: =Maps!$B$7 -> Map_03 | B25: =Factions!$B$7 -> Faction_03 | C25: =Maps!$F$7 -> Minerals | D25: =Factions!$C$7 -> Minerals | E25: =IF(D25=C25,Factions!$D$7,D25) -> Flowers | F25: =IF(D25=C25,"SWAPPED","-") -> SWAPPED | G25: =IF(AND(C25<>"Flowers",E25<>"Flowers"),"Flowers",IF(AND(C25<>"Crystals",E25<>"Crystals"),"Crystals","Minerals")) -> Crystals | H25: =IF(OR(C25=E25,C25=G25,E25=G25),"BROKEN","ok") -> ok
A26: =Maps!$B$7 -> Map_03 | B26: =Factions!$B$8 -> Faction_04 | C26: =Maps!$F$7 -> Minerals | D26: =Factions!$C$8 -> Crystals | E26: =IF(D26=C26,Factions!$D$8,D26) -> Crystals | F26: =IF(D26=C26,"SWAPPED","-") -> - | G26: =IF(AND(C26<>"Flowers",E26<>"Flowers"),"Flowers",IF(AND(C26<>"Crystals",E26<>"Crystals"),"Crystals","Minerals")) -> Flowers | H26: =IF(OR(C26=E26,C26=G26,E26=G26),"BROKEN","ok") -> ok
A27: =Maps!$B$7 -> Map_03 | B27: =Factions!$B$9 -> Faction_05 | C27: =Maps!$F$7 -> Minerals | D27: =Factions!$C$9 -> Flowers | E27: =IF(D27=C27,Factions!$D$9,D27) -> Flowers | F27: =IF(D27=C27,"SWAPPED","-") -> - | G27: =IF(AND(C27<>"Flowers",E27<>"Flowers"),"Flowers",IF(AND(C27<>"Crystals",E27<>"Crystals"),"Crystals","Minerals")) -> Crystals | H27: =IF(OR(C27=E27,C27=G27,E27=G27),"BROKEN","ok") -> ok
A28: =Maps!$B$7 -> Map_03 | B28: =Factions!$B$10 -> Faction_06 | C28: =Maps!$F$7 -> Minerals | D28: =Factions!$C$10 -> Minerals | E28: =IF(D28=C28,Factions!$D$10,D28) -> Crystals | F28: =IF(D28=C28,"SWAPPED","-") -> SWAPPED | G28: =IF(AND(C28<>"Flowers",E28<>"Flowers"),"Flowers",IF(AND(C28<>"Crystals",E28<>"Crystals"),"Crystals","Minerals")) -> Flowers | H28: =IF(OR(C28=E28,C28=G28,E28=G28),"BROKEN","ok") -> ok
A29: =Maps!$B$7 -> Map_03 | B29: =Factions!$B$11 -> Faction_07 | C29: =Maps!$F$7 -> Minerals | D29: =Factions!$C$11 -> Crystals | E29: =IF(D29=C29,Factions!$D$11,D29) -> Crystals | F29: =IF(D29=C29,"SWAPPED","-") -> - | G29: =IF(AND(C29<>"Flowers",E29<>"Flowers"),"Flowers",IF(AND(C29<>"Crystals",E29<>"Crystals"),"Crystals","Minerals")) -> Flowers | H29: =IF(OR(C29=E29,C29=G29,E29=G29),"BROKEN","ok") -> ok
A30: =Maps!$B$7 -> Map_03 | B30: =Factions!$B$12 -> Faction_08 | C30: =Maps!$F$7 -> Minerals | D30: =Factions!$C$12 -> Flowers | E30: =IF(D30=C30,Factions!$D$12,D30) -> Flowers | F30: =IF(D30=C30,"SWAPPED","-") -> - | G30: =IF(AND(C30<>"Flowers",E30<>"Flowers"),"Flowers",IF(AND(C30<>"Crystals",E30<>"Crystals"),"Crystals","Minerals")) -> Crystals | H30: =IF(OR(C30=E30,C30=G30,E30=G30),"BROKEN","ok") -> ok
A31: =Maps!$B$7 -> Map_03 | B31: =Factions!$B$13 -> Faction_09 | C31: =Maps!$F$7 -> Minerals | D31: =Factions!$C$13 -> Minerals | E31: =IF(D31=C31,Factions!$D$13,D31) -> Flowers | F31: =IF(D31=C31,"SWAPPED","-") -> SWAPPED | G31: =IF(AND(C31<>"Flowers",E31<>"Flowers"),"Flowers",IF(AND(C31<>"Crystals",E31<>"Crystals"),"Crystals","Minerals")) -> Crystals | H31: =IF(OR(C31=E31,C31=G31,E31=G31),"BROKEN","ok") -> ok
A32: =Maps!$B$8 -> Map_04 | B32: =Factions!$B$5 -> Faction_01 | C32: =Maps!$F$8 -> Minerals | D32: =Factions!$C$5 -> Crystals | E32: =IF(D32=C32,Factions!$D$5,D32) -> Crystals | F32: =IF(D32=C32,"SWAPPED","-") -> - | G32: =IF(AND(C32<>"Flowers",E32<>"Flowers"),"Flowers",IF(AND(C32<>"Crystals",E32<>"Crystals"),"Crystals","Minerals")) -> Flowers | H32: =IF(OR(C32=E32,C32=G32,E32=G32),"BROKEN","ok") -> ok
A33: =Maps!$B$8 -> Map_04 | B33: =Factions!$B$6 -> Faction_02 | C33: =Maps!$F$8 -> Minerals | D33: =Factions!$C$6 -> Flowers | E33: =IF(D33=C33,Factions!$D$6,D33) -> Flowers | F33: =IF(D33=C33,"SWAPPED","-") -> - | G33: =IF(AND(C33<>"Flowers",E33<>"Flowers"),"Flowers",IF(AND(C33<>"Crystals",E33<>"Crystals"),"Crystals","Minerals")) -> Crystals | H33: =IF(OR(C33=E33,C33=G33,E33=G33),"BROKEN","ok") -> ok
A34: =Maps!$B$8 -> Map_04 | B34: =Factions!$B$7 -> Faction_03 | C34: =Maps!$F$8 -> Minerals | D34: =Factions!$C$7 -> Minerals | E34: =IF(D34=C34,Factions!$D$7,D34) -> Flowers | F34: =IF(D34=C34,"SWAPPED","-") -> SWAPPED | G34: =IF(AND(C34<>"Flowers",E34<>"Flowers"),"Flowers",IF(AND(C34<>"Crystals",E34<>"Crystals"),"Crystals","Minerals")) -> Crystals | H34: =IF(OR(C34=E34,C34=G34,E34=G34),"BROKEN","ok") -> ok
A35: =Maps!$B$8 -> Map_04 | B35: =Factions!$B$8 -> Faction_04 | C35: =Maps!$F$8 -> Minerals | D35: =Factions!$C$8 -> Crystals | E35: =IF(D35=C35,Factions!$D$8,D35) -> Crystals | F35: =IF(D35=C35,"SWAPPED","-") -> - | G35: =IF(AND(C35<>"Flowers",E35<>"Flowers"),"Flowers",IF(AND(C35<>"Crystals",E35<>"Crystals"),"Crystals","Minerals")) -> Flowers | H35: =IF(OR(C35=E35,C35=G35,E35=G35),"BROKEN","ok") -> ok
A36: =Maps!$B$8 -> Map_04 | B36: =Factions!$B$9 -> Faction_05 | C36: =Maps!$F$8 -> Minerals | D36: =Factions!$C$9 -> Flowers | E36: =IF(D36=C36,Factions!$D$9,D36) -> Flowers | F36: =IF(D36=C36,"SWAPPED","-") -> - | G36: =IF(AND(C36<>"Flowers",E36<>"Flowers"),"Flowers",IF(AND(C36<>"Crystals",E36<>"Crystals"),"Crystals","Minerals")) -> Crystals | H36: =IF(OR(C36=E36,C36=G36,E36=G36),"BROKEN","ok") -> ok
A37: =Maps!$B$8 -> Map_04 | B37: =Factions!$B$10 -> Faction_06 | C37: =Maps!$F$8 -> Minerals | D37: =Factions!$C$10 -> Minerals | E37: =IF(D37=C37,Factions!$D$10,D37) -> Crystals | F37: =IF(D37=C37,"SWAPPED","-") -> SWAPPED | G37: =IF(AND(C37<>"Flowers",E37<>"Flowers"),"Flowers",IF(AND(C37<>"Crystals",E37<>"Crystals"),"Crystals","Minerals")) -> Flowers | H37: =IF(OR(C37=E37,C37=G37,E37=G37),"BROKEN","ok") -> ok
A38: =Maps!$B$8 -> Map_04 | B38: =Factions!$B$11 -> Faction_07 | C38: =Maps!$F$8 -> Minerals | D38: =Factions!$C$11 -> Crystals | E38: =IF(D38=C38,Factions!$D$11,D38) -> Crystals | F38: =IF(D38=C38,"SWAPPED","-") -> - | G38: =IF(AND(C38<>"Flowers",E38<>"Flowers"),"Flowers",IF(AND(C38<>"Crystals",E38<>"Crystals"),"Crystals","Minerals")) -> Flowers | H38: =IF(OR(C38=E38,C38=G38,E38=G38),"BROKEN","ok") -> ok
A39: =Maps!$B$8 -> Map_04 | B39: =Factions!$B$12 -> Faction_08 | C39: =Maps!$F$8 -> Minerals | D39: =Factions!$C$12 -> Flowers | E39: =IF(D39=C39,Factions!$D$12,D39) -> Flowers | F39: =IF(D39=C39,"SWAPPED","-") -> - | G39: =IF(AND(C39<>"Flowers",E39<>"Flowers"),"Flowers",IF(AND(C39<>"Crystals",E39<>"Crystals"),"Crystals","Minerals")) -> Crystals | H39: =IF(OR(C39=E39,C39=G39,E39=G39),"BROKEN","ok") -> ok
A40: =Maps!$B$8 -> Map_04 | B40: =Factions!$B$13 -> Faction_09 | C40: =Maps!$F$8 -> Minerals | D40: =Factions!$C$13 -> Minerals | E40: =IF(D40=C40,Factions!$D$13,D40) -> Flowers | F40: =IF(D40=C40,"SWAPPED","-") -> SWAPPED | G40: =IF(AND(C40<>"Flowers",E40<>"Flowers"),"Flowers",IF(AND(C40<>"Crystals",E40<>"Crystals"),"Crystals","Minerals")) -> Crystals | H40: =IF(OR(C40=E40,C40=G40,E40=G40),"BROKEN","ok") -> ok
A41: =Maps!$B$9 -> Map_05 | B41: =Factions!$B$5 -> Faction_01 | C41: =Maps!$F$9 -> Crystals | D41: =Factions!$C$5 -> Crystals | E41: =IF(D41=C41,Factions!$D$5,D41) -> Minerals | F41: =IF(D41=C41,"SWAPPED","-") -> SWAPPED | G41: =IF(AND(C41<>"Flowers",E41<>"Flowers"),"Flowers",IF(AND(C41<>"Crystals",E41<>"Crystals"),"Crystals","Minerals")) -> Flowers | H41: =IF(OR(C41=E41,C41=G41,E41=G41),"BROKEN","ok") -> ok
A42: =Maps!$B$9 -> Map_05 | B42: =Factions!$B$6 -> Faction_02 | C42: =Maps!$F$9 -> Crystals | D42: =Factions!$C$6 -> Flowers | E42: =IF(D42=C42,Factions!$D$6,D42) -> Flowers | F42: =IF(D42=C42,"SWAPPED","-") -> - | G42: =IF(AND(C42<>"Flowers",E42<>"Flowers"),"Flowers",IF(AND(C42<>"Crystals",E42<>"Crystals"),"Crystals","Minerals")) -> Minerals | H42: =IF(OR(C42=E42,C42=G42,E42=G42),"BROKEN","ok") -> ok
A43: =Maps!$B$9 -> Map_05 | B43: =Factions!$B$7 -> Faction_03 | C43: =Maps!$F$9 -> Crystals | D43: =Factions!$C$7 -> Minerals | E43: =IF(D43=C43,Factions!$D$7,D43) -> Minerals | F43: =IF(D43=C43,"SWAPPED","-") -> - | G43: =IF(AND(C43<>"Flowers",E43<>"Flowers"),"Flowers",IF(AND(C43<>"Crystals",E43<>"Crystals"),"Crystals","Minerals")) -> Flowers | H43: =IF(OR(C43=E43,C43=G43,E43=G43),"BROKEN","ok") -> ok
A44: =Maps!$B$9 -> Map_05 | B44: =Factions!$B$8 -> Faction_04 | C44: =Maps!$F$9 -> Crystals | D44: =Factions!$C$8 -> Crystals | E44: =IF(D44=C44,Factions!$D$8,D44) -> Flowers | F44: =IF(D44=C44,"SWAPPED","-") -> SWAPPED | G44: =IF(AND(C44<>"Flowers",E44<>"Flowers"),"Flowers",IF(AND(C44<>"Crystals",E44<>"Crystals"),"Crystals","Minerals")) -> Minerals | H44: =IF(OR(C44=E44,C44=G44,E44=G44),"BROKEN","ok") -> ok
A45: =Maps!$B$9 -> Map_05 | B45: =Factions!$B$9 -> Faction_05 | C45: =Maps!$F$9 -> Crystals | D45: =Factions!$C$9 -> Flowers | E45: =IF(D45=C45,Factions!$D$9,D45) -> Flowers | F45: =IF(D45=C45,"SWAPPED","-") -> - | G45: =IF(AND(C45<>"Flowers",E45<>"Flowers"),"Flowers",IF(AND(C45<>"Crystals",E45<>"Crystals"),"Crystals","Minerals")) -> Minerals | H45: =IF(OR(C45=E45,C45=G45,E45=G45),"BROKEN","ok") -> ok
A46: =Maps!$B$9 -> Map_05 | B46: =Factions!$B$10 -> Faction_06 | C46: =Maps!$F$9 -> Crystals | D46: =Factions!$C$10 -> Minerals | E46: =IF(D46=C46,Factions!$D$10,D46) -> Minerals | F46: =IF(D46=C46,"SWAPPED","-") -> - | G46: =IF(AND(C46<>"Flowers",E46<>"Flowers"),"Flowers",IF(AND(C46<>"Crystals",E46<>"Crystals"),"Crystals","Minerals")) -> Flowers | H46: =IF(OR(C46=E46,C46=G46,E46=G46),"BROKEN","ok") -> ok
A47: =Maps!$B$9 -> Map_05 | B47: =Factions!$B$11 -> Faction_07 | C47: =Maps!$F$9 -> Crystals | D47: =Factions!$C$11 -> Crystals | E47: =IF(D47=C47,Factions!$D$11,D47) -> Minerals | F47: =IF(D47=C47,"SWAPPED","-") -> SWAPPED | G47: =IF(AND(C47<>"Flowers",E47<>"Flowers"),"Flowers",IF(AND(C47<>"Crystals",E47<>"Crystals"),"Crystals","Minerals")) -> Flowers | H47: =IF(OR(C47=E47,C47=G47,E47=G47),"BROKEN","ok") -> ok
A48: =Maps!$B$9 -> Map_05 | B48: =Factions!$B$12 -> Faction_08 | C48: =Maps!$F$9 -> Crystals | D48: =Factions!$C$12 -> Flowers | E48: =IF(D48=C48,Factions!$D$12,D48) -> Flowers | F48: =IF(D48=C48,"SWAPPED","-") -> - | G48: =IF(AND(C48<>"Flowers",E48<>"Flowers"),"Flowers",IF(AND(C48<>"Crystals",E48<>"Crystals"),"Crystals","Minerals")) -> Minerals | H48: =IF(OR(C48=E48,C48=G48,E48=G48),"BROKEN","ok") -> ok
A49: =Maps!$B$9 -> Map_05 | B49: =Factions!$B$13 -> Faction_09 | C49: =Maps!$F$9 -> Crystals | D49: =Factions!$C$13 -> Minerals | E49: =IF(D49=C49,Factions!$D$13,D49) -> Minerals | F49: =IF(D49=C49,"SWAPPED","-") -> - | G49: =IF(AND(C49<>"Flowers",E49<>"Flowers"),"Flowers",IF(AND(C49<>"Crystals",E49<>"Crystals"),"Crystals","Minerals")) -> Flowers | H49: =IF(OR(C49=E49,C49=G49,E49=G49),"BROKEN","ok") -> ok
A50: =Maps!$B$10 -> Map_06 | B50: =Factions!$B$5 -> Faction_01 | C50: =Maps!$F$10 -> Flowers | D50: =Factions!$C$5 -> Crystals | E50: =IF(D50=C50,Factions!$D$5,D50) -> Crystals | F50: =IF(D50=C50,"SWAPPED","-") -> - | G50: =IF(AND(C50<>"Flowers",E50<>"Flowers"),"Flowers",IF(AND(C50<>"Crystals",E50<>"Crystals"),"Crystals","Minerals")) -> Minerals | H50: =IF(OR(C50=E50,C50=G50,E50=G50),"BROKEN","ok") -> ok
A51: =Maps!$B$10 -> Map_06 | B51: =Factions!$B$6 -> Faction_02 | C51: =Maps!$F$10 -> Flowers | D51: =Factions!$C$6 -> Flowers | E51: =IF(D51=C51,Factions!$D$6,D51) -> Crystals | F51: =IF(D51=C51,"SWAPPED","-") -> SWAPPED | G51: =IF(AND(C51<>"Flowers",E51<>"Flowers"),"Flowers",IF(AND(C51<>"Crystals",E51<>"Crystals"),"Crystals","Minerals")) -> Minerals | H51: =IF(OR(C51=E51,C51=G51,E51=G51),"BROKEN","ok") -> ok
A52: =Maps!$B$10 -> Map_06 | B52: =Factions!$B$7 -> Faction_03 | C52: =Maps!$F$10 -> Flowers | D52: =Factions!$C$7 -> Minerals | E52: =IF(D52=C52,Factions!$D$7,D52) -> Minerals | F52: =IF(D52=C52,"SWAPPED","-") -> - | G52: =IF(AND(C52<>"Flowers",E52<>"Flowers"),"Flowers",IF(AND(C52<>"Crystals",E52<>"Crystals"),"Crystals","Minerals")) -> Crystals | H52: =IF(OR(C52=E52,C52=G52,E52=G52),"BROKEN","ok") -> ok
A53: =Maps!$B$10 -> Map_06 | B53: =Factions!$B$8 -> Faction_04 | C53: =Maps!$F$10 -> Flowers | D53: =Factions!$C$8 -> Crystals | E53: =IF(D53=C53,Factions!$D$8,D53) -> Crystals | F53: =IF(D53=C53,"SWAPPED","-") -> - | G53: =IF(AND(C53<>"Flowers",E53<>"Flowers"),"Flowers",IF(AND(C53<>"Crystals",E53<>"Crystals"),"Crystals","Minerals")) -> Minerals | H53: =IF(OR(C53=E53,C53=G53,E53=G53),"BROKEN","ok") -> ok
A54: =Maps!$B$10 -> Map_06 | B54: =Factions!$B$9 -> Faction_05 | C54: =Maps!$F$10 -> Flowers | D54: =Factions!$C$9 -> Flowers | E54: =IF(D54=C54,Factions!$D$9,D54) -> Minerals | F54: =IF(D54=C54,"SWAPPED","-") -> SWAPPED | G54: =IF(AND(C54<>"Flowers",E54<>"Flowers"),"Flowers",IF(AND(C54<>"Crystals",E54<>"Crystals"),"Crystals","Minerals")) -> Crystals | H54: =IF(OR(C54=E54,C54=G54,E54=G54),"BROKEN","ok") -> ok
A55: =Maps!$B$10 -> Map_06 | B55: =Factions!$B$10 -> Faction_06 | C55: =Maps!$F$10 -> Flowers | D55: =Factions!$C$10 -> Minerals | E55: =IF(D55=C55,Factions!$D$10,D55) -> Minerals | F55: =IF(D55=C55,"SWAPPED","-") -> - | G55: =IF(AND(C55<>"Flowers",E55<>"Flowers"),"Flowers",IF(AND(C55<>"Crystals",E55<>"Crystals"),"Crystals","Minerals")) -> Crystals | H55: =IF(OR(C55=E55,C55=G55,E55=G55),"BROKEN","ok") -> ok
A56: =Maps!$B$10 -> Map_06 | B56: =Factions!$B$11 -> Faction_07 | C56: =Maps!$F$10 -> Flowers | D56: =Factions!$C$11 -> Crystals | E56: =IF(D56=C56,Factions!$D$11,D56) -> Crystals | F56: =IF(D56=C56,"SWAPPED","-") -> - | G56: =IF(AND(C56<>"Flowers",E56<>"Flowers"),"Flowers",IF(AND(C56<>"Crystals",E56<>"Crystals"),"Crystals","Minerals")) -> Minerals | H56: =IF(OR(C56=E56,C56=G56,E56=G56),"BROKEN","ok") -> ok
A57: =Maps!$B$10 -> Map_06 | B57: =Factions!$B$12 -> Faction_08 | C57: =Maps!$F$10 -> Flowers | D57: =Factions!$C$12 -> Flowers | E57: =IF(D57=C57,Factions!$D$12,D57) -> Crystals | F57: =IF(D57=C57,"SWAPPED","-") -> SWAPPED | G57: =IF(AND(C57<>"Flowers",E57<>"Flowers"),"Flowers",IF(AND(C57<>"Crystals",E57<>"Crystals"),"Crystals","Minerals")) -> Minerals | H57: =IF(OR(C57=E57,C57=G57,E57=G57),"BROKEN","ok") -> ok
A58: =Maps!$B$10 -> Map_06 | B58: =Factions!$B$13 -> Faction_09 | C58: =Maps!$F$10 -> Flowers | D58: =Factions!$C$13 -> Minerals | E58: =IF(D58=C58,Factions!$D$13,D58) -> Minerals | F58: =IF(D58=C58,"SWAPPED","-") -> - | G58: =IF(AND(C58<>"Flowers",E58<>"Flowers"),"Flowers",IF(AND(C58<>"Crystals",E58<>"Crystals"),"Crystals","Minerals")) -> Crystals | H58: =IF(OR(C58=E58,C58=G58,E58=G58),"BROKEN","ok") -> ok
A59: =Maps!$B$11 -> Map_07 | B59: =Factions!$B$5 -> Faction_01 | C59: =Maps!$F$11 -> Minerals | D59: =Factions!$C$5 -> Crystals | E59: =IF(D59=C59,Factions!$D$5,D59) -> Crystals | F59: =IF(D59=C59,"SWAPPED","-") -> - | G59: =IF(AND(C59<>"Flowers",E59<>"Flowers"),"Flowers",IF(AND(C59<>"Crystals",E59<>"Crystals"),"Crystals","Minerals")) -> Flowers | H59: =IF(OR(C59=E59,C59=G59,E59=G59),"BROKEN","ok") -> ok
A60: =Maps!$B$11 -> Map_07 | B60: =Factions!$B$6 -> Faction_02 | C60: =Maps!$F$11 -> Minerals | D60: =Factions!$C$6 -> Flowers | E60: =IF(D60=C60,Factions!$D$6,D60) -> Flowers | F60: =IF(D60=C60,"SWAPPED","-") -> - | G60: =IF(AND(C60<>"Flowers",E60<>"Flowers"),"Flowers",IF(AND(C60<>"Crystals",E60<>"Crystals"),"Crystals","Minerals")) -> Crystals | H60: =IF(OR(C60=E60,C60=G60,E60=G60),"BROKEN","ok") -> ok
A61: =Maps!$B$11 -> Map_07 | B61: =Factions!$B$7 -> Faction_03 | C61: =Maps!$F$11 -> Minerals | D61: =Factions!$C$7 -> Minerals | E61: =IF(D61=C61,Factions!$D$7,D61) -> Flowers | F61: =IF(D61=C61,"SWAPPED","-") -> SWAPPED | G61: =IF(AND(C61<>"Flowers",E61<>"Flowers"),"Flowers",IF(AND(C61<>"Crystals",E61<>"Crystals"),"Crystals","Minerals")) -> Crystals | H61: =IF(OR(C61=E61,C61=G61,E61=G61),"BROKEN","ok") -> ok
A62: =Maps!$B$11 -> Map_07 | B62: =Factions!$B$8 -> Faction_04 | C62: =Maps!$F$11 -> Minerals | D62: =Factions!$C$8 -> Crystals | E62: =IF(D62=C62,Factions!$D$8,D62) -> Crystals | F62: =IF(D62=C62,"SWAPPED","-") -> - | G62: =IF(AND(C62<>"Flowers",E62<>"Flowers"),"Flowers",IF(AND(C62<>"Crystals",E62<>"Crystals"),"Crystals","Minerals")) -> Flowers | H62: =IF(OR(C62=E62,C62=G62,E62=G62),"BROKEN","ok") -> ok
A63: =Maps!$B$11 -> Map_07 | B63: =Factions!$B$9 -> Faction_05 | C63: =Maps!$F$11 -> Minerals | D63: =Factions!$C$9 -> Flowers | E63: =IF(D63=C63,Factions!$D$9,D63) -> Flowers | F63: =IF(D63=C63,"SWAPPED","-") -> - | G63: =IF(AND(C63<>"Flowers",E63<>"Flowers"),"Flowers",IF(AND(C63<>"Crystals",E63<>"Crystals"),"Crystals","Minerals")) -> Crystals | H63: =IF(OR(C63=E63,C63=G63,E63=G63),"BROKEN","ok") -> ok
A64: =Maps!$B$11 -> Map_07 | B64: =Factions!$B$10 -> Faction_06 | C64: =Maps!$F$11 -> Minerals | D64: =Factions!$C$10 -> Minerals | E64: =IF(D64=C64,Factions!$D$10,D64) -> Crystals | F64: =IF(D64=C64,"SWAPPED","-") -> SWAPPED | G64: =IF(AND(C64<>"Flowers",E64<>"Flowers"),"Flowers",IF(AND(C64<>"Crystals",E64<>"Crystals"),"Crystals","Minerals")) -> Flowers | H64: =IF(OR(C64=E64,C64=G64,E64=G64),"BROKEN","ok") -> ok
A65: =Maps!$B$11 -> Map_07 | B65: =Factions!$B$11 -> Faction_07 | C65: =Maps!$F$11 -> Minerals | D65: =Factions!$C$11 -> Crystals | E65: =IF(D65=C65,Factions!$D$11,D65) -> Crystals | F65: =IF(D65=C65,"SWAPPED","-") -> - | G65: =IF(AND(C65<>"Flowers",E65<>"Flowers"),"Flowers",IF(AND(C65<>"Crystals",E65<>"Crystals"),"Crystals","Minerals")) -> Flowers | H65: =IF(OR(C65=E65,C65=G65,E65=G65),"BROKEN","ok") -> ok
A66: =Maps!$B$11 -> Map_07 | B66: =Factions!$B$12 -> Faction_08 | C66: =Maps!$F$11 -> Minerals | D66: =Factions!$C$12 -> Flowers | E66: =IF(D66=C66,Factions!$D$12,D66) -> Flowers | F66: =IF(D66=C66,"SWAPPED","-") -> - | G66: =IF(AND(C66<>"Flowers",E66<>"Flowers"),"Flowers",IF(AND(C66<>"Crystals",E66<>"Crystals"),"Crystals","Minerals")) -> Crystals | H66: =IF(OR(C66=E66,C66=G66,E66=G66),"BROKEN","ok") -> ok
A67: =Maps!$B$11 -> Map_07 | B67: =Factions!$B$13 -> Faction_09 | C67: =Maps!$F$11 -> Minerals | D67: =Factions!$C$13 -> Minerals | E67: =IF(D67=C67,Factions!$D$13,D67) -> Flowers | F67: =IF(D67=C67,"SWAPPED","-") -> SWAPPED | G67: =IF(AND(C67<>"Flowers",E67<>"Flowers"),"Flowers",IF(AND(C67<>"Crystals",E67<>"Crystals"),"Crystals","Minerals")) -> Crystals | H67: =IF(OR(C67=E67,C67=G67,E67=G67),"BROKEN","ok") -> ok
A68: =Maps!$B$12 -> Map_08 | B68: =Factions!$B$5 -> Faction_01 | C68: =Maps!$F$12 -> Crystals | D68: =Factions!$C$5 -> Crystals | E68: =IF(D68=C68,Factions!$D$5,D68) -> Minerals | F68: =IF(D68=C68,"SWAPPED","-") -> SWAPPED | G68: =IF(AND(C68<>"Flowers",E68<>"Flowers"),"Flowers",IF(AND(C68<>"Crystals",E68<>"Crystals"),"Crystals","Minerals")) -> Flowers | H68: =IF(OR(C68=E68,C68=G68,E68=G68),"BROKEN","ok") -> ok
A69: =Maps!$B$12 -> Map_08 | B69: =Factions!$B$6 -> Faction_02 | C69: =Maps!$F$12 -> Crystals | D69: =Factions!$C$6 -> Flowers | E69: =IF(D69=C69,Factions!$D$6,D69) -> Flowers | F69: =IF(D69=C69,"SWAPPED","-") -> - | G69: =IF(AND(C69<>"Flowers",E69<>"Flowers"),"Flowers",IF(AND(C69<>"Crystals",E69<>"Crystals"),"Crystals","Minerals")) -> Minerals | H69: =IF(OR(C69=E69,C69=G69,E69=G69),"BROKEN","ok") -> ok
A70: =Maps!$B$12 -> Map_08 | B70: =Factions!$B$7 -> Faction_03 | C70: =Maps!$F$12 -> Crystals | D70: =Factions!$C$7 -> Minerals | E70: =IF(D70=C70,Factions!$D$7,D70) -> Minerals | F70: =IF(D70=C70,"SWAPPED","-") -> - | G70: =IF(AND(C70<>"Flowers",E70<>"Flowers"),"Flowers",IF(AND(C70<>"Crystals",E70<>"Crystals"),"Crystals","Minerals")) -> Flowers | H70: =IF(OR(C70=E70,C70=G70,E70=G70),"BROKEN","ok") -> ok
A71: =Maps!$B$12 -> Map_08 | B71: =Factions!$B$8 -> Faction_04 | C71: =Maps!$F$12 -> Crystals | D71: =Factions!$C$8 -> Crystals | E71: =IF(D71=C71,Factions!$D$8,D71) -> Flowers | F71: =IF(D71=C71,"SWAPPED","-") -> SWAPPED | G71: =IF(AND(C71<>"Flowers",E71<>"Flowers"),"Flowers",IF(AND(C71<>"Crystals",E71<>"Crystals"),"Crystals","Minerals")) -> Minerals | H71: =IF(OR(C71=E71,C71=G71,E71=G71),"BROKEN","ok") -> ok
A72: =Maps!$B$12 -> Map_08 | B72: =Factions!$B$9 -> Faction_05 | C72: =Maps!$F$12 -> Crystals | D72: =Factions!$C$9 -> Flowers | E72: =IF(D72=C72,Factions!$D$9,D72) -> Flowers | F72: =IF(D72=C72,"SWAPPED","-") -> - | G72: =IF(AND(C72<>"Flowers",E72<>"Flowers"),"Flowers",IF(AND(C72<>"Crystals",E72<>"Crystals"),"Crystals","Minerals")) -> Minerals | H72: =IF(OR(C72=E72,C72=G72,E72=G72),"BROKEN","ok") -> ok
A73: =Maps!$B$12 -> Map_08 | B73: =Factions!$B$10 -> Faction_06 | C73: =Maps!$F$12 -> Crystals | D73: =Factions!$C$10 -> Minerals | E73: =IF(D73=C73,Factions!$D$10,D73) -> Minerals | F73: =IF(D73=C73,"SWAPPED","-") -> - | G73: =IF(AND(C73<>"Flowers",E73<>"Flowers"),"Flowers",IF(AND(C73<>"Crystals",E73<>"Crystals"),"Crystals","Minerals")) -> Flowers | H73: =IF(OR(C73=E73,C73=G73,E73=G73),"BROKEN","ok") -> ok
A74: =Maps!$B$12 -> Map_08 | B74: =Factions!$B$11 -> Faction_07 | C74: =Maps!$F$12 -> Crystals | D74: =Factions!$C$11 -> Crystals | E74: =IF(D74=C74,Factions!$D$11,D74) -> Minerals | F74: =IF(D74=C74,"SWAPPED","-") -> SWAPPED | G74: =IF(AND(C74<>"Flowers",E74<>"Flowers"),"Flowers",IF(AND(C74<>"Crystals",E74<>"Crystals"),"Crystals","Minerals")) -> Flowers | H74: =IF(OR(C74=E74,C74=G74,E74=G74),"BROKEN","ok") -> ok
A75: =Maps!$B$12 -> Map_08 | B75: =Factions!$B$12 -> Faction_08 | C75: =Maps!$F$12 -> Crystals | D75: =Factions!$C$12 -> Flowers | E75: =IF(D75=C75,Factions!$D$12,D75) -> Flowers | F75: =IF(D75=C75,"SWAPPED","-") -> - | G75: =IF(AND(C75<>"Flowers",E75<>"Flowers"),"Flowers",IF(AND(C75<>"Crystals",E75<>"Crystals"),"Crystals","Minerals")) -> Minerals | H75: =IF(OR(C75=E75,C75=G75,E75=G75),"BROKEN","ok") -> ok
A76: =Maps!$B$12 -> Map_08 | B76: =Factions!$B$13 -> Faction_09 | C76: =Maps!$F$12 -> Crystals | D76: =Factions!$C$13 -> Minerals | E76: =IF(D76=C76,Factions!$D$13,D76) -> Minerals | F76: =IF(D76=C76,"SWAPPED","-") -> - | G76: =IF(AND(C76<>"Flowers",E76<>"Flowers"),"Flowers",IF(AND(C76<>"Crystals",E76<>"Crystals"),"Crystals","Minerals")) -> Flowers | H76: =IF(OR(C76=E76,C76=G76,E76=G76),"BROKEN","ok") -> ok
A77: =Maps!$B$13 -> Map_09 | B77: =Factions!$B$5 -> Faction_01 | C77: =Maps!$F$13 -> Crystals | D77: =Factions!$C$5 -> Crystals | E77: =IF(D77=C77,Factions!$D$5,D77) -> Minerals | F77: =IF(D77=C77,"SWAPPED","-") -> SWAPPED | G77: =IF(AND(C77<>"Flowers",E77<>"Flowers"),"Flowers",IF(AND(C77<>"Crystals",E77<>"Crystals"),"Crystals","Minerals")) -> Flowers | H77: =IF(OR(C77=E77,C77=G77,E77=G77),"BROKEN","ok") -> ok
A78: =Maps!$B$13 -> Map_09 | B78: =Factions!$B$6 -> Faction_02 | C78: =Maps!$F$13 -> Crystals | D78: =Factions!$C$6 -> Flowers | E78: =IF(D78=C78,Factions!$D$6,D78) -> Flowers | F78: =IF(D78=C78,"SWAPPED","-") -> - | G78: =IF(AND(C78<>"Flowers",E78<>"Flowers"),"Flowers",IF(AND(C78<>"Crystals",E78<>"Crystals"),"Crystals","Minerals")) -> Minerals | H78: =IF(OR(C78=E78,C78=G78,E78=G78),"BROKEN","ok") -> ok
A79: =Maps!$B$13 -> Map_09 | B79: =Factions!$B$7 -> Faction_03 | C79: =Maps!$F$13 -> Crystals | D79: =Factions!$C$7 -> Minerals | E79: =IF(D79=C79,Factions!$D$7,D79) -> Minerals | F79: =IF(D79=C79,"SWAPPED","-") -> - | G79: =IF(AND(C79<>"Flowers",E79<>"Flowers"),"Flowers",IF(AND(C79<>"Crystals",E79<>"Crystals"),"Crystals","Minerals")) -> Flowers | H79: =IF(OR(C79=E79,C79=G79,E79=G79),"BROKEN","ok") -> ok
A80: =Maps!$B$13 -> Map_09 | B80: =Factions!$B$8 -> Faction_04 | C80: =Maps!$F$13 -> Crystals | D80: =Factions!$C$8 -> Crystals | E80: =IF(D80=C80,Factions!$D$8,D80) -> Flowers | F80: =IF(D80=C80,"SWAPPED","-") -> SWAPPED | G80: =IF(AND(C80<>"Flowers",E80<>"Flowers"),"Flowers",IF(AND(C80<>"Crystals",E80<>"Crystals"),"Crystals","Minerals")) -> Minerals | H80: =IF(OR(C80=E80,C80=G80,E80=G80),"BROKEN","ok") -> ok
A81: =Maps!$B$13 -> Map_09 | B81: =Factions!$B$9 -> Faction_05 | C81: =Maps!$F$13 -> Crystals | D81: =Factions!$C$9 -> Flowers | E81: =IF(D81=C81,Factions!$D$9,D81) -> Flowers | F81: =IF(D81=C81,"SWAPPED","-") -> - | G81: =IF(AND(C81<>"Flowers",E81<>"Flowers"),"Flowers",IF(AND(C81<>"Crystals",E81<>"Crystals"),"Crystals","Minerals")) -> Minerals | H81: =IF(OR(C81=E81,C81=G81,E81=G81),"BROKEN","ok") -> ok
A82: =Maps!$B$13 -> Map_09 | B82: =Factions!$B$10 -> Faction_06 | C82: =Maps!$F$13 -> Crystals | D82: =Factions!$C$10 -> Minerals | E82: =IF(D82=C82,Factions!$D$10,D82) -> Minerals | F82: =IF(D82=C82,"SWAPPED","-") -> - | G82: =IF(AND(C82<>"Flowers",E82<>"Flowers"),"Flowers",IF(AND(C82<>"Crystals",E82<>"Crystals"),"Crystals","Minerals")) -> Flowers | H82: =IF(OR(C82=E82,C82=G82,E82=G82),"BROKEN","ok") -> ok
A83: =Maps!$B$13 -> Map_09 | B83: =Factions!$B$11 -> Faction_07 | C83: =Maps!$F$13 -> Crystals | D83: =Factions!$C$11 -> Crystals | E83: =IF(D83=C83,Factions!$D$11,D83) -> Minerals | F83: =IF(D83=C83,"SWAPPED","-") -> SWAPPED | G83: =IF(AND(C83<>"Flowers",E83<>"Flowers"),"Flowers",IF(AND(C83<>"Crystals",E83<>"Crystals"),"Crystals","Minerals")) -> Flowers | H83: =IF(OR(C83=E83,C83=G83,E83=G83),"BROKEN","ok") -> ok
A84: =Maps!$B$13 -> Map_09 | B84: =Factions!$B$12 -> Faction_08 | C84: =Maps!$F$13 -> Crystals | D84: =Factions!$C$12 -> Flowers | E84: =IF(D84=C84,Factions!$D$12,D84) -> Flowers | F84: =IF(D84=C84,"SWAPPED","-") -> - | G84: =IF(AND(C84<>"Flowers",E84<>"Flowers"),"Flowers",IF(AND(C84<>"Crystals",E84<>"Crystals"),"Crystals","Minerals")) -> Minerals | H84: =IF(OR(C84=E84,C84=G84,E84=G84),"BROKEN","ok") -> ok
A85: =Maps!$B$13 -> Map_09 | B85: =Factions!$B$13 -> Faction_09 | C85: =Maps!$F$13 -> Crystals | D85: =Factions!$C$13 -> Minerals | E85: =IF(D85=C85,Factions!$D$13,D85) -> Minerals | F85: =IF(D85=C85,"SWAPPED","-") -> - | G85: =IF(AND(C85<>"Flowers",E85<>"Flowers"),"Flowers",IF(AND(C85<>"Crystals",E85<>"Crystals"),"Crystals","Minerals")) -> Flowers | H85: =IF(OR(C85=E85,C85=G85,E85=G85),"BROKEN","ok") -> ok
A87: Swapped? = SWAPPED on the 9 pairings (one per map) where the faction's premium collided with the map's primary.
A88: Valid? must read 'ok' on all 81 rows. A single BROKEN means two roles landed on the same resource and a wave decision has died.
A89: This sheet is the reason Premium_Secondary exists. Without it, 9 of 81 pairings have no quest resource at all.

Sheet Tech_Tree
A1: Loyalty Tech Tree — 3 unlocks per faction, 27 total
A2: Loyalty with a faction unlocks THAT faction's tech for YOUR use. Rivals mean you cannot have it all.
A4: Faction | B4: Rival | C4: T1 Unit @ | D4: T2 Structure @ | E4: T3 Base Upgrade @ | F4: Total Loyalty To Max | G4: Notes
A5: =Factions!$B$5 -> Faction_01 | B5: =Factions!$E$5 -> 2 | C5: =Global_Params!$B$35 -> 100 | D5: =Global_Params!$B$36 -> 260 | E5: =Global_Params!$B$37 -> 520 | F5: =E5 -> 520 | G5: One unit, one structure, one base upgrade. Thresholds are cumulative loyalty, not spent.
A6: =Factions!$B$6 -> Faction_02 | B6: =Factions!$E$6 -> 1 | C6: =Global_Params!$B$35 -> 100 | D6: =Global_Params!$B$36 -> 260 | E6: =Global_Params!$B$37 -> 520 | F6: =E6 -> 520 | G6: One unit, one structure, one base upgrade. Thresholds are cumulative loyalty, not spent.
A7: =Factions!$B$7 -> Faction_03 | B7: =Factions!$E$7 -> 4 | C7: =Global_Params!$B$35 -> 100 | D7: =Global_Params!$B$36 -> 260 | E7: =Global_Params!$B$37 -> 520 | F7: =E7 -> 520 | G7: One unit, one structure, one base upgrade. Thresholds are cumulative loyalty, not spent.
A8: =Factions!$B$8 -> Faction_04 | B8: =Factions!$E$8 -> 3 | C8: =Global_Params!$B$35 -> 100 | D8: =Global_Params!$B$36 -> 260 | E8: =Global_Params!$B$37 -> 520 | F8: =E8 -> 520 | G8: One unit, one structure, one base upgrade. Thresholds are cumulative loyalty, not spent.
A9: =Factions!$B$9 -> Faction_05 | B9: =Factions!$E$9 -> 6 | C9: =Global_Params!$B$35 -> 100 | D9: =Global_Params!$B$36 -> 260 | E9: =Global_Params!$B$37 -> 520 | F9: =E9 -> 520 | G9: One unit, one structure, one base upgrade. Thresholds are cumulative loyalty, not spent.
A10: =Factions!$B$10 -> Faction_06 | B10: =Factions!$E$10 -> 5 | C10: =Global_Params!$B$35 -> 100 | D10: =Global_Params!$B$36 -> 260 | E10: =Global_Params!$B$37 -> 520 | F10: =E10 -> 520 | G10: One unit, one structure, one base upgrade. Thresholds are cumulative loyalty, not spent.
A11: =Factions!$B$11 -> Faction_07 | B11: =Factions!$E$11 -> 8 | C11: =Global_Params!$B$35 -> 100 | D11: =Global_Params!$B$36 -> 260 | E11: =Global_Params!$B$37 -> 520 | F11: =E11 -> 520 | G11: One unit, one structure, one base upgrade. Thresholds are cumulative loyalty, not spent.
A12: =Factions!$B$12 -> Faction_08 | B12: =Factions!$E$12 -> 7 | C12: =Global_Params!$B$35 -> 100 | D12: =Global_Params!$B$36 -> 260 | E12: =Global_Params!$B$37 -> 520 | F12: =E12 -> 520 | G12: One unit, one structure, one base upgrade. Thresholds are cumulative loyalty, not spent.
A13: =Factions!$B$13 -> Faction_09 | B13: =Factions!$E$13 -> none | C13: =Global_Params!$B$35 -> 100 | D13: =Global_Params!$B$36 -> 260 | E13: =Global_Params!$B$37 -> 520 | F13: =E13 -> 520 | G13: One unit, one structure, one base upgrade. Thresholds are cumulative loyalty, not spent.
A15: CAMPAIGN LOYALTY BUDGET
A16: Total loyalty available (all 9 maps, all quest nodes) | B16: =SUM(Wave_Table!$Y$5:$Y$76) -> 1270 | C16: One perfect campaign pass, every quest node harvested.
A17: Loyalty to max ALL 9 factions | B17: =9*Global_Params!$B$37 -> 4680 | C17: Ignoring rival penalties.
A18: Can a perfect run max everything? | B18: =IF(B16>=B17,"YES — TOO GENEROUS","NO — good") -> NO — good | C18: Must read NO. Scarcity is what makes the rival choice mean anything.
A20: RIVAL PENALTY: loyalty gained with a faction is lost with its rival at the Rival_Penalty rate (default 0.5).
A21: So courting faction 01 actively burns your standing with 02. Four reciprocal pairs; faction 09 is unaligned.
A22: CONSEQUENCE: a player can realistically max one side of the rivalry map, never both. That IS the build choice.
A23: Faction 09 has no rival, so it is the only faction whose tech is free of opportunity cost. Price it accordingly.
A24: Quest_Giver_Faction (Maps sheet) decides WHOSE loyalty a map's quest resource earns — so the campaign order
A25: determines which factions the player can even court. Reordering the maps reorders the meta. Handle with care.

Sheet Quest_Contract
A1: The Quest Contract — accept, fail, or refuse
A2: Offered in the PRE-MATCH dialog, before the map is seen. There is NO neutral option: every map, you either serve a faction or you spite them.
A4: Outcome | B4: Loyalty: Giver | C4: Loyalty: Rival | D4: Tempo Cost | E4: What it means
A5: ACCEPT & FULFIL | B5: + Loyalty_Per_Node x nodes | C5: - 50% of the gain | D5: HIGH | E5: You hauled to the far edge, wave after wave, and paid for it in time bonus.
A6: ACCEPT & FAIL | B6: partial gain - Broken_Promise_Penalty | C6: - 50% of the partial gain | D6: MEDIUM | E6: You took the contract and came up short. WORSE than never taking it. Overpromising must sting.
A7: DECLINE | B7: - Decline_Cost | C7: + 50% of Decline_Cost | D7: NONE | E7: Free. You keep every second of the time bonus. But you have made an enemy and pleased their enemy.
A9: WORKED EXAMPLE
A10: Map_ID | B10: 5 | E10: Which map's contract.
A11: Quest_Nodes_On_Map | B11: 24 | E11: Sum of Wave_Table quest nodes for this map (waves 5-8).
A12: Nodes_Harvested | B12: 18 | E12: Player choice. The only lever they have.
A13: Contract_Accepted? | B13: YES | E13: YES or NO. Declared in the pre-match dialog.
A14: Giver_Faction | B14: {=INDEX(Maps!$J$5:$J$13,MATCH($B$10,Maps!$A$5:$A$13,0))} -> 9 | E14: From Maps.
A15: Rival_Faction | B15: {=INDEX(Factions!$E$5:$E$13,MATCH(B14,Factions!$A$5:$A$13,0))} -> none | E15: 'none' = unaligned.
A16: Fulfilment_Rate | B16: =IF($B$11=0,0,$B$12/$B$11) -> 0.75 | E16: Share of the map's quest nodes harvested.
A17: Contract_Status | B17: =IF($B$13="NO","DECLINED",IF(B16>=Global_Params!$B$41,"FULFILLED","BROKEN")) -> FULFILLED | E17: Three states. BROKEN is the one that hurts.
A19: RESULT
A20: Loyalty_With_Giver | B20: =IF($B$17="DECLINED",-Global_Params!$B$39,IF($B$17="FULFILLED",$B$12*Global_Params!$B$33,$B$12*Global_Params!$B$33-Global_Params!$B$42)) -> 180 | E20: Refusing costs a little. Accepting and failing can cost MORE than refusing.
A21: Loyalty_With_Rival | B21: =IF(B15="none",0,IF($B$17="DECLINED",ROUND(Global_Params!$B$39*Global_Params!$B$40,0),-ROUND(MAX(0,$B$20)*Global_Params!$B$34,0))) -> 0 | E21: REFUSING A FACTION PLEASES ITS RIVAL. This is what makes the system zero-sum.
A23: WHY THERE IS NO NEUTRAL OPTION:
A24: Before this rule, a player targeting faction 01 simply never harvested faction 02's quest. Skipping was FREE —
A25: it even improved their time bonus. The rival penalty had no teeth; it just told you which maps to ignore.
A27: Now every map forces a declaration. Serve the giver (and burn their rival), or refuse (and feed their rival).
A28: You cannot abstain. Loyalty is a stance, not a stockpile.
A30: THE TRADE THIS CREATES — and it is the point of the whole system:
A31: DEPTH build: declines often -> keeps the time bonus -> MORE GOLD, fewer unlocks, 2 base upgrades.
A32: BREADTH build: accepts often -> hauls to the far edge -> LESS GOLD, more unlocks, no base upgrades.
A33: Gold and loyalty now push against each other. Before this, they ran on parallel rails and never met.
A35: BALANCE CONSTRAINT: Broken_Promise_Penalty (45) MUST exceed Decline_Cost (30).
A36: If it does not, a player accepts every contract and deliberately fails the cheap ones. Overpromising must
A37: cost more than an honest refusal, or the contract means nothing.
... A41: can build a tech tree purely by being unpleasant to everyone. That would be funny once, then broken.
